Workbook

Sheet 25.Q2
A1: 报价总价比价 (Q2 招标)
A2: Consignor | B2: Consignee | C2: POL | D2: POD | E2: Payer | F2: Contact | G2: Transport | H2: Volume/Q2 | I2: Rolig | J2: Geodis | K2: 凯福 | L2: 合力通 | M2: 宝优 | N2: 舫心 | O2: Superchain | P2: 睿弘 | Q2: DSV | R2: 华洋 | S2: 青岛中外运
A3: AI-Turkey | Turkey (Izmit) | Q2 招标
A4: SAI - 3 Gaobao Lake East Rd, Yubei, Chongqing | B4: AI Termal Sistemleri A.Ş., Kocaeli/Izmit | C4: SHA | D4: Izmit | E4: AITURKEY | F4: Dilek Elmaser Polat | G4: D2D | H4: 15 | I4: 7680 | J4: 6633 | L4: 6385 | M4: 7200 | N4: 5450 | O4: 6300 | P4: / | Q4: 6822
A5: AIMX | Mexico (Manzanillo) | Q2 招标
A6: AITH (Thailand) | B6: AIMX Manzanillo Port | C6: Laem Chabang | D6: MANZANILLO | E6: AIMX | G6: CIF | H6: 3 | I6: 2788 | J6: 2860 | K6: 3430 | N6: 2480 | O6: 3550 | P6: /
A7: DELTA ELECTRONICS (Thailand) | B7: AIMX Manzanillo Port | C7: Bangkok | D7: MANZANILLO | E7: AIMX | G7: CIF | H7: 19 | I7: 2688 | J7: 2860 | K7: 3430 | N7: 2480 | O7: 3800 | P7: /
A8: AINT - 666 Wenchang Rd | B8: AIMX Manzanillo Port | C8: SHA | D8: MANZANILLO | E8: AIMX | G8: CIF | H8: 21 | I8: 2803 | J8: 2420 | K8: 2530 | L8: 4060 | M8: 4626 | N8: 2260 | O8: 3550 | P8: 2800 | Q8: 2266
A9: Creative Components, India | B9: AIMX Manzanillo Port | C9: Nhava Sheva | D9: MANZANILLO | E9: AIMX | G9: CIF | H9: 18 | I9: 3863 | J9: 3080 | K9: 4000 | N9: 3100 | O9: 5200 | P9: /
A10: Dalian ABIC | B10: AIMX Manzanillo Port | C10: Dalian | D10: MANZANILLO | E10: AIMX | G10: CIF | H10: 12 | I10: 2483 | J10: 2530 | K10: 2200 | M10: 5226 | N10: 2180 | O10: 3900 | P10: / | Q10: 1921
A11: AIUS | USA (HOU / Detroit / Savanna) | Q2 招标
A12: AINT - 666 Wenchang Rd | B12: GTZ Warehouse, McAllen, TX | C12: SHA | D12: HOU | E12: AIUS | G12: D2D | H12: 6 | I12: 7245 | J12: 8334 | K12: 6030 | L12: 6960 | M12: 8276 | N12: 6145 | O12: 7300 | P12: 5600 | Q12: 6365 | R12: 8945
A13: AISH - 108 Chunguang Rd | B13: FTZ Metro Warehouse, MI | C13: SHA | D13: Detroit | E13: AIUS | G13: D2D | H13: 6 | I13: 6205 | J13: 5947 | K13: 7180 | L13: 7041 | M13: 7650 | N13: 5495 | O13: 7150 | P13: 5100 | Q13: 6915 | R13: 9561
A14: AITH (Thailand) | B14: AIUS Baxter, Winchester, TN | C14: Laem Chabang | D14: Savanna | E14: AIUS | G14: D2D | H14: 10 | I14: 6780 | J14: 3720 | K14: 6080 | N14: 6065 | O14: 7750 | P14: /
A15: AINT - 666 Wenchang Rd | B15: AIUS Baxter, Winchester, TN | C15: SHA | D15: Savanna | E15: AIUS | G15: D2D | H15: 8 | I15: 7055 | J15: 4895 | K15: 6030 | L15: 7560 | M15: 8111 | N15: 6145 | O15: 7200 | P15: 5900 | Q15: 6465 | R15: 10261
A16: AISH | Asia → SHA (inbound) | Q2 招标
A17: DELTA ELECTRONICS (Thailand) | B17: AINT - 666 Wenchang Rd | C17: Laemchabang | D17: SHA | E17: AISH | F17: Kevin | G17: D2D | H17: 15 | I17: 1715 | J17: 2053 | K17: 1650 | N17: 1850 | O17: 1790 | P17: /
A18: Woory Industrial, Korea | B18: AINT - 666 Wenchang Rd | C18: Incheon | D18: SHA | E18: AISH | F18: Kevin | G18: D2D | H18: 7 | I18: 1859 | J18: 1818 | K18: 1950 | N18: 1800 | O18: 1690 | P18: /
A19: AINT - 666 Wenchang Rd | B19: AI Termal Sistemleri A.Ş., Kocaeli/Izmit | C19: SHA | D19: Izmit | E19: AISH | F19: Kevin | G19: D2D | H19: 45 | I19: 4950 | J19: 5735 | L19: 5420 | M19: 6226 | N19: 4440 | O19: 4900 | P19: / | Q19: 5915
A20: AITH | Thailand (Laemchabang) | Q2 招标
A21: AITH (Thailand) | B21: AISK, Nitra, Slovakia | C21: Laem Chabang | D21: Koper | E21: AITH | F21: Pornsuda | G21: D2D | H21: 4 | I21: 5135 | J21: 6218 | K21: 6360 | N21: 8280 | O21: 6550 | P21: /
A22: AISH - 108 Chunguang Rd | B22: AITH, Chonburi Thailand | C22: SHA | D22: Laemchabang | E22: AITH | F22: Pornsuda | G22: D2D | H22: 3 | I22: 1870 | J22: 2833 | K22: 2330 | M22: 2426 | N22: 2360 | O22: 2400 | P22: 3400 | Q22: 2190
A23: Shanghai Huafon Aluminium | B23: AITH, Rayong Thailand | C23: SHA | D23: Laemchabang | E23: AITH | F23: Pornsuda | G23: D2D | H23: 12 | I23: 1895 | J23: 2833 | K23: 2330 | M23: 2300 | N23: 2360 | O23: 2400 | P23: 3400 | Q23: 2190
A24: Hyo Seong Electric (Tianjin) | B24: AITH, Chonburi Thailand | C24: Tianjin | D24: Laemchabang | E24: AITH | F24: Pornsuda | G24: D2D | H24: 3 | I24: 1870 | J24: 2908 | K24: 2350 | M24: 2550 | N24: 3550 | O24: 2800 | P24: / | Q24: 2121
A25: OSE Industries, Dubai | B25: AITH, Rayong Thailand | C25: Dubai | D25: Laemchabang | E25: AITH | F25: Pornsuda | G25: D2D | H25: 3 | I25: 1360 | J25: 2250 | N25: 2225 | O25: 3900 | P25: /
A26: AISK | Slovakia (Hamburg) | Q2 招标
A27: AINT - 666 Wenchang Rd | B27: AISK, Nitra, Slovakia | C27: SHA | D27: Koper | E27: AISK | F27: Bafrnec, Marcel | G27: D2D | H27: 3 | I27: 5110 | J27: 6108 | M27: 6026 | N27: 5560 | O27: 5700 | P27: / | Q27: 5315
A28: Creative Components, India | B28: AISK, Nitra, Slovakia | C28: India | D28: Koper | E28: AISK | F28: Bafrnec, Marcel | G28: D2D | H28: 1 | I28: 5330 | J28: 4540 | N28: 5500 | O28: 5700 | P28: /
A30: 仅海运费比价 (Q2 招标)
A31: Consignor | B31: Consignee | C31: POL | D31: POD | E31: Payer | F31: Contact | G31: Transport | H31: Volume/Q2 | I31: Rolig | J31: Geodis | K31: 凯福 | L31: 合力通 | M31: 宝优 | N31: 舫心 | O31: Superchain | P31: 睿弘 | Q31: DSV | R31: 华洋 | S31: 青岛中外运
A32: AI-Turkey | Turkey (Izmit) | Q2 招标
A33: SAI - 3 Gaobao Lake East Rd, Yubei, Chongqing | B33: AI Termal Sistemleri A.Ş., Kocaeli/Izmit | C33: SHA | D33: Izmit | E33: AITURKEY | G33: D2D | H33: 15 | I33: 3200 | J33: 4950 | L33: 4475 | M33: 4150 | N33: 3700 | O33: 4550 | P33: / | Q33: 4200
A34: AIMX | Mexico (Manzanillo) | Q2 招标
A35: AITH (Thailand) | B35: AIMX Manzanillo Port | C35: Laem Chabang | D35: MANZANILLO | E35: AIMX | G35: CIF | H35: 3 | I35: 2000 | J35: 2860 | K35: 2750 | N35: 1800 | O35: 2465 | P35: /
A36: DELTA ELECTRONICS (Thailand) | B36: AIMX Manzanillo Port | C36: Bangkok | D36: MANZANILLO | E36: AIMX | G36: CIF | H36: 19 | I36: 1900 | J36: 2860 | K36: 2750 | N36: 1800 | O36: 2685 | P36: /
A37: AINT - 666 Wenchang Rd | B37: AIMX Manzanillo Port | C37: SHA | D37: MANZANILLO | E37: AIMX | G37: CIF | H37: 21 | I37: 1700 | J37: 2420 | K37: 1650 | L37: 3200 | M37: 2500 | N37: 1500 | O37: 2750 | P37: 1900 | Q37: 1300
A38: Creative Components, India | B38: AIMX Manzanillo Port | C38: Nhava Sheva | D38: MANZANILLO | E38: AIMX | G38: CIF | H38: 18 | I38: 2200 | J38: 3080 | K38: 2650 | N38: 2200 | O38: 3550 | P38: /
A39: Dalian ABIC | B39: AIMX Manzanillo Port | C39: Dalian | D39: MANZANILLO | E39: AIMX | G39: CIF | H39: 12 | I39: 1700 | J39: 2530 | K39: 1650 | M39: 3000 | N39: 1650 | O39: 3330 | P39: / | Q39: 1300
A40: AIUS | USA (HOU / Detroit / Savanna) | Q2 招标
A41: AINT - 666 Wenchang Rd | B41: GTZ Warehouse, McAllen, TX | C41: SHA | D41: HOU | E41: AIUS | G41: D2D | H41: 6 | I41: 3725 | J41: 4885 | K41: 2700 | L41: 3550 | M41: 4100 | N41: 2900 | O41: 4260 | P41: 2600 | Q41: 2700 | R41: 2900
A42: AISH - 108 Chunguang Rd | B42: FTZ Metro Warehouse, MI | C42: SHA | D42: Detroit | E42: AIUS | G42: D2D | H42: 6 | I42: 4500 | J42: 4576 | K42: 4350 | L42: 5400 | M42: 5600 | N42: 4200 | O42: 5725 | P42: 3100 | Q42: 5000 | R42: 4669
A43: AITH (Thailand) | B43: AIUS Baxter, Winchester, TN | C43: Laem Chabang | D43: Savanna | E43: AIUS | G43: D2D | H43: 10 | I43: 3525 | J43: 2130 | K43: 2950 | N43: 2800 | O43: 4165 | P43: /
A44: AINT - 666 Wenchang Rd | B44: AIUS Baxter, Winchester, TN | C44: SHA | D44: Savanna | E44: AIUS | G44: D2D | H44: 8 | I44: 3525 | J44: 2970 | K44: 2700 | L44: 3700 | M44: 4100 | N44: 2800 | O44: 3750 | P44: 2400 | Q44: 2700 | R44: 2900
A45: AISH | Asia → SHA (inbound) | Q2 招标
A46: DELTA ELECTRONICS (Thailand) | B46: AINT - 666 Wenchang Rd | C46: Laemchabang | D46: SHA | E46: AISH | G46: D2D | H46: 15 | I46: 140 | J46: 565 | K46: 100 | N46: 300 | O46: 280 | P46: /
A47: Woory Industrial, Korea | B47: AINT - 666 Wenchang Rd | C47: Incheon | D47: SHA | E47: AISH | G47: D2D | H47: 7 | I47: 210 | J47: 100 | K47: 150 | N47: 150 | O47: 330 | P47: /
A48: AINT - 666 Wenchang Rd | B48: AI Termal Sistemleri A.Ş., Kocaeli/Izmit | C48: SHA | D48: Izmit | E48: AISH | G48: D2D | H48: 45 | I48: 3200 | J48: 3850 | L48: 3400 | M48: 4150 | N48: 2700 | O48: 3100 | P48: / | Q48: 3100
A49: AITH | Thailand (Laemchabang) | Q2 招标
A50: AITH (Thailand) | B50: AISK, Nitra, Slovakia | C50: Laem Chabang | D50: Koper | E50: AITH | G50: D2D | H50: 4 | I50: 2590 | J50: 4150 | K50: 3700 | N50: 5900 | O50: 4000 | P50: /
A51: AISH - 108 Chunguang Rd | B51: AITH, Chonburi Thailand | C51: SHA | D51: Laemchabang | E51: AITH | G51: D2D | H51: 3 | I51: 800 | J51: 1683 | K51: 800 | M51: 900 | N51: 850 | O51: 1230 | P51: 1100 | Q51: 850
A52: Shanghai Huafon Aluminium | B52: AITH, Rayong Thailand | C52: SHA | D52: Laemchabang | E52: AITH | G52: D2D | H52: 12 | I52: 800 | J52: 1683 | K52: 800 | M52: 900 | N52: 850 | O52: 1210 | P52: 1100 | Q52: 850
A53: Hyo Seong Electric (Tianjin) | B53: AITH, Chonburi Thailand | C53: Tianjin | D53: Laemchabang | E53: AITH | G53: D2D | H53: 3 | I53: 800 | J53: 1683 | K53: 1100 | M53: 900 | N53: 950 | O53: 1430 | P53: / | Q53: 850
A54: OSE Industries, Dubai | B54: AITH, Rayong Thailand | C54: Dubai | D54: Laemchabang | E54: AITH | G54: D2D | H54: 3 | I54: 180 | J54: 350 | N54: 450 | O54: 1900 | P54: /
A55: AISK | Slovakia (Hamburg) | Q2 招标
A56: AINT - 666 Wenchang Rd | B56: AISK, Nitra, Slovakia | C56: SHA | D56: Koper | E56: AISK | G56: D2D | H56: 3 | I56: 2290 | J56: 3705 | M56: 4200 | N56: 3100 | O56: 3325 | P56: / | Q56: 2400
A57: Creative Components, India | B57: AISK, Nitra, Slovakia | C57: India | D57: Koper | E57: AISK | G57: D2D | H57: 1 | I57: 1950 | J57: 2200 | N57: 2900 | O57: 2510 | P57: /

Sheet 25.7-8月
A1: Lane | B1: Consignor | C1: Consignee | D1: POL | E1: POD | F1: Incoterm | G1: Q3 HQ40 Demand | H1: Booking | I1: Doc | J1: THC | K1: Loading | L1: Customs | M1: B/L | N1: Local Subtotal | O1: Dest Subtotal | P1: Sea Freight | Q1: Transit Time | R1: Total (USD) | S1: Winning Forwarder
A2: AI-Turkey | Turkey (Izmit) | 2 条航线 | Q3 季需求 50 HQ40
A3: SHA-Izmit | B3: AINT - 666 Wenchang Rd, Tongzhou, Nantong | C3: AI Termal Sistemleri A.Ş., Kocaeli/Izmit | D3: SHA | E3: Izmit | F3: DAP | G3: 35 | H3: 70 | I3: 70 | J3: 140 | K3: 400 | L3: 10 | M3: 70 | N3: =SUM(H3:M3) -> 760 | O3: 950 | P3: 3480 | Q3: — | R3: =IFERROR(N3+IF(ISNUMBER(O3),O3,0)+IF(ISNUMBER(P3),P3,0),"") -> 5190 | S3: Bestunit
A4: SAI-Izmit | B4: SAI - 3 Gaobao Lake East Rd, Yubei, Chongqing | C4: AI Termal Sistemleri A.Ş., Kocaeli/Izmit | D4: SHA | E4: Izmit | F4: EXW | G4: 15 | H4: 70 | I4: 70 | J4: 140 | K4: 200 | L4: 20 | M4: 50 | N4: =SUM(H4:M4) -> 550 | O4: 950 | P4: 3480 | Q4: — | R4: =IFERROR(N4+IF(ISNUMBER(O4),O4,0)+IF(ISNUMBER(P4),P4,0),"") -> 4980 | S4: Bestunit
A5: AIMX | Mexico (Manzanillo) | 12 条航线 | Q3 季需求 69 HQ40
A6: Laem-Manzanillo | B6: AITH (Thailand) | C6: AIMX Manzanillo Port | D6: Laem Chabang | E6: MANZANILLO | F6: CIF | G6: 8 | H6: 70 | I6: 50 | J6: 260 | K6: 250 | L6: 90 | M6: 80 | N6: =SUM(H6:M6) -> 800 | O6: N/A | P6: 3500 | Q6: — | R6: =IFERROR(N6+IF(ISNUMBER(O6),O6,0)+IF(ISNUMBER(P6),P6,0),"") -> 4300 | S6: Kaifu
A7: Bangkok-Manzanillo | B7: DELTA ELECTRONICS (Thailand) | C7: AIMX Manzanillo Port | D7: Bangkok | E7: MANZANILLO | F7: CIF | G7: 15 | H7: 70 | I7: 50 | J7: 260 | K7: 325 | L7: 90 | M7: 80 | N7: =SUM(H7:M7) -> 875 | O7: N/A | P7: 3500 | Q7: — | R7: =IFERROR(N7+IF(ISNUMBER(O7),O7,0)+IF(ISNUMBER(P7),P7,0),"") -> 4375 | S7: Kaifu
A8: Nhava-Manzanillo | B8: Creative Component, Pune, India | C8: AIMX Manzanillo Port | D8: Nhava Sheva | E8: MANZANILLO | F8: CIF | G8: 8 | H8: 70 | I8: 80 | J8: 160 | K8: 1000 | L8: 50 | M8: 75 | N8: =SUM(H8:M8) -> 1435 | O8: N/A | P8: 2500 | Q8: — | R8: =IFERROR(N8+IF(ISNUMBER(O8),O8,0)+IF(ISNUMBER(P8),P8,0),"") -> 3935 | S8: Kaifu
A9: Dalian-Manzanillo | B9: Dalian Aibike Air Conditioning Parts | C9: AIMX Manzanillo Port | D9: Dalian | E9: MANZANILLO | F9: CIF | G9: 4 | H9: 70 | I9: 70 | J9: 145 | K9: 200 | L9: 15 | M9: 50 | N9: =SUM(H9:M9) -> 550 | O9: N/A | P9: 3000 | Q9: — | R9: =IFERROR(N9+IF(ISNUMBER(O9),O9,0)+IF(ISNUMBER(P9),P9,0),"") -> 3550 | S9: Superchain
A10: Incheon-Manzanillo | B10: Woory Industrial, Korea | C10: AIMX Manzanillo Port | D10: Incheon | E10: MANZANILLO | F10: CIF | G10: 8 | H10: 70 | I10: 35 | J10: 145 | K10: 350 | L10: 150 | M10: 50 | N10: =SUM(H10:M10) -> 800 | O10: N/A | P10: 2700 | Q10: — | R10: =IFERROR(N10+IF(ISNUMBER(O10),O10,0)+IF(ISNUMBER(P10),P10,0),"") -> 3500 | S10: Superchain
A11: SHA-Manzanillo (Bokang) | B11: Bokang (FOB Shanghai) | C11: AIMX Manzanillo Port | D11: SHA | E11: MANZANILLO | F11: CIF | G11: 3 | H11: 70 | I11: 70 | J11: 145 | K11: 50 | L11: 15 | M11: 60 | N11: =SUM(H11:M11) -> 410 | O11: N/A | P11: 2700 | Q11: — | R11: =IFERROR(N11+IF(ISNUMBER(O11),O11,0)+IF(ISNUMBER(P11),P11,0),"") -> 3110 | S11: Superchain
A12: SHA-Manzanillo (Ganglong) | B12: Ganglong (EXW Shanghai) | C12: AIMX Manzanillo Port | D12: SHA | E12: MANZANILLO | F12: CIF | G12: 3 | H12: 70 | I12: 70 | J12: 145 | K12: 230 | L12: 15 | M12: 60 | N12: =SUM(H12:M12) -> 590 | O12: N/A | P12: 2700 | Q12: — | R12: =IFERROR(N12+IF(ISNUMBER(O12),O12,0)+IF(ISNUMBER(P12),P12,0),"") -> 3290 | S12: Superchain
A13: SHA-Manzanillo (PMC) | B13: PMC (EXW Nanjing) | C13: AIMX Manzanillo Port | D13: SHA | E13: MANZANILLO | F13: CIF | G13: 3 | H13: 70 | I13: 70 | J13: 145 | K13: 550 | L13: 15 | M13: 60 | N13: =SUM(H13:M13) -> 910 | O13: N/A | P13: 2700 | Q13: — | R13: =IFERROR(N13+IF(ISNUMBER(O13),O13,0)+IF(ISNUMBER(P13),P13,0),"") -> 3610 | S13: Superchain
A14: SHA-Manzanillo (Boling) | B14: Chongqing Boling (EXW Chongqing) | C14: AIMX Manzanillo Port | D14: SHA | E14: MANZANILLO | F14: CIF | G14: 3 | H14: 70 | I14: 70 | J14: 145 | K14: 1550 | L14: 15 | M14: 60 | N14: =SUM(H14:M14) -> 1910 | O14: N/A | P14: 2700 | Q14: — | R14: =IFERROR(N14+IF(ISNUMBER(O14),O14,0)+IF(ISNUMBER(P14),P14,0),"") -> 4610 | S14: Superchain
A15: SHA-Manzanillo (Huafeng) | B15: Huafeng (EXW Shanghai) | C15: AIMX Manzanillo Port | D15: SHA | E15: MANZANILLO | F15: CIF | G15: 3 | H15: 70 | I15: 70 | J15: 145 | K15: 250 | L15: 15 | M15: 60 | N15: =SUM(H15:M15) -> 610 | O15: N/A | P15: 2700 | Q15: — | R15: =IFERROR(N15+IF(ISNUMBER(O15),O15,0)+IF(ISNUMBER(P15),P15,0),"") -> 3310 | S15: Superchain
A16: SHA-Manzanillo (Xinrui) | B16: Xinrui (EXW Shaoxing) | C16: AIMX Manzanillo Port | D16: SHA | E16: MANZANILLO | F16: CIF | G16: 3 | H16: 70 | I16: 70 | J16: 145 | K16: 500 | L16: 15 | M16: 60 | N16: =SUM(H16:M16) -> 860 | O16: N/A | P16: 2700 | Q16: — | R16: =IFERROR(N16+IF(ISNUMBER(O16),O16,0)+IF(ISNUMBER(P16),P16,0),"") -> 3560 | S16: Superchain
A17: SHA-Manzanillo (AITD) | B17: AITD (EXW Nantong) | C17: AIMX Manzanillo Port | D17: SHA | E17: MANZANILLO | F17: CIF | G17: 8 | H17: 70 | I17: 70 | J17: 145 | K17: 350 | L17: 15 | M17: 60 | O17: N/A | P17: 2700 | Q17: — | S17: Superchain
A18: AIUS | USA (HOU / Detroit / Savanna) | 5 条航线 | Q3 季需求 31 HQ40
A19: SHA-HOU | B19: AINT - 666 Wenchang Rd, Tongzhou, Nantong | C19: GTZ Warehouse, McAllen, TX | D19: SHA | E19: HOU | F19: DAP | G19: 6 | H19: 70 | I19: 70 | J19: 140 | K19: 400 | L19: 10 | M19: 70 | N19: =SUM(H19:M19) -> 760 | O19: 2685 | P19: 4600 | Q19: — | R19: =IFERROR(N19+IF(ISNUMBER(O19),O19,0)+IF(ISNUMBER(P19),P19,0),"") -> 8045 | S19: Bestunit
A20: SHA-Detroit | B20: AISH - 108 Chunguang Rd, Minhang, Shanghai | C20: FTZ Metro Warehouse, Highland Park, MI | D20: SHA | E20: Detroit | F20: DAP | G20: 6 | H20: 70 | I20: 70 | J20: 140 | K20: 250 | L20: 10 | M20: 70 | N20: =SUM(H20:M20) -> 610 | O20: 885 | P20: 5000 | Q20: — | R20: =IFERROR(N20+IF(ISNUMBER(O20),O20,0)+IF(ISNUMBER(P20),P20,0),"") -> 6495 | S20: Bestunit
A21: Laem-Savanna | B21: AITH (Thailand) | C21: AIUS Baxter, Winchester, TN | D21: Laem Chabang | E21: Savanna | F21: DAP | G21: 1 | H21: 70 | I21: 70 | J21: 140 | K21: 300 | L21: 30 | M21: 70 | N21: =SUM(H21:M21) -> 680 | O21: 2785 | P21: 6182 | Q21: — | R21: =IFERROR(N21+IF(ISNUMBER(O21),O21,0)+IF(ISNUMBER(P21),P21,0),"") -> 9647 | S21: Bestunit
A22: Nhava-Savanna | B22: Divine & Creative, India | C22: AIUS Baxter, Winchester, TN | D22: Nhava Sheva | E22: Savanna | F22: DAP | G22: 10 | H22: 70 | I22: 80 | J22: 160 | K22: 1000 | L22: 50 | M22: 75 | N22: =SUM(H22:M22) -> 1435 | O22: 2785 | P22: 4870 | Q22: — | R22: =IFERROR(N22+IF(ISNUMBER(O22),O22,0)+IF(ISNUMBER(P22),P22,0),"") -> 9090 | S22: Bestunit
A23: SHA-Savanna | B23: AINT - 666 Wenchang Rd, Tongzhou, Nantong | C23: AIUS Baxter, Winchester, TN | D23: SHA | E23: Savanna | F23: DAP | G23: 8 | H23: 70 | I23: 70 | J23: 140 | K23: 400 | L23: 10 | M23: 70 | O23: 2785 | P23: 4932 | Q23: — | S23: Bestunit
A24: AISH | Asia → SHA (inbound) | 2 条航线 | Q3 季需求 22 HQ40
A25: Laem-SHA | B25: DELTA ELECTRONICS (Thailand) | C25: AINT - 666 Wenchang Rd, Tongzhou, Nantong | D25: Laem Chabang | E25: SHA | F25: DAP | G25: 15 | H25: 70 | I25: 50 | J25: 260 | K25: 325 | L25: 90 | M25: 80 | N25: =SUM(H25:M25) -> 875 | O25: 600 | P25: 30 | Q25: — | R25: =IFERROR(N25+IF(ISNUMBER(O25),O25,0)+IF(ISNUMBER(P25),P25,0),"") -> 1505 | S25: Superchain
A26: Incheon-SHA | B26: Woory Industrial, Korea | C26: AINT - 666 Wenchang Rd, Tongzhou, Nantong | D26: Incheon | E26: SHA | F26: DAP | G26: 7 | H26: 70 | I26: 35 | J26: 145 | K26: 350 | L26: 150 | M26: 50 | O26: 600 | P26: 1 | Q26: — | S26: Superchain
A27: AITH | Thailand (Laemchabang) | 4 条航线 | Q3 季需求 21 HQ40
A28: SHA-Laem | B28: AISH - 108 Chunguang Rd, Minhang, Shanghai | C28: AITH, Chonburi 20230 Thailand | D28: SHA | E28: Laemchabang | F28: DAP | G28: 3 | H28: 70 | I28: 70 | J28: 140 | K28: 250 | L28: 10 | M28: 70 | N28: =SUM(H28:M28) -> 610 | O28: 800 | P28: 440 | Q28: — | R28: =IFERROR(N28+IF(ISNUMBER(O28),O28,0)+IF(ISNUMBER(P28),P28,0),"") -> 1850 | S28: Geodis (泰本地 $1725)
A29: SHA-Laem (Huafon) | B29: Shanghai Huafon Aluminium Corp. | C29: AITH, Rayong 21140 Thailand | D29: SHA | E29: Laemchabang | F29: DAP | G29: 12 | H29: 70 | I29: 70 | J29: 140 | K29: 250 | L29: 10 | M29: 70 | N29: =SUM(H29:M29) -> 610 | O29: 800 | P29: 440 | Q29: — | R29: =IFERROR(N29+IF(ISNUMBER(O29),O29,0)+IF(ISNUMBER(P29),P29,0),"") -> 1850 | S29: Geodis (泰本地 $1717)
A30: Tianjin-Laem | B30: Hyo Seong Electric (Tianjin) | C30: AITH, Chonburi 20230 Thailand | D30: Tianjin | E30: Laemchabang | F30: DAP | G30: 3 | H30: 70 | I30: 70 | J30: 140 | K30: 420 | L30: 30 | M30: 70 | N30: =SUM(H30:M30) -> 800 | O30: 800 | P30: 440 | Q30: — | R30: =IFERROR(N30+IF(ISNUMBER(O30),O30,0)+IF(ISNUMBER(P30),P30,0),"") -> 2040 | S30: Geodis (泰本地 $2062)
A31: Dubai-Laem | B31: OSE Industries LLC, Dubai | C31: AITH, Rayong 21140 Thailand | D31: Dubai | E31: Laemchabang | F31: DAP | G31: 3 | H31: 70 | I31: 70 | J31: 140 | K31: 420 | L31: 30 | M31: 70 | N31: =SUM(H31:M31) -> 800 | O31: 800 | P31: 150 | Q31: — | R31: =IFERROR(N31+IF(ISNUMBER(O31),O31,0)+IF(ISNUMBER(P31),P31,0),"") -> 1750 | S31: Geodis (泰本地 $1956)
A32: AITH-AISK (泰国本地) | B32: AITH | C32: AISK | D32: AITH | E32: AISK | F32: DAP | Q32: — | S32: Cargo (泰本地 $6000)
A33: AISK | Slovakia (Hamburg) | 3 条航线 | Q3 季需求 15 HQ40
A34: SHA-Koper | B34: AINT - 666 Wenchang Rd, Tongzhou, Nantong | C34: AISK, Nitra, Slovakia | D34: SHA | E34: Koper | F34: DAP | G34: 3 | H34: 70 | I34: 70 | J34: 140 | K34: 400 | L34: 10 | M34: 70 | N34: =SUM(H34:M34) -> 760 | O34: 2200 | P34: 2680 | Q34: — | R34: =IFERROR(N34+IF(ISNUMBER(O34),O34,0)+IF(ISNUMBER(P34),P34,0),"") -> 5640 | S34: Rohlig
A35: Nhava-Hamburg | B35: Divine Tooling | C35: AISK, Nitra, Slovakia | D35: Nhava Sheva | E35: Hamburg | F35: DAP | G35: 10 | H35: 70 | I35: 70 | J35: 140 | K35: 300 | L35: 250 | M35: 70 | N35: =SUM(H35:M35) -> 900 | O35: 2200 | P35: 1995 | Q35: — | R35: =IFERROR(N35+IF(ISNUMBER(O35),O35,0)+IF(ISNUMBER(P35),P35,0),"") -> 5095 | S35: Rohlig
A36: Nhava-Koper | B36: Delta Electronics | C36: AISK, Nitra, Slovakia | D36: Nhava Sheva | E36: Koper | F36: DAP | G36: 2 | H36: 70 | I36: 70 | J36: 140 | K36: 300 | L36: 30 | M36: 70 | N36: =SUM(H36:M36) -> 680 | O36: 2200 | P36: 2785 | Q36: — | R36: =IFERROR(N36+IF(ISNUMBER(O36),O36,0)+IF(ISNUMBER(P36),P36,0),"") -> 5665 | S36: Rohlig

Sheet 25.9月
A1: Lane | B1: Consignor | C1: Consignee | D1: POL | E1: POD | F1: Incoterm | G1: HQ40 Demand | H1: Booking | I1: Doc | J1: THC | K1: Loading | L1: Customs | M1: B/L | N1: Local Subtotal | O1: Dest Subtotal | P1: Sea Freight | Q1: Transit Time | R1: Total (USD) | S1: Winning Forwarder
A2: AI-Turkey | Turkey (Izmit) | 2 条航线 | 月需求 26 HQ40
A3: SHA-Izmit | B3: AINT - 666 Wenchang Rd, Tongzhou, Nantong | C3: AI Termal Sistemleri A.Ş., İstanbul | D3: SHA | E3: Izmit | F3: DAP | G3: 22 | H3: 70 | I3: 70 | J3: 140 | K3: 400 | L3: 10 | M3: 70 | N3: =SUM(H3:M3) -> 760 | O3: 950 | P3: 2800 | Q3: 8-10 wks | R3: =IFERROR(N3+IF(ISNUMBER(O3),O3,0)+IF(ISNUMBER(P3),P3,0),"") -> 4510 | S3: 合力通
A4: SAI-Izmit | B4: SAI - 3 Gaobao Lake East Rd, Yubei, Chongqing | C4: AI Termal Sistemleri A.Ş., İstanbul | D4: SHA | E4: Izmit | F4: EXW | G4: 4 | H4: 70 | I4: 70 | J4: 140 | K4: 200 | L4: 20 | M4: 50 | N4: =SUM(H4:M4) -> 550 | O4: 950 | P4: 4294 | Q4: — | R4: =IFERROR(N4+IF(ISNUMBER(O4),O4,0)+IF(ISNUMBER(P4),P4,0),"") -> 5794 | S4: Freetrans
A5: AIMX | Mexico (Manzanillo) | 15 条航线 | 月需求 35 HQ40
A6: Laem-Manzanillo | B6: AITH | C6: Puebla + Saltillo | D6: Laemchabang | E6: MANZANILLO | F6: CIF | G6: 11 | H6: 70 | I6: 50 | J6: 260 | K6: 250 | L6: 90 | M6: 80 | N6: =SUM(H6:M6) -> 800 | O6: N/A | P6: 3050 | Q6: — | R6: =IFERROR(N6+IF(ISNUMBER(O6),O6,0)+IF(ISNUMBER(P6),P6,0),"") -> 3850 | S6: Freetrans
A7: Bangkok-Manzanillo | B7: DELTA | C7: Saltillo | D7: Bangkok | E7: MANZANILLO | F7: CIF | G7: 3 | H7: 70 | I7: 50 | J7: 260 | K7: 325 | L7: 90 | M7: 80 | N7: =SUM(H7:M7) -> 875 | O7: N/A | P7: 2995 | Q7: — | R7: =IFERROR(N7+IF(ISNUMBER(O7),O7,0)+IF(ISNUMBER(P7),P7,0),"") -> 3870 | S7: Freetrans
A8: Laem-Manzanillo (TNC) | B8: TNC | C8: Puebla | D8: Laemchabang | E8: MANZANILLO | F8: CIF | G8: 0.5 | H8: 70 | I8: 50 | J8: 260 | K8: 250 | L8: 90 | M8: 80 | N8: =SUM(H8:M8) -> 800 | O8: N/A | P8: 3200 | Q8: — | R8: =IFERROR(N8+IF(ISNUMBER(O8),O8,0)+IF(ISNUMBER(P8),P8,0),"") -> 4000 | S8: Freetrans/Kaifu
A9: Nhava-Manzanillo | B9: Creative Components | C9: Saltillo | D9: Nhava Sheva | E9: MANZANILLO | F9: CIF | G9: 2 | H9: 70 | I9: 80 | J9: 160 | K9: 1000 | L9: 50 | M9: 75 | N9: =SUM(H9:M9) -> 1435 | O9: N/A | P9: 2500 | Q9: — | R9: =IFERROR(N9+IF(ISNUMBER(O9),O9,0)+IF(ISNUMBER(P9),P9,0),"") -> 3935 | S9: Kaifu
A10: Incheon-Manzanillo | B10: WOORY | C10: Saltillo | D10: INCHEON | E10: MANZANILLO | F10: CIF | G10: 1 | H10: 70 | I10: 35 | J10: 145 | K10: 350 | L10: 150 | M10: 50 | N10: =SUM(H10:M10) -> 800 | O10: N/A | P10: 2800 | Q10: — | R10: =IFERROR(N10+IF(ISNUMBER(O10),O10,0)+IF(ISNUMBER(P10),P10,0),"") -> 3600 | S10: Kaifu
A11: SHA-Manzanillo (Chao Li) | B11: Jiangsu Chao Li | C11: Puebla | D11: SHA | E11: MANZANILLO | F11: CIF | G11: 2 | H11: 70 | I11: 70 | J11: 145 | K11: 550 | L11: 15 | M11: 60 | N11: =SUM(H11:M11) -> 910 | O11: N/A | P11: 2695 | Q11: — | R11: =IFERROR(N11+IF(ISNUMBER(O11),O11,0)+IF(ISNUMBER(P11),P11,0),"") -> 3605 | S11: Freetrans
A12: SHA-Manzanillo (Yangzhou) | B12: Yangzhou RSL | C12: Puebla | D12: SHA | E12: MANZANILLO | F12: CIF | G12: 1 | H12: 70 | I12: 70 | J12: 145 | K12: 550 | L12: 15 | M12: 60 | N12: =SUM(H12:M12) -> 910 | O12: N/A | P12: 2695 | Q12: — | R12: =IFERROR(N12+IF(ISNUMBER(O12),O12,0)+IF(ISNUMBER(P12),P12,0),"") -> 3605 | S12: Freetrans
A13: SHA-Manzanillo (Yuansheng) | B13: Zhejiang Yuansheng | C13: Puebla | D13: SHA | E13: MANZANILLO | F13: CIF | G13: 1 | H13: 70 | I13: 70 | J13: 145 | K13: 550 | L13: 15 | M13: 60 | N13: =SUM(H13:M13) -> 910 | O13: N/A | P13: 2695 | Q13: — | R13: =IFERROR(N13+IF(ISNUMBER(O13),O13,0)+IF(ISNUMBER(P13),P13,0),"") -> 3605 | S13: Freetrans
A14: SHA-Manzanillo (Huafon Coil) | B14: Shanghai Huafon Coil | C14: Puebla | D14: SHA | E14: MANZANILLO | F14: CIF | G14: 2 | H14: 70 | I14: 70 | J14: 145 | K14: 250 | L14: 15 | M14: 60 | N14: =SUM(H14:M14) -> 610 | O14: N/A | P14: 2695 | Q14: — | R14: =IFERROR(N14+IF(ISNUMBER(O14),O14,0)+IF(ISNUMBER(P14),P14,0),"") -> 3305 | S14: Freetrans
A15: SHA-Manzanillo (ABIC) | B15: Dalian ABIC | C15: Puebla | D15: SHA | E15: MANZANILLO | F15: CIF | G15: 2 | H15: 70 | I15: 70 | J15: 145 | K15: 200 | L15: 15 | M15: 50 | N15: =SUM(H15:M15) -> 550 | O15: N/A | P15: 2695 | Q15: — | R15: =IFERROR(N15+IF(ISNUMBER(O15),O15,0)+IF(ISNUMBER(P15),P15,0),"") -> 3245 | S15: Freetrans
A16: SHA-Manzanillo (Boling) | B16: Chongqing Boling | C16: Puebla | D16: SHA | E16: MANZANILLO | F16: CIF | G16: 0.5 | H16: 70 | I16: 70 | J16: 145 | K16: 1550 | L16: 15 | M16: 60 | N16: =SUM(H16:M16) -> 1910 | O16: N/A | P16: 2695 | Q16: — | R16: =IFERROR(N16+IF(ISNUMBER(O16),O16,0)+IF(ISNUMBER(P16),P16,0),"") -> 4605 | S16: Freetrans
A17: SHA-Manzanillo (AITD) | B17: AITD | C17: Saltillo | D17: SHA | E17: MANZANILLO | F17: CIF | G17: 4 | H17: 70 | I17: 70 | J17: 145 | K17: 350 | L17: 15 | M17: 60 | N17: =SUM(H17:M17) -> 710 | O17: N/A | P17: 2695 | Q17: — | R17: =IFERROR(N17+IF(ISNUMBER(O17),O17,0)+IF(ISNUMBER(P17),P17,0),"") -> 3405 | S17: Freetrans
... A20: SHA-Manzanillo (Shenda) | B20: Changsha Shenda | C20: Saltillo | D20: SHA | E20: MANZANILLO | F20: CIF | G20: 2 | H20: 70 | I20: 70 | J20: 145 | K20: 1500 | L20: 15 | M20: 60 | N20: =SUM(H20:M20) -> 1860 | O20: N/A | P20: 2695 | Q20: — | R20: =IFERROR(N20+IF(ISNUMBER(O20),O20,0)+IF(ISNUMBER(P20),P20,0),"") -> 4555 | S20: Freetrans
A21: AIUS | USA (HOU / Detroit / Savanna) | 5 条航线 | 月需求 8 HQ40
A22: SHA-HOU | B22: AINT - 666 Wenchang Rd, Tongzhou, Nantong | C22: GTZ WAREHOUSE LLC, McALLEN, TX | D22: SHA | E22: HOU | F22: EXW | G22: 2 | H22: 70 | I22: 70 | J22: 140 | K22: 400 | L22: 10 | M22: 70 | O22: 2685 | P22: 3485 | Q22: 8-10 wks | S22: Bestunit
A23: SHA-Detroit | B23: AISH - 108 Chunguang Rd, Minhang, Shanghai | C23: FTZ METRO WAREHOUSE, HIGHLAND PARK, MI | D23: SHA | E23: Detroit | F23: EXW | G23: 0 | H23: 70 | I23: 70 | J23: 140 | K23: 250 | L23: 10 | M23: 70 | N23: =SUM(H23:M23) -> 610 | O23: 885 | P23: 5935 | Q23: — | R23: =IFERROR(N23+IF(ISNUMBER(O23),O23,0)+IF(ISNUMBER(P23),P23,0),"") -> 7430 | S23: Bestunit
A24: Laem-Savanna | B24: AITH (Thailand) | C24: AIUS Baxter, Winchester, TN | D24: Laem Chabang | E24: Savanna | F24: EXW | G24: 0 | H24: 70 | I24: 70 | J24: 140 | K24: 300 | L24: 30 | M24: 70 | N24: =SUM(H24:M24) -> 680 | O24: 2785 | P24: 6200 | Q24: — | R24: =IFERROR(N24+IF(ISNUMBER(O24),O24,0)+IF(ISNUMBER(P24),P24,0),"") -> 9665 | S24: Bestunit
A25: Nhava-Savanna | B25: Divine & Creative (India) | C25: AIUS Baxter, Winchester, TN | D25: Nhava Sheva | E25: Savanna | F25: EXW | G25: 3 | H25: 70 | I25: 80 | J25: 160 | K25: 1000 | L25: 50 | M25: 75 | N25: =SUM(H25:M25) -> 1435 | O25: 2785 | P25: 6500 | Q25: — | R25: =IFERROR(N25+IF(ISNUMBER(O25),O25,0)+IF(ISNUMBER(P25),P25,0),"") -> 10720 | S25: Bestunit
A26: SHA-Savanna | B26: AINT - 666 Wenchang Rd, Tongzhou, Nantong | C26: AIUS Baxter, Winchester, TN | D26: SHA | E26: Savanna | F26: EXW | G26: 3 | H26: 70 | I26: 70 | J26: 140 | K26: 400 | L26: 10 | M26: 70 | N26: =SUM(H26:M26) -> 760 | O26: 2785 | P26: 4849 | Q26: — | R26: =IFERROR(N26+IF(ISNUMBER(O26),O26,0)+IF(ISNUMBER(P26),P26,0),"") -> 8394 | S26: Bestunit
A27: AISH | Asia → SHA (inbound) | 2 条航线 | 月需求 4 HQ40
A28: Bangkok-SHA | B28: DELTA ELECTRONICS (Thailand) | C28: AINT - 666 Wenchang Rd, Tongzhou, Nantong | D28: Bangkok | E28: SHA | F28: EXW | G28: 2 | H28: 70 | I28: 50 | J28: 260 | K28: 325 | L28: 90 | M28: 80 | O28: 600 | P28: 1 | Q28: <18 days | S28: Bestunit
A29: Incheon-SHA | B29: Woory Industrial, Korea | C29: AINT - 666 Wenchang Rd, Tongzhou, Nantong | D29: INCHEON | E29: SHA | F29: EXW | G29: 2 | H29: 70 | I29: 35 | J29: 145 | K29: 350 | L29: 150 | M29: 50 | N29: =SUM(H29:M29) -> 800 | O29: 600 | P29: 1 | Q29: <12 days | R29: =IFERROR(N29+IF(ISNUMBER(O29),O29,0)+IF(ISNUMBER(P29),P29,0),"") -> 1401 | S29: Bestunit/Superchain
A30: AITH | Thailand (Laemchabang) | 5 条航线 | 月需求 11 HQ40
A31: SHA-Laem | B31: AISH - 108 Chunguang Rd, Minhang, Shanghai | C31: AITH, Chonburi 20230 Thailand | D31: SHA | E31: Laemchabang | F31: EXW | G31: 1 | H31: 70 | I31: 70 | J31: 140 | K31: 250 | L31: 10 | M31: 70 | O31: 800 | P31: 490 | Q31: 15-20 days | S31: Rohlig
A32: SHA-Laem (Huafon) | B32: Shanghai Huafon Aluminium Corp. | C32: AITH, Rayong 21140 Thailand | D32: SHA | E32: Laemchabang | F32: EXW | G32: 3 | H32: 70 | I32: 70 | J32: 140 | K32: 250 | L32: 10 | M32: 70 | N32: =SUM(H32:M32) -> 610 | O32: 800 | P32: 490 | Q32: 15-20 days | R32: =IFERROR(N32+IF(ISNUMBER(O32),O32,0)+IF(ISNUMBER(P32),P32,0),"") -> 1900 | S32: Rohlig
A33: Tianjin-Laem | B33: Hyo Seong Electric (Tianjin) | C33: AITH, Chonburi 20230 Thailand | D33: Tianjin | E33: Laemchabang | F33: EXW | G33: 0.5 | H33: 70 | I33: 70 | J33: 140 | K33: 420 | L33: 30 | M33: 70 | N33: =SUM(H33:M33) -> 800 | O33: 800 | P33: 300 | Q33: 18-23 days | R33: =IFERROR(N33+IF(ISNUMBER(O33),O33,0)+IF(ISNUMBER(P33),P33,0),"") -> 1900 | S33: Rohlig
A34: Dubai-Laem | B34: OSE Industries LLC, Dubai | C34: AITH, Rayong 21140 Thailand | D34: Dubai | E34: Laemchabang | F34: EXW | G34: 0.5 | H34: 70 | I34: 70 | J34: 140 | K34: 420 | L34: 30 | M34: 70 | N34: =SUM(H34:M34) -> 800 | O34: 800 | P34: 900 | Q34: 20-25 days | R34: =IFERROR(N34+IF(ISNUMBER(O34),O34,0)+IF(ISNUMBER(P34),P34,0),"") -> 2500 | S34: Superchain
A35: Laem-Hamburg | B35: AITH, Rayong 21140 Thailand | C35: AISK, Nitra, Slovakia | D35: Laemchabang | E35: Hamburg | F35: DDP | G35: 6 | H35: 70 | I35: 70 | J35: 140 | K35: 300 | L35: 30 | M35: 70 | N35: =SUM(H35:M35) -> 680 | O35: 2200 | P35: 4800 | Q35: 9-10 wks | R35: =IFERROR(N35+IF(ISNUMBER(O35),O35,0)+IF(ISNUMBER(P35),P35,0),"") -> 7680 | S35: Superchain
A36: AISK | Slovakia (Hamburg) | 3 条航线 | 月需求 4.5 HQ40
A37: SHA-Hamburg | B37: AINT - 666 Wenchang Rd, Tongzhou, Nantong | C37: AISK, Nitra, Slovakia | D37: SHA | E37: Hamburg | F37: EXW | G37: 1 | H37: 70 | I37: 70 | J37: 140 | K37: 400 | L37: 10 | M37: 70 | O37: 2200 | P37: 3635 | Q37: 8-9 wks | S37: Bestunit
A38: Nhava-Hamburg | B38: Divine Tooling | C38: AISK, Nitra, Slovakia | D38: Nhava Sheva | E38: Hamburg | F38: EXW | G38: 3 | H38: 70 | I38: 70 | J38: 140 | K38: 300 | L38: 250 | M38: 70 | N38: =SUM(H38:M38) -> 900 | O38: 2200 | P38: 4500 | Q38: 8-10 wks | R38: =IFERROR(N38+IF(ISNUMBER(O38),O38,0)+IF(ISNUMBER(P38),P38,0),"") -> 7600 | S38: Superchain
A39: Bangkok-Hamburg | B39: Delta Electronics | C39: AISK, Nitra, Slovakia | D39: Bangkok | E39: Hamburg | F39: EXW | G39: 0.5 | H39: 70 | I39: 70 | J39: 140 | K39: 300 | L39: 250 | M39: 70 | N39: =SUM(H39:M39) -> 900 | O39: 2200 | P39: 4500 | Q39: 9-10 wks | R39: =IFERROR(N39+IF(ISNUMBER(O39),O39,0)+IF(ISNUMBER(P39),P39,0),"") -> 7600 | S39: Superchain

Sheet 25.10月
A1: Lane | B1: Consignor | C1: Consignee | D1: POL | E1: POD | F1: Incoterm | G1: HQ40 Demand | H1: Booking Fee | I1: Doc Fee | J1: THC | K1: Loading | L1: Customs | M1: B/L | N1: Local Subtotal | O1: Dest Local Cost | P1: Sea Freight | Q1: Transit Time | R1: Total (USD) | S1: Winning Forwarder
A2: AI-Turkey | Turkey (Izmit) | 2 条航线 | 月需求 18 HQ40
A3: SHA-Izmit | B3: AINT- 666 Wenchang Road, Tongzhou District, Nantong City | C3: AIR INTERNATIONAL TERMAL SİSTEMLERİ A. Ş. ESENTEPE MAH. ALİ KAYA SK. POLAT PLAZA B BLOK NO: 1/1 İÇ KAPI NO:69 ŞİŞLİ/İSTANBUL | D3: SHA | E3: Izmit | F3: DAP | G3: 16 | H3: 70 | I3: 70 | J3: 140 | K3: 400 | L3: 10 | M3: 70 | N3: =SUM(H3:M3) -> 760 | O3: 950 | P3: 2200 | R3: =IFERROR(N3+IF(ISNUMBER(O3),O3,0)+IF(ISNUMBER(P3),P3,0),"") -> 3910 | S3: Holiton
A4: SHA-Izmit | B4: SAI-No. 3 Gaobao Lake East Road, Yubei District, Chongqing | C4: AIR INTERNATIONAL TERMAL SİSTEMLERİ A. Ş. ESENTEPE MAH. ALİ KAYA SK. POLAT PLAZA B BLOK NO: 1/1 İÇ KAPI NO:69 ŞİŞLİ/İSTANBUL | D4: SHA | E4: Izmit | F4: EXW | G4: 2 | H4: 70 | I4: 70 | J4: 140 | K4: 200 | L4: 20 | M4: 50 | N4: =SUM(H4:M4) -> 550 | O4: 950 | P4: 2650 | R4: =IFERROR(N4+IF(ISNUMBER(O4),O4,0)+IF(ISNUMBER(P4),P4,0),"") -> 4150 | S4: Kaifu
A5: AIMX | Mexico (Manzanillo) | 15 条航线 | 月需求 34 HQ40
A6: Laemchabang-Manzanillo | B6: AITH | C6: Puebla + Saltillo | D6: Laemchabang | E6: Manzanillo | F6: CIF | G6: 9 | H6: 70 | I6: 50 | J6: 260 | K6: 250 | L6: 90 | M6: 80 | N6: =SUM(H6:M6) -> 800 | O6: N/A | P6: 2550 | R6: =IFERROR(N6+IF(ISNUMBER(O6),O6,0)+IF(ISNUMBER(P6),P6,0),"") -> 3350 | S6: Bondex
A7: Bangkok-Manzanillo | B7: DELTA | C7: Saltillo | D7: Bangkok | E7: Manzanillo | F7: CIF | G7: 4 | H7: 70 | I7: 50 | J7: 260 | K7: 325 | L7: 90 | M7: 80 | N7: =SUM(H7:M7) -> 875 | O7: N/A | P7: 2550 | R7: =IFERROR(N7+IF(ISNUMBER(O7),O7,0)+IF(ISNUMBER(P7),P7,0),"") -> 3425 | S7: Bondex
A8: Laemchabang-Manzanillo | B8: TNC | C8: Puebla | D8: Laemchabang | E8: Manzanillo | F8: CIF | G8: 0.5 | H8: 70 | I8: 50 | J8: 260 | K8: 250 | L8: 90 | M8: 80 | N8: =SUM(H8:M8) -> 800 | O8: N/A | P8: 2550 | R8: =IFERROR(N8+IF(ISNUMBER(O8),O8,0)+IF(ISNUMBER(P8),P8,0),"") -> 3350 | S8: Bondex
A9: Nhava Sheva-Manzanillo | B9: Creative Components | C9: Saltillo | D9: Nhava Sheva | E9: Manzanillo | F9: CIF | G9: 2 | H9: 70 | I9: 80 | J9: 160 | K9: 1000 | L9: 50 | M9: 75 | N9: =SUM(H9:M9) -> 1435 | O9: N/A | P9: 2500 | R9: =IFERROR(N9+IF(ISNUMBER(O9),O9,0)+IF(ISNUMBER(P9),P9,0),"") -> 3935 | S9: Kaifu
A10: Incheon-Manzanillo | B10: WOORY | C10: Saltillo | D10: Incheon | E10: Manzanillo | F10: CIF | G10: 1 | H10: 70 | I10: 35 | J10: 145 | K10: 350 | L10: 150 | M10: 50 | N10: =SUM(H10:M10) -> 800 | O10: N/A | P10: 2500 | R10: =IFERROR(N10+IF(ISNUMBER(O10),O10,0)+IF(ISNUMBER(P10),P10,0),"") -> 3300 | S10: Bondex
A11: SHA-Manzanillo | B11: Jiangsu Chao Li | C11: Puebla | D11: SHA | E11: Manzanillo | F11: FOB | G11: 2 | H11: 70 | I11: 70 | J11: 145 | K11: 550 | L11: 15 | M11: 60 | N11: =SUM(H11:M11) -> 910 | O11: N/A | P11: 2250 | R11: =IFERROR(N11+IF(ISNUMBER(O11),O11,0)+IF(ISNUMBER(P11),P11,0),"") -> 3160 | S11: Bondex
A12: SHA-Manzanillo | B12: Yangzhou RSL | C12: Puebla | D12: SHA | E12: Manzanillo | F12: CIF | G12: 1 | H12: 70 | I12: 70 | J12: 145 | K12: 550 | L12: 15 | M12: 60 | N12: =SUM(H12:M12) -> 910 | O12: N/A | P12: 2250 | R12: =IFERROR(N12+IF(ISNUMBER(O12),O12,0)+IF(ISNUMBER(P12),P12,0),"") -> 3160 | S12: Bondex
A13: SHA-Manzanillo | B13: Zhejiang Yuansheng | C13: Puebla | D13: SHA | E13: Manzanillo | F13: CIF | G13: 1 | H13: 70 | I13: 70 | J13: 145 | K13: 550 | L13: 15 | M13: 60 | N13: =SUM(H13:M13) -> 910 | O13: N/A | P13: 2250 | R13: =IFERROR(N13+IF(ISNUMBER(O13),O13,0)+IF(ISNUMBER(P13),P13,0),"") -> 3160 | S13: Bondex
A14: SHA-Manzanillo | B14: Shanghai Huafon Coil | C14: Puebla | D14: SHA | E14: Manzanillo | F14: CIF | G14: 2 | H14: 70 | I14: 70 | J14: 145 | K14: 250 | L14: 15 | M14: 60 | N14: =SUM(H14:M14) -> 610 | O14: N/A | P14: 2250 | R14: =IFERROR(N14+IF(ISNUMBER(O14),O14,0)+IF(ISNUMBER(P14),P14,0),"") -> 2860 | S14: Bondex
A15: SHA-Manzanillo | B15: Dalian ABIC | C15: Puebla | D15: SHA | E15: Manzanillo | F15: CIF | G15: 2 | H15: 70 | I15: 70 | J15: 145 | K15: 200 | L15: 15 | M15: 50 | N15: =SUM(H15:M15) -> 550 | O15: N/A | P15: 2300 | R15: =IFERROR(N15+IF(ISNUMBER(O15),O15,0)+IF(ISNUMBER(P15),P15,0),"") -> 2850 | S15: Kaifu
A16: SHA-Manzanillo | B16: Chongqing Boling | C16: Puebla | D16: SHA | E16: Manzanillo | F16: CIF | G16: 0.5 | H16: 70 | I16: 70 | J16: 145 | K16: 1550 | L16: 15 | M16: 60 | N16: =SUM(H16:M16) -> 1910 | O16: N/A | P16: 2300 | R16: =IFERROR(N16+IF(ISNUMBER(O16),O16,0)+IF(ISNUMBER(P16),P16,0),"") -> 4210 | S16: Kaifu
A17: SHA-Manzanillo | B17: AITD | C17: Saltillo | D17: SHA | E17: Manzanillo | F17: CIF | G17: 4 | H17: 70 | I17: 70 | J17: 145 | K17: 350 | L17: 15 | M17: 60 | N17: =SUM(H17:M17) -> 710 | O17: N/A | P17: 2250 | R17: =IFERROR(N17+IF(ISNUMBER(O17),O17,0)+IF(ISNUMBER(P17),P17,0),"") -> 2960 | S17: Bondex
... A20: SHA-Manzanillo | B20: Changsha Shenda | C20: Saltillo | D20: SHA | E20: Manzanillo | F20: CIF | G20: 2 | H20: 70 | I20: 70 | J20: 145 | K20: 1500 | L20: 15 | M20: 60 | N20: =SUM(H20:M20) -> 1860 | O20: N/A | P20: 2300 | R20: =IFERROR(N20+IF(ISNUMBER(O20),O20,0)+IF(ISNUMBER(P20),P20,0),"") -> 4160 | S20: Kaifu
A21: AIUS | USA (HOU / Detroit / Savanna) | 5 条航线 | 月需求 10 HQ40
A22: SHA-HOU | B22: AINT- 666 Wenchang Road, Tongzhou District, Nantong City | C22: Air International Thermal System-c/o GTZ WAREHOUSE LLC-662 SOUTH 33rd STREET, BUILDING-J, McALLEN, TX 78503 | D22: SHA | E22: HOU | F22: EXW | G22: 2 | H22: 70 | I22: 70 | J22: 140 | K22: 400 | L22: 10 | M22: 70 | N22: =SUM(H22:M22) -> 760 | O22: 2685 | P22: 2886 | R22: =IFERROR(N22+IF(ISNUMBER(O22),O22,0)+IF(ISNUMBER(P22),P22,0),"") -> 6331 | S22: Bestunit
A23: SHA-Detroit | B23: AISH-108 Chunguang Road, Minhang District, Shanghai | C23: Air International Thermal Systems-c/o FTZ METRO WAREHOUSE-1200 E. McNICHOLS RD, HIGHLAND PARK, MI 48203 | D23: SHA | E23: Detroit | F23: EXW | G23: 2 | H23: 70 | I23: 70 | J23: 140 | K23: 250 | L23: 10 | M23: 70 | N23: =SUM(H23:M23) -> 610 | O23: 885 | P23: 3979 | R23: =IFERROR(N23+IF(ISNUMBER(O23),O23,0)+IF(ISNUMBER(P23),P23,0),"") -> 5474 | S23: Bestunit
A24: Laem Chabang-Savanna | B24: Air International Thermal Systems (Thailand) Ltd. (Head Office) 500/46 Moo 3, WHA Eastern Seaboard Industrial Estate 1 Tambol Tasit, Amphur Pluak Daeng, Rayong 21140 Thailand | C24: Air International Thermal Systems 466 Baxter Lane Winchester, TN, USA, 37398 | D24: Laem Chabang | E24: Savanna | F24: EXW | G24: 0 | H24: 70 | I24: 70 | J24: 140 | K24: 300 | L24: 30 | M24: 70 | N24: =SUM(H24:M24) -> 680 | O24: 2785 | P24: 3770 | R24: =IFERROR(N24+IF(ISNUMBER(O24),O24,0)+IF(ISNUMBER(P24),P24,0),"") -> 7235 | S24: Bestunit
A25: Nhava Sheva-Savanna | B25: Divine & Creative from India | C25: Air International Thermal Systems 466 Baxter Lane Winchester, TN, USA, 37398 | D25: Nhava Sheva | E25: Savanna | F25: EXW | G25: 3 | H25: 70 | I25: 80 | J25: 160 | K25: 1000 | L25: 50 | M25: 75 | N25: =SUM(H25:M25) -> 1435 | O25: 2785 | P25: 4737 | R25: =IFERROR(N25+IF(ISNUMBER(O25),O25,0)+IF(ISNUMBER(P25),P25,0),"") -> 8957 | S25: Bestunit
A26: SHA-Savanna | B26: AINT- 666 Wenchang Road, Tongzhou District, Nantong City | C26: Air International Thermal Systems 466 Baxter Lane Winchester, TN, USA, 37398 | D26: SHA | E26: Savanna | F26: EXW | G26: 3 | H26: 70 | I26: 70 | J26: 140 | K26: 400 | L26: 10 | M26: 70 | N26: =SUM(H26:M26) -> 760 | O26: 2785 | P26: 3168 | R26: =IFERROR(N26+IF(ISNUMBER(O26),O26,0)+IF(ISNUMBER(P26),P26,0),"") -> 6713 | S26: Bestunit
A27: AISH | Asia → SHA (inbound) | 2 条航线 | 月需求 1 HQ40
A28: Bangkok-SHA | B28: DELTA ELECTRONICS (THAILAND) PUBLIC COMPANY LIMITED 111 MOO 9, BANGNA-TRAD RD., TAMBOL BANGWUA AMPHUR BANGPAKONG CHACHOENGSAO, 24180 THAILAND | C28: AINT- 666 Wenchang Road, Tongzhou District, Nantong City | D28: Bangkok | E28: SHA | F28: EXW | G28: 0 | H28: 70 | I28: 50 | J28: 260 | K28: 325 | L28: 90 | M28: 80 | N28: =SUM(H28:M28) -> 875 | O28: 600 | P28: 1 | R28: =IFERROR(N28+IF(ISNUMBER(O28),O28,0)+IF(ISNUMBER(P28),P28,0),"") -> 1476 | S28: Superchain
A29: Incheon-SHA | B29: Woory Industrial Co., Ltd #531, Jigok-dong, Kihung-gu Yongin-city, Kyonggi-Do, Korea | C29: AINT- 666 Wenchang Road, Tongzhou District, Nantong City | D29: Incheon | E29: SHA | F29: EXW | G29: 1 | H29: 70 | I29: 35 | J29: 145 | K29: 350 | L29: 150 | M29: 50 | N29: =SUM(H29:M29) -> 800 | O29: 600 | P29: 1 | R29: =IFERROR(N29+IF(ISNUMBER(O29),O29,0)+IF(ISNUMBER(P29),P29,0),"") -> 1401 | S29: Superchain
A30: AITH | Thailand (Laemchabang) | 5 条航线 | 月需求 11 HQ40
A31: SHA-Laemchabang | B31: Air International (Shanghai) Co., Ltd. No. 108 Chunguang Road, XinZhuang Industrial Zone, Minhang, Shanghai P.R. China 201108 | C31: Air International Thermal Systems (Thailand) Ltd. 41/17,18,19 MOO 8, T.BOWIN, A.SRIRACHA, CHONBURI, 20230 THAILAND | D31: SHA | E31: Laemchabang | F31: EXW | G31: 1 | H31: 70 | I31: 70 | J31: 140 | K31: 250 | L31: 10 | M31: 70 | N31: =SUM(H31:M31) -> 610 | O31: 800 | P31: 395 | R31: =IFERROR(N31+IF(ISNUMBER(O31),O31,0)+IF(ISNUMBER(P31),P31,0),"") -> 1805 | S31: Rohlig
A32: SHA-Laemchabang | B32: Shanghai Huafon Aluminium Corp. 1111# Yuegong Road, Jinshan District, Shanghai 201506 | C32: Air International Thermal Systems (Thailand) Ltd. 500/46 Moo 3, WHA Eastern Seaboard Industrial Estate 1, T. Tasit, A. Pluekdaeng, Rayong 21140 | D32: SHA | E32: Laemchabang | F32: EXW | G32: 3 | H32: 70 | I32: 70 | J32: 140 | K32: 250 | L32: 10 | M32: 70 | N32: =SUM(H32:M32) -> 610 | O32: 800 | P32: 420 | R32: =IFERROR(N32+IF(ISNUMBER(O32),O32,0)+IF(ISNUMBER(P32),P32,0),"") -> 1830 | S32: Rohlig
A33: Tianjin-Laemchabang | B33: Hyo Seong Electric (Toanjin) Co., Ltd No.99, Xi San Dao, Tianjin Airport Industrial Park, TPFTZ, Tianjin, P.R. China | C33: Air International Thermal Systems (Thailand) Ltd. 41/17,18,19 MOO 8, T.BOWIN, A.SRIRACHA, CHONBURI, 20230 THAILAND | D33: Tianjin | E33: Laemchabang | F33: EXW | G33: 0.5 | H33: 70 | I33: 70 | J33: 140 | K33: 420 | L33: 30 | M33: 70 | N33: =SUM(H33:M33) -> 800 | O33: 800 | P33: 205 | R33: =IFERROR(N33+IF(ISNUMBER(O33),O33,0)+IF(ISNUMBER(P33),P33,0),"") -> 1805 | S33: Rohlig
A34: Dubai-Laemchabang | B34: OSE Industries LLC. Dubai Industrial Park, Office#103, First Floor, Building 1, Dubai Industrial City, Dubai, UAE, Post Box 126344 | C34: Air International Thermal Systems (Thailand) Ltd. 500/46 Moo 3, WHA Eastern Seaboard Industrial Estate 1, T. Tasit, A. Pluekdaeng, Rayong 21140 | D34: Dubai | E34: Laemchabang | F34: EXW | G34: 0.5 | H34: 70 | I34: 70 | J34: 140 | K34: 420 | L34: 30 | M34: 70 | N34: =SUM(H34:M34) -> 800 | O34: 800 | P34: 400 | R34: =IFERROR(N34+IF(ISNUMBER(O34),O34,0)+IF(ISNUMBER(P34),P34,0),"") -> 2000 | S34: Bondex
A35: Laemchabang-Hamburg | B35: Air International Thermal Systems (Thailand) Ltd. 500/46 Moo 3, WHA Eastern Seaboard Industrial Estate 1, T. Tasit, A. Pluekdaeng, Rayong 21140 | C35: Air International Thermal (Slovakia) s.r.o. Prologis Park Nitra, DC3 Cez panske 4289/9, 949 01 Nitra, Slovakia | D35: Laemchabang | E35: Hamburg | F35: DDP | G35: 6 | H35: 70 | I35: 70 | J35: 140 | K35: 300 | L35: 30 | M35: 70 | N35: =SUM(H35:M35) -> 680 | O35: 2200 | P35: 2340 | R35: =IFERROR(N35+IF(ISNUMBER(O35),O35,0)+IF(ISNUMBER(P35),P35,0),"") -> 5220 | S35: Bondex
A36: AISK | Slovakia (Hamburg) | 3 条航线 | 月需求 4.5 HQ40
A37: SHA-Hamburg | B37: AINT- 666 Wenchang Road, Tongzhou District, Nantong City, China | C37: Air International Thermal (Slovakia) s.r.o. Prologis Park Nitra, DC3 Cez panske 4289/9, 949 01 Nitra, Slovakia | D37: SHA | E37: Hamburg | F37: EXW | G37: 1 | H37: 70 | I37: 70 | J37: 140 | K37: 400 | L37: 10 | M37: 70 | N37: =SUM(H37:M37) -> 760 | O37: 2200 | P37: 1990 | R37: =IFERROR(N37+IF(ISNUMBER(O37),O37,0)+IF(ISNUMBER(P37),P37,0),"") -> 4950 | S37: Bondex
A38: Nhava Sheva-Hamburg | B38: Divine tooling | C38: Air International Thermal (Slovakia) s.r.o. Prologis Park Nitra, DC3 Cez panske 4289/9, 949 01 Nitra, Slovakia | D38: Nhava Sheva | E38: Hamburg | F38: EXW | G38: 3 | H38: 70 | I38: 70 | J38: 140 | K38: 300 | L38: 250 | M38: 70 | N38: =SUM(H38:M38) -> 900 | O38: 2200 | P38: 1590 | R38: =IFERROR(N38+IF(ISNUMBER(O38),O38,0)+IF(ISNUMBER(P38),P38,0),"") -> 4690 | S38: Bondex
A39: Bangkok-Hamburg | B39: Delta Electronics | C39: Air International Thermal (Slovakia) s.r.o. Prologis Park Nitra, DC3 Cez panske 4289/9, 949 01 Nitra, Slovakia | D39: Bangkok | E39: Hamburg | F39: EXW | G39: 0.5 | H39: 70 | I39: 70 | J39: 140 | K39: 300 | L39: 250 | M39: 70 | N39: =SUM(H39:M39) -> 900 | O39: 2200 | P39: 1590 | R39: =IFERROR(N39+IF(ISNUMBER(O39),O39,0)+IF(ISNUMBER(P39),P39,0),"") -> 4690 | S39: Bondex

Sheet 25.11月
A1: Lane | B1: Consignor | C1: Consignee | D1: POL | E1: POD | F1: Incoterm | G1: HQ40 Demand | H1: Booking Fee | I1: Doc Fee | J1: THC | K1: Loading | L1: Customs | M1: B/L | N1: Local Subtotal | O1: Dest Local Cost | P1: Sea Freight | Q1: Transit Time | R1: Total (USD) | S1: Winning Forwarder
A2: AI-Turkey | Turkey (Izmit) | 2 条航线 | 月需求 22 HQ40
A3: SHA-Izmit | B3: AINT- 666 Wenchang Road, Tongzhou District, Nantong City | C3: AIR INTERNATIONAL TERMAL SİSTEMLERİ A. Ş. ESENTEPE MAH. ALİ KAYA SK. POLAT PLAZA B BLOK NO: 1/1 İÇ KAPI NO:69 ŞİŞLİ/İSTANBUL | D3: SHA | E3: Izmit | F3: DAP | G3: 18 | H3: 70 | I3: 70 | J3: 140 | K3: 400 | L3: 10 | M3: 70 | N3: =SUM(H3:M3) -> 760 | O3: 950 | P3: 2145 | R3: =IFERROR(N3+IF(ISNUMBER(O3),O3,0)+IF(ISNUMBER(P3),P3,0),"") -> 3855 | S3: Holiton 3 + Bestunit 15
A4: SHA-Izmit | B4: SAI-No. 3 Gaobao Lake East Road, Yubei District, Chongqing | C4: AIR INTERNATIONAL TERMAL SİSTEMLERİ A. Ş. ESENTEPE MAH. ALİ KAYA SK. POLAT PLAZA B BLOK NO: 1/1 İÇ KAPI NO:69 ŞİŞLİ/İSTANBUL | D4: SHA | E4: Izmit | F4: EXW | G4: 4 | H4: 70 | I4: 70 | J4: 140 | K4: 200 | L4: 20 | M4: 50 | N4: =SUM(H4:M4) -> 550 | O4: 950 | P4: 3650 | R4: =IFERROR(N4+IF(ISNUMBER(O4),O4,0)+IF(ISNUMBER(P4),P4,0),"") -> 5150 | S4: Bestunit
A5: AIMX | Mexico (Manzanillo) | 15 条航线 | 月需求 31 HQ40
A6: Laemchabang-Manzanillo | B6: AITH | C6: Puebla + Saltillo | D6: Laemchabang | E6: Manzanillo | F6: CIF | G6: 9 | H6: 70 | I6: 50 | J6: 260 | K6: 250 | L6: 90 | M6: 80 | N6: =SUM(H6:M6) -> 800 | O6: N/A | P6: 2350 | R6: =IFERROR(N6+IF(ISNUMBER(O6),O6,0)+IF(ISNUMBER(P6),P6,0),"") -> 3150 | S6: Freetrans
A7: Bangkok-Manzanillo | B7: DELTA | C7: Saltillo | D7: Bangkok | E7: Manzanillo | F7: CIF | G7: 2 | H7: 70 | I7: 50 | J7: 260 | K7: 325 | L7: 90 | M7: 80 | N7: =SUM(H7:M7) -> 875 | O7: N/A | P7: 2100 | R7: =IFERROR(N7+IF(ISNUMBER(O7),O7,0)+IF(ISNUMBER(P7),P7,0),"") -> 2975 | S7: Kaifu
A8: Laemchabang-Manzanillo | B8: TNC | C8: Puebla | D8: Laemchabang | E8: Manzanillo | F8: CIF | G8: 0.5 | H8: 70 | I8: 50 | J8: 260 | K8: 250 | L8: 90 | M8: 80 | N8: =SUM(H8:M8) -> 800 | O8: N/A | P8: 2250 | R8: =IFERROR(N8+IF(ISNUMBER(O8),O8,0)+IF(ISNUMBER(P8),P8,0),"") -> 3050 | S8: Kaifu
A9: Nhava Sheva-Manzanillo | B9: Creative Components | C9: Saltillo | D9: Nhava Sheva | E9: Manzanillo | F9: CIF | G9: 1 | H9: 70 | I9: 80 | J9: 160 | K9: 1000 | L9: 50 | M9: 75 | N9: =SUM(H9:M9) -> 1435 | O9: N/A | P9: 2500 | R9: =IFERROR(N9+IF(ISNUMBER(O9),O9,0)+IF(ISNUMBER(P9),P9,0),"") -> 3935 | S9: Kaifu
A10: Incheon-Manzanillo | B10: WOORY | C10: Saltillo | D10: Incheon | E10: Manzanillo | F10: CIF | G10: 1 | H10: 70 | I10: 35 | J10: 145 | K10: 350 | L10: 150 | M10: 50 | N10: =SUM(H10:M10) -> 800 | O10: N/A | P10: 2390 | R10: =IFERROR(N10+IF(ISNUMBER(O10),O10,0)+IF(ISNUMBER(P10),P10,0),"") -> 3190 | S10: Kaifu
A11: SHA-Manzanillo | B11: Jiangsu Chao Li | C11: Puebla | D11: SHA | E11: Manzanillo | F11: CIF | G11: 2 | H11: 70 | I11: 70 | J11: 145 | K11: 550 | L11: 15 | M11: 60 | N11: =SUM(H11:M11) -> 910 | O11: N/A | P11: 1790 | R11: =IFERROR(N11+IF(ISNUMBER(O11),O11,0)+IF(ISNUMBER(P11),P11,0),"") -> 2700 | S11: Kaifu
A12: SHA-Manzanillo | B12: Yangzhou RSL | C12: Puebla | D12: SHA | E12: Manzanillo | F12: CIF | G12: 1 | H12: 70 | I12: 70 | J12: 145 | K12: 550 | L12: 15 | M12: 60 | N12: =SUM(H12:M12) -> 910 | O12: N/A | P12: 1800 | R12: =IFERROR(N12+IF(ISNUMBER(O12),O12,0)+IF(ISNUMBER(P12),P12,0),"") -> 2710 | S12: Kaifu
A13: SHA-Manzanillo | B13: Zhejiang Yuansheng | C13: Puebla | D13: SHA | E13: Manzanillo | F13: CIF | G13: 1 | H13: 70 | I13: 70 | J13: 145 | K13: 550 | L13: 15 | M13: 60 | N13: =SUM(H13:M13) -> 910 | O13: N/A | P13: 1800 | R13: =IFERROR(N13+IF(ISNUMBER(O13),O13,0)+IF(ISNUMBER(P13),P13,0),"") -> 2710 | S13: Kaifu
A14: SHA-Manzanillo | B14: Shanghai Huafon Coil | C14: Puebla | D14: SHA | E14: Manzanillo | F14: CIF | G14: 2 | H14: 70 | I14: 70 | J14: 145 | K14: 250 | L14: 15 | M14: 60 | N14: =SUM(H14:M14) -> 610 | O14: N/A | P14: 1800 | R14: =IFERROR(N14+IF(ISNUMBER(O14),O14,0)+IF(ISNUMBER(P14),P14,0),"") -> 2410 | S14: Kaifu
A15: SHA-Manzanillo | B15: Dalian ABIC | C15: Puebla | D15: SHA | E15: Manzanillo | F15: CIF | G15: 2 | H15: 70 | I15: 70 | J15: 145 | K15: 200 | L15: 15 | M15: 50 | N15: =SUM(H15:M15) -> 550 | O15: N/A | P15: 1770 | R15: =IFERROR(N15+IF(ISNUMBER(O15),O15,0)+IF(ISNUMBER(P15),P15,0),"") -> 2320 | S15: Kaifu
A16: SHA-Manzanillo | B16: Chongqing Boling | C16: Puebla | D16: SHA | E16: Manzanillo | F16: CIF | G16: 0.5 | H16: 70 | I16: 70 | J16: 145 | K16: 1550 | L16: 15 | M16: 60 | N16: =SUM(H16:M16) -> 1910 | O16: N/A | P16: 1800 | R16: =IFERROR(N16+IF(ISNUMBER(O16),O16,0)+IF(ISNUMBER(P16),P16,0),"") -> 3710 | S16: Kaifu
A17: SHA-Manzanillo | B17: AITD | C17: Saltillo | D17: SHA | E17: Manzanillo | F17: CIF | G17: 4 | H17: 70 | I17: 70 | J17: 145 | K17: 350 | L17: 15 | M17: 60 | N17: =SUM(H17:M17) -> 710 | O17: N/A | P17: 1800 | R17: =IFERROR(N17+IF(ISNUMBER(O17),O17,0)+IF(ISNUMBER(P17),P17,0),"") -> 2510 | S17: Kaifu
... A20: SHA-Manzanillo | B20: Changsha Shenda | C20: Saltillo | D20: SHA | E20: Manzanillo | F20: CIF | G20: 2 | H20: 70 | I20: 70 | J20: 145 | K20: 1500 | L20: 15 | M20: 60 | N20: =SUM(H20:M20) -> 1860 | O20: N/A | P20: 1800 | R20: =IFERROR(N20+IF(ISNUMBER(O20),O20,0)+IF(ISNUMBER(P20),P20,0),"") -> 3660 | S20: Kaifu
A21: AIUS | USA (HOU / Detroit / Savanna) | 5 条航线 | 月需求 12 HQ40
A22: SHA-HOU | B22: AINT- 666 Wenchang Road, Tongzhou District, Nantong City | C22: Air International Thermal System-c/o GTZ WAREHOUSE LLC-662 SOUTH 33rd STREET, BUILDING-J, McALLEN, TX 78503 | D22: SHA | E22: HOU | F22: EXW | G22: 2 | H22: 70 | I22: 70 | J22: 140 | K22: 400 | L22: 10 | M22: 70 | N22: =SUM(H22:M22) -> 760 | O22: 2685 | P22: 2600 | R22: =IFERROR(N22+IF(ISNUMBER(O22),O22,0)+IF(ISNUMBER(P22),P22,0),"") -> 6045 | S22: Kaifu
A23: SHA-Detroit | B23: AISH-108 Chunguang Road, Minhang District, Shanghai | C23: Air International Thermal Systems-c/o FTZ METRO WAREHOUSE-1200 E. McNICHOLS RD, HIGHLAND PARK, MI 48203 | D23: SHA | E23: Detroit | F23: EXW | G23: 1 | H23: 70 | I23: 70 | J23: 140 | K23: 250 | L23: 10 | M23: 70 | N23: =SUM(H23:M23) -> 610 | O23: 885 | P23: 4050 | R23: =IFERROR(N23+IF(ISNUMBER(O23),O23,0)+IF(ISNUMBER(P23),P23,0),"") -> 5545 | S23: Kaifu
A24: Laem Chabang-Savanna | B24: Air International Thermal Systems (Thailand) Ltd. (Head Office) 500/46 Moo 3, WHA Eastern Seaboard Industrial Estate 1 Tambol Tasit, Amphur Pluak Daeng, Rayong 21140 Thailand | C24: Air International Thermal Systems 466 Baxter Lane Winchester, TN, USA, 37398 | D24: Laem Chabang | E24: Savanna | F24: EXW | G24: 3 | H24: 70 | I24: 70 | J24: 140 | K24: 300 | L24: 30 | M24: 70 | N24: =SUM(H24:M24) -> 680 | O24: 2785 | P24: 2495 | R24: =IFERROR(N24+IF(ISNUMBER(O24),O24,0)+IF(ISNUMBER(P24),P24,0),"") -> 5960 | S24: Freetrans
A25: Nhava Sheva-Savanna | B25: Divine & Creative from India | C25: Air International Thermal Systems 466 Baxter Lane Winchester, TN, USA, 37398 | D25: Nhava Sheva | E25: Savanna | F25: EXW | G25: 3 | H25: 70 | I25: 80 | J25: 160 | K25: 1000 | L25: 50 | M25: 75 | N25: =SUM(H25:M25) -> 1435 | O25: 2785 | P25: 2485 | R25: =IFERROR(N25+IF(ISNUMBER(O25),O25,0)+IF(ISNUMBER(P25),P25,0),"") -> 6705 | S25: Freetrans
A26: SHA-Savanna | B26: AINT- 666 Wenchang Road, Tongzhou District, Nantong City | C26: Air International Thermal Systems 466 Baxter Lane Winchester, TN, USA, 37398 | D26: SHA | E26: Savanna | F26: EXW | G26: 3 | H26: 70 | I26: 70 | J26: 140 | K26: 400 | L26: 10 | M26: 70 | N26: =SUM(H26:M26) -> 760 | O26: 2785 | P26: 2250 | R26: =IFERROR(N26+IF(ISNUMBER(O26),O26,0)+IF(ISNUMBER(P26),P26,0),"") -> 5795 | S26: Freetrans
A27: AISH | Asia → SHA (inbound) | 2 条航线 | 月需求 3 HQ40
A28: Bangkok-SHA | B28: DELTA ELECTRONICS (THAILAND) PUBLIC COMPANY LIMITED 111 MOO 9, BANGNA-TRAD RD., TAMBOL BANGWUA AMPHUR BANGPAKONG CHACHOENGSAO, 24180 THAILAND | C28: AINT- 666 Wenchang Road, Tongzhou District, Nantong City | D28: Bangkok | E28: SHA | F28: EXW | G28: 2 | H28: 70 | I28: 50 | J28: 260 | K28: 325 | L28: 90 | M28: 80 | N28: =SUM(H28:M28) -> 875 | O28: 600 | P28: 1 | R28: =IFERROR(N28+IF(ISNUMBER(O28),O28,0)+IF(ISNUMBER(P28),P28,0),"") -> 1476 | S28: Superchain
A29: Incheon-SHA | B29: Woory Industrial Co., Ltd #531, Jigok-dong, Kihung-gu Yongin-city, Kyonggi-Do, Korea | C29: AINT- 666 Wenchang Road, Tongzhou District, Nantong City | D29: Incheon | E29: SHA | F29: EXW | G29: 1 | H29: 70 | I29: 35 | J29: 145 | K29: 350 | L29: 150 | M29: 50 | N29: =SUM(H29:M29) -> 800 | O29: 600 | P29: 1 | R29: =IFERROR(N29+IF(ISNUMBER(O29),O29,0)+IF(ISNUMBER(P29),P29,0),"") -> 1401 | S29: Superchain
A30: AITH | Thailand (Laemchabang) | 5 条航线 | 月需求 11 HQ40
A31: SHA-Laemchabang | B31: Air International (Shanghai) Co., Ltd. No. 108 Chunguang Road, XinZhuang Industrial Zone, Minhang, Shanghai P.R. China 201108 | C31: Air International Thermal Systems (Thailand) Ltd. 41/17,18,19 MOO 8, T.BOWIN, A.SRIRACHA, CHONBURI, 20230 THAILAND | D31: SHA | E31: Laemchabang | F31: EXW | G31: 1 | H31: 70 | I31: 70 | J31: 140 | K31: 250 | L31: 10 | M31: 70 | N31: =SUM(H31:M31) -> 610 | O31: 800 | P31: 395 | R31: =IFERROR(N31+IF(ISNUMBER(O31),O31,0)+IF(ISNUMBER(P31),P31,0),"") -> 1805 | S31: Rohlig
A32: SHA-Laemchabang | B32: Shanghai Huafon Aluminium Corp. 1111# Yuegong Road, Jinshan District, Shanghai 201506 | C32: Air International Thermal Systems (Thailand) Ltd. 500/46 Moo 3, WHA Eastern Seaboard Industrial Estate 1, T. Tasit, A. Pluekdaeng, Rayong 21140 | D32: SHA | E32: Laemchabang | F32: EXW | G32: 3 | H32: 70 | I32: 70 | J32: 140 | K32: 250 | L32: 10 | M32: 70 | N32: =SUM(H32:M32) -> 610 | O32: 800 | P32: 420 | R32: =IFERROR(N32+IF(ISNUMBER(O32),O32,0)+IF(ISNUMBER(P32),P32,0),"") -> 1830 | S32: Rohlig
A33: Tianjin-Laemchabang | B33: Hyo Seong Electric (Toanjin) Co., Ltd No.99, Xi San Dao, Tianjin Airport Industrial Park, TPFTZ, Tianjin, P.R. China | C33: Air International Thermal Systems (Thailand) Ltd. 41/17,18,19 MOO 8, T.BOWIN, A.SRIRACHA, CHONBURI, 20230 THAILAND | D33: Tianjin | E33: Laemchabang | F33: EXW | G33: 0.5 | H33: 70 | I33: 70 | J33: 140 | K33: 420 | L33: 30 | M33: 70 | N33: =SUM(H33:M33) -> 800 | O33: 800 | P33: 205 | R33: =IFERROR(N33+IF(ISNUMBER(O33),O33,0)+IF(ISNUMBER(P33),P33,0),"") -> 1805 | S33: Rohlig
A34: Dubai-Laemchabang | B34: OSE Industries LLC. Dubai Industrial Park, Office#103, First Floor, Building 1, Dubai Industrial City, Dubai, UAE, Post Box 126344 | C34: Air International Thermal Systems (Thailand) Ltd. 500/46 Moo 3, WHA Eastern Seaboard Industrial Estate 1, T. Tasit, A. Pluekdaeng, Rayong 21140 | D34: Dubai | E34: Laemchabang | F34: EXW | G34: 0.5 | H34: 70 | I34: 70 | J34: 140 | K34: 420 | L34: 30 | M34: 70 | N34: =SUM(H34:M34) -> 800 | O34: 800 | P34: 1640 | R34: =IFERROR(N34+IF(ISNUMBER(O34),O34,0)+IF(ISNUMBER(P34),P34,0),"") -> 3240 | S34: 当地自行招标
A35: Laemchabang-Hamburg | B35: Air International Thermal Systems (Thailand) Ltd. 500/46 Moo 3, WHA Eastern Seaboard Industrial Estate 1, T. Tasit, A. Pluekdaeng, Rayong 21140 | C35: Air International Thermal (Slovakia) s.r.o. Prologis Park Nitra, DC3 Cez panske 4289/9, 949 01 Nitra, Slovakia | D35: Laemchabang | E35: Hamburg | F35: DDP | G35: 6 | H35: 70 | I35: 70 | J35: 140 | K35: 300 | L35: 30 | M35: 70 | N35: =SUM(H35:M35) -> 680 | O35: 2200 | P35: 2670 | R35: =IFERROR(N35+IF(ISNUMBER(O35),O35,0)+IF(ISNUMBER(P35),P35,0),"") -> 5550 | S35: Rohlig
A36: AISK | Slovakia (Hamburg) | 3 条航线 | 月需求 3.5 HQ40
A37: SHA-Hamburg | B37: AINT- 666 Wenchang Road, Tongzhou District, Nantong City, China | C37: Air International Thermal (Slovakia) s.r.o. Prologis Park Nitra, DC3 Cez panske 4289/9, 949 01 Nitra, Slovakia | D37: SHA | E37: Hamburg | F37: EXW | G37: 1 | H37: 70 | I37: 70 | J37: 140 | K37: 400 | L37: 10 | M37: 70 | N37: =SUM(H37:M37) -> 760 | O37: 2200 | P37: 1890 | R37: =IFERROR(N37+IF(ISNUMBER(O37),O37,0)+IF(ISNUMBER(P37),P37,0),"") -> 4850 | S37: Bondex
A38: Nhava Sheva-Hamburg | B38: Divine tooling | C38: Air International Thermal (Slovakia) s.r.o. Prologis Park Nitra, DC3 Cez panske 4289/9, 949 01 Nitra, Slovakia | D38: Nhava Sheva | E38: Hamburg | F38: EXW | G38: 2 | H38: 70 | I38: 70 | J38: 140 | K38: 300 | L38: 250 | M38: 70 | N38: =SUM(H38:M38) -> 900 | O38: 2200 | P38: 4603 | R38: =IFERROR(N38+IF(ISNUMBER(O38),O38,0)+IF(ISNUMBER(P38),P38,0),"") -> 7703 | S38: 当地自行招标
A39: Bangkok-Hamburg | B39: Delta Electronics | C39: Air International Thermal (Slovakia) s.r.o. Prologis Park Nitra, DC3 Cez panske 4289/9, 949 01 Nitra, Slovakia | D39: Bangkok | E39: Hamburg | F39: EXW | G39: 0.5 | H39: 70 | I39: 70 | J39: 140 | K39: 300 | L39: 250 | M39: 70 | N39: =SUM(H39:M39) -> 900 | O39: 2200 | P39: 5156 | R39: =IFERROR(N39+IF(ISNUMBER(O39),O39,0)+IF(ISNUMBER(P39),P39,0),"") -> 8256 | S39: 当地自行招标

Sheet 25.12月
A1: Lane | B1: Consignor | C1: Consignee | D1: POL | E1: POD | F1: Incoterm | G1: HQ40 Demand | H1: Booking Fee | I1: Doc Fee | J1: THC | K1: Loading | L1: Customs | M1: B/L | N1: Local Subtotal | O1: Dest Local Cost | P1: Sea Freight | Q1: Transit Time | R1: Total (USD) | S1: Winning Forwarder
A2: AI-Turkey | Turkey (Izmit) | 2 条航线 | 月需求 20 HQ40
A3: SHA-Izmit | B3: AINT- 666 Wenchang Road, Tongzhou District, Nantong City | C3: AIR INTERNATIONAL TERMAL SİSTEMLERİ A. Ş. ESENTEPE MAH. ALİ KAYA SK. POLAT PLAZA B BLOK NO: 1/1 İÇ KAPI NO:69 ŞİŞLİ/İSTANBUL | D3: SHA | E3: Izmit | F3: DAP | G3: 16 | H3: 70 | I3: 70 | J3: 140 | K3: 400 | L3: 10 | M3: 70 | N3: =SUM(H3:M3) -> 760 | O3: 950 | P3: 2800 | Q3: 8-10 wks | R3: =IFERROR(N3+IF(ISNUMBER(O3),O3,0)+IF(ISNUMBER(P3),P3,0),"") -> 4510 | S3: Kaifu
A4: SHA-Izmit | B4: SAI-No. 3 Gaobao Lake East Road, Yubei District, Chongqing | C4: AIR INTERNATIONAL TERMAL SİSTEMLERİ A. Ş. ESENTEPE MAH. ALİ KAYA SK. POLAT PLAZA B BLOK NO: 1/1 İÇ KAPI NO:69 ŞİŞLİ/İSTANBUL | D4: SHA | E4: Izmit | F4: EXW | G4: 4 | H4: 70 | I4: 70 | J4: 170 | K4: 250 | L4: 50 | M4: 50 | N4: =SUM(H4:M4) -> 660 | O4: 950 | P4: 4600 | Q4: 9-11 wks | R4: =IFERROR(N4+IF(ISNUMBER(O4),O4,0)+IF(ISNUMBER(P4),P4,0),"") -> 6210 | S4: Kaifu
A5: AIMX | Mexico (Manzanillo) | 16 条航线 | 月需求 31 HQ40
A6: Laemchabang-Manzanillo | B6: AITH | C6: Puebla + Saltillo | D6: Laemchabang | E6: Manzanillo | F6: CIF | G6: 9 | H6: 70 | I6: 50 | J6: 260 | K6: 250 | L6: 90 | M6: 80 | N6: =SUM(H6:M6) -> 800 | O6: N/A | P6: 2048 | Q6: 35-45 days | R6: =IFERROR(N6+IF(ISNUMBER(O6),O6,0)+IF(ISNUMBER(P6),P6,0),"") -> 2848 | S6: Bondex
A7: Bangkok-Manzanillo | B7: DELTA | C7: Saltillo | D7: Bangkok | E7: Manzanillo | F7: CIF | G7: 2 | H7: 70 | I7: 50 | J7: 260 | K7: 325 | L7: 90 | M7: 80 | N7: =SUM(H7:M7) -> 875 | O7: N/A | P7: 2048 | R7: =IFERROR(N7+IF(ISNUMBER(O7),O7,0)+IF(ISNUMBER(P7),P7,0),"") -> 2923 | S7: Bondex
A8: Laemchabang-Manzanillo | B8: TNC | C8: Puebla | D8: Laemchabang | E8: Manzanillo | F8: CIF | G8: 1 | H8: 70 | I8: 50 | J8: 260 | K8: 250 | L8: 90 | M8: 80 | N8: =SUM(H8:M8) -> 800 | O8: N/A | P8: 2048 | R8: =IFERROR(N8+IF(ISNUMBER(O8),O8,0)+IF(ISNUMBER(P8),P8,0),"") -> 2848 | S8: Bondex
A9: Nhava Sheva-Manzanillo | B9: Creative Components | C9: Saltillo | D9: Nhava Sheva | E9: Manzanillo | F9: CIF | G9: 2 | H9: 70 | I9: 80 | J9: 160 | K9: 1000 | L9: 50 | M9: 75 | N9: =SUM(H9:M9) -> 1435 | O9: N/A | P9: 2500 | Q9: 50-55 days | R9: =IFERROR(N9+IF(ISNUMBER(O9),O9,0)+IF(ISNUMBER(P9),P9,0),"") -> 3935 | S9: KF
A10: Incheon-Manzanillo | B10: WOORY | C10: Saltillo | D10: Incheon | E10: Manzanillo | F10: CIF | G10: 1 | H10: 70 | I10: 35 | J10: 145 | K10: 350 | L10: 150 | M10: 50 | N10: =SUM(H10:M10) -> 800 | O10: N/A | P10: 2350 | Q10: 25-30 days | R10: =IFERROR(N10+IF(ISNUMBER(O10),O10,0)+IF(ISNUMBER(P10),P10,0),"") -> 3150 | S10: KF
A11: SHA-Manzanillo | B11: Jiangsu Chao Li | C11: Puebla | D11: SHA | E11: Manzanillo | F11: FOB | G11: 2 | H11: 70 | I11: 70 | J11: 145 | K11: 550 | L11: 15 | M11: 60 | N11: =SUM(H11:M11) -> 910 | O11: N/A | P11: 1749 | Q11: 18-23 days | R11: =IFERROR(N11+IF(ISNUMBER(O11),O11,0)+IF(ISNUMBER(P11),P11,0),"") -> 2659 | S11: Freetrans
A12: SHA-Manzanillo | B12: Yangzhou RSL | C12: Puebla | D12: SHA | E12: Manzanillo | F12: CIF | G12: 1 | H12: 70 | I12: 70 | J12: 145 | K12: 550 | L12: 15 | M12: 60 | N12: =SUM(H12:M12) -> 910 | O12: N/A | P12: 1749 | R12: =IFERROR(N12+IF(ISNUMBER(O12),O12,0)+IF(ISNUMBER(P12),P12,0),"") -> 2659 | S12: Freetrans
A13: SHA-Manzanillo | B13: Zhejiang Yuansheng | C13: Puebla | D13: SHA | E13: Manzanillo | F13: CIF | G13: 0.5 | H13: 70 | I13: 70 | J13: 145 | K13: 550 | L13: 15 | M13: 60 | N13: =SUM(H13:M13) -> 910 | O13: N/A | P13: 1749 | R13: =IFERROR(N13+IF(ISNUMBER(O13),O13,0)+IF(ISNUMBER(P13),P13,0),"") -> 2659 | S13: Freetrans
A14: SHA-Manzanillo | B14: Shanghai Huafon Coil | C14: Puebla | D14: SHA | E14: Manzanillo | F14: CIF | G14: 2 | H14: 70 | I14: 70 | J14: 145 | K14: 250 | L14: 15 | M14: 60 | N14: =SUM(H14:M14) -> 610 | O14: N/A | P14: 1749 | R14: =IFERROR(N14+IF(ISNUMBER(O14),O14,0)+IF(ISNUMBER(P14),P14,0),"") -> 2359 | S14: Freetrans
A15: SHA-Manzanillo | B15: Dalian ABIC | C15: Puebla | D15: SHA | E15: Manzanillo | F15: CIF | G15: 2 | H15: 70 | I15: 70 | J15: 145 | K15: 200 | L15: 15 | M15: 50 | N15: =SUM(H15:M15) -> 550 | O15: N/A | P15: 1749 | R15: =IFERROR(N15+IF(ISNUMBER(O15),O15,0)+IF(ISNUMBER(P15),P15,0),"") -> 2299 | S15: Freetrans
A16: SHA-Manzanillo | B16: Chongqing Boling | C16: Puebla | D16: SHA | E16: Manzanillo | F16: CIF | G16: 0.5 | H16: 70 | I16: 70 | J16: 145 | K16: 1550 | L16: 15 | M16: 60 | N16: =SUM(H16:M16) -> 1910 | O16: N/A | P16: 1749 | R16: =IFERROR(N16+IF(ISNUMBER(O16),O16,0)+IF(ISNUMBER(P16),P16,0),"") -> 3659 | S16: Freetrans
A17: SHA-Manzanillo | B17: AITD | C17: Saltillo | D17: SHA | E17: Manzanillo | F17: CIF | G17: 2 | H17: 70 | I17: 70 | J17: 145 | K17: 350 | L17: 15 | M17: 60 | N17: =SUM(H17:M17) -> 710 | O17: N/A | P17: 1749 | R17: =IFERROR(N17+IF(ISNUMBER(O17),O17,0)+IF(ISNUMBER(P17),P17,0),"") -> 2459 | S17: Freetrans
A18: SHA-Manzanillo | B18: Wuhu Bokang | C18: Saltillo | D18: SHA | E18: Manzanillo | F18: FOB | G18: 1 | H18: 70 | I18: 70 | J18: 145 | K18: 50 | L18: 15 | M18: 60 | N18: =SUM(H18:M18) -> 410 | O18: N/A | P18: 1749 | R18: =IFERROR(N18+IF(ISNUMBER(O18),O18,0)+IF(ISNUMBER(P18),P18,0),"") -> 2159 | S18: Freetrans
A19: SHA-Manzanillo | B19: Zhejiang Yida | C19: Puebla | D19: SHA | E19: Manzanillo | F19: CIF | G19: 1 | H19: 70 | I19: 70 | J19: 145 | K19: 550 | L19: 15 | M19: 60 | N19: =SUM(H19:M19) -> 910 | O19: N/A | P19: 1749 | R19: =IFERROR(N19+IF(ISNUMBER(O19),O19,0)+IF(ISNUMBER(P19),P19,0),"") -> 2659 | S19: Freetrans
A20: SHA-Manzanillo | B20: Nanjing PMC | C20: Saltillo | D20: SHA | E20: Manzanillo | F20: CIF | G20: 2 | H20: 70 | I20: 70 | J20: 145 | K20: 550 | L20: 15 | M20: 60 | N20: =SUM(H20:M20) -> 910 | O20: N/A | P20: 1749 | R20: =IFERROR(N20+IF(ISNUMBER(O20),O20,0)+IF(ISNUMBER(P20),P20,0),"") -> 2659 | S20: Freetrans
A21: SHA-Manzanillo | B21: Changsha Shenda | C21: Saltillo | D21: SHA | E21: Manzanillo | F21: CIF | G21: 2 | H21: 70 | I21: 70 | J21: 145 | K21: 1500 | L21: 15 | M21: 60 | N21: =SUM(H21:M21) -> 1860 | O21: N/A | P21: 1749 | R21: =IFERROR(N21+IF(ISNUMBER(O21),O21,0)+IF(ISNUMBER(P21),P21,0),"") -> 3609 | S21: Freetrans
A22: AIUS | USA (HOU / Detroit / Savanna) | 5 条航线 | 月需求 12 HQ40
A23: SHA-HOU | B23: AINT- 666 Wenchang Road, Tongzhou District, Nantong City | C23: Air International Thermal System-c/o GTZ WAREHOUSE LLC-662 SOUTH 33rd STREET, BUILDING-J, McALLEN, TX 78503 | D23: SHA | E23: HOU | F23: EXW | G23: 2 | H23: 70 | I23: 70 | J23: 140 | K23: 400 | L23: 10 | M23: 70 | N23: =SUM(H23:M23) -> 760 | O23: 2685 | P23: 2600 | Q23: 8-10 wks | R23: =IFERROR(N23+IF(ISNUMBER(O23),O23,0)+IF(ISNUMBER(P23),P23,0),"") -> 6045 | S23: KF
A24: SHA-Detroit | B24: AISH-108 Chunguang Road, Minhang District, Shanghai | C24: Air International Thermal Systems-c/o FTZ METRO WAREHOUSE-1200 E. McNICHOLS RD, HIGHLAND PARK, MI 48203 | D24: SHA | E24: Detroit | F24: EXW | G24: 1 | H24: 70 | I24: 70 | J24: 140 | K24: 250 | L24: 10 | M24: 70 | N24: =SUM(H24:M24) -> 610 | O24: 885 | P24: 4050 | R24: =IFERROR(N24+IF(ISNUMBER(O24),O24,0)+IF(ISNUMBER(P24),P24,0),"") -> 5545 | S24: KF
A25: Laem Chabang-Savanna | B25: Air International Thermal Systems (Thailand) Ltd. (Head Office) 500/46 Moo 3, WHA Eastern Seaboard Industrial Estate 1 Tambol Tasit, Amphur Pluak Daeng, Rayong 21140 Thailand | C25: Air International Thermal Systems 466 Baxter Lane Winchester, TN, USA, 37398 | D25: Laem Chabang | E25: Savanna | F25: DAP | G25: 3 | H25: 70 | I25: 70 | J25: 140 | K25: 300 | L25: 30 | M25: 70 | N25: =SUM(H25:M25) -> 680 | O25: 2785 | P25: 1900 | Q25: 8-10 wks | R25: =IFERROR(N25+IF(ISNUMBER(O25),O25,0)+IF(ISNUMBER(P25),P25,0),"") -> 5365 | S25: KF
A26: Nhava Sheva-Savanna | B26: Divine & Creative from India | C26: Air International Thermal Systems 466 Baxter Lane Winchester, TN, USA, 37398 | D26: Nhava Sheva | E26: Savanna | F26: DAP | G26: 3 | H26: 70 | I26: 80 | J26: 160 | K26: 1000 | L26: 50 | M26: 75 | N26: =SUM(H26:M26) -> 1435 | O26: 2785 | P26: 1750 | Q26: 7-9 wks | R26: =IFERROR(N26+IF(ISNUMBER(O26),O26,0)+IF(ISNUMBER(P26),P26,0),"") -> 5970 | S26: KF
A27: SHA-Savanna | B27: AINT- 666 Wenchang Road, Tongzhou District, Nantong City | C27: Air International Thermal Systems 466 Baxter Lane Winchester, TN, USA, 37398 | D27: SHA | E27: Savanna | F27: DAP | G27: 3 | H27: 70 | I27: 70 | J27: 140 | K27: 400 | L27: 10 | M27: 70 | N27: =SUM(H27:M27) -> 760 | O27: 2785 | P27: 1300 | Q27: 6-8 wks | R27: =IFERROR(N27+IF(ISNUMBER(O27),O27,0)+IF(ISNUMBER(P27),P27,0),"") -> 4845 | S27: KF
A28: AISH | Asia → SHA (inbound) | 2 条航线 | 月需求 3 HQ40
A29: Bangkok-SHA | B29: DELTA ELECTRONICS (THAILAND) PUBLIC COMPANY LIMITED 111 MOO 9, BANGNA-TRAD RD., TAMBOL BANGWUA AMPHUR BANGPAKONG CHACHOENGSAO, 24180 THAILAND | C29: AINT- 666 Wenchang Road, Tongzhou District, Nantong City | D29: Bangkok | E29: SHA | F29: EXW | G29: 2 | H29: 70 | I29: 50 | J29: 260 | K29: 325 | L29: 90 | M29: 80 | N29: =SUM(H29:M29) -> 875 | O29: 600 | P29: 1 | Q29: 15-20 days | R29: =IFERROR(N29+IF(ISNUMBER(O29),O29,0)+IF(ISNUMBER(P29),P29,0),"") -> 1476 | S29: Superchain
A30: Incheon-SHA | B30: Woory Industrial Co., Ltd #531, Jigok-dong, Kihung-gu Yongin-city, Kyonggi-Do, Korea | C30: AINT- 666 Wenchang Road, Tongzhou District, Nantong City | D30: Incheon | E30: SHA | F30: EXW | G30: 1 | H30: 70 | I30: 35 | J30: 145 | K30: 350 | L30: 150 | M30: 50 | N30: =SUM(H30:M30) -> 800 | O30: 600 | P30: 1 | Q30: 5-10 days | R30: =IFERROR(N30+IF(ISNUMBER(O30),O30,0)+IF(ISNUMBER(P30),P30,0),"") -> 1401 | S30: Superchain
A31: AITH | Thailand (Laemchabang) | 5 条航线 | 月需求 11 HQ40
A32: SHA-Laemchabang | B32: Air International (Shanghai) Co., Ltd. No. 108 Chunguang Road, XinZhuang Industrial Zone, Minhang, Shanghai P.R. China 201108 | C32: Air International Thermal Systems (Thailand) Ltd. 41/17,18,19 MOO 8, T.BOWIN, A.SRIRACHA, CHONBURI, 20230 THAILAND | D32: SHA | E32: Laemchabang | F32: EXW | G32: 1 | H32: 70 | I32: 70 | J32: 140 | K32: 250 | L32: 10 | M32: 70 | N32: =SUM(H32:M32) -> 610 | O32: 800 | P32: 395 | Q32: 15-20 days | R32: =IFERROR(N32+IF(ISNUMBER(O32),O32,0)+IF(ISNUMBER(P32),P32,0),"") -> 1805 | S32: Rohlig
A33: SHA-Laemchabang | B33: Shanghai Huafon Aluminium Corp. 1111# Yuegong Road, Jinshan District, Shanghai 201506 | C33: Air International Thermal Systems (Thailand) Ltd. 500/46 Moo 3, WHA Eastern Seaboard Industrial Estate 1, T. Tasit, A. Pluekdaeng, Rayong 21140 | D33: SHA | E33: Laemchabang | F33: EXW | G33: 3 | H33: 70 | I33: 70 | J33: 140 | K33: 250 | L33: 10 | M33: 70 | N33: =SUM(H33:M33) -> 610 | O33: 800 | P33: 420 | Q33: 15-20 days | R33: =IFERROR(N33+IF(ISNUMBER(O33),O33,0)+IF(ISNUMBER(P33),P33,0),"") -> 1830 | S33: Rohlig
A34: Tianjin-Laemchabang | B34: Hyo Seong Electric (Toanjin) Co., Ltd No.99, Xi San Dao, Tianjin Airport Industrial Park, TPFTZ, Tianjin, P.R. China | C34: Air International Thermal Systems (Thailand) Ltd. 41/17,18,19 MOO 8, T.BOWIN, A.SRIRACHA, CHONBURI, 20230 THAILAND | D34: Tianjin | E34: Laemchabang | F34: EXW | G34: 0.5 | H34: 70 | I34: 70 | J34: 140 | K34: 420 | L34: 30 | M34: 70 | N34: =SUM(H34:M34) -> 800 | O34: 800 | P34: 205 | Q34: 18-23 days | R34: =IFERROR(N34+IF(ISNUMBER(O34),O34,0)+IF(ISNUMBER(P34),P34,0),"") -> 1805 | S34: Rohlig
A35: Dubai-Laemchabang | B35: OSE Industries LLC. Dubai Industrial Park, Office#103, First Floor, Building 1, Dubai Industrial City, Dubai, UAE, Post Box 126344 | C35: Air International Thermal Systems (Thailand) Ltd. 500/46 Moo 3, WHA Eastern Seaboard Industrial Estate 1, T. Tasit, A. Pluekdaeng, Rayong 21140 | D35: Dubai | E35: Laemchabang | F35: EXW | G35: 0.5 | H35: 70 | I35: 70 | J35: 140 | K35: 420 | L35: 30 | M35: 70 | N35: =SUM(H35:M35) -> 800 | O35: 800 | P35: - | Q35: 20-25 days | R35: =IFERROR(N35+IF(ISNUMBER(O35),O35,0)+IF(ISNUMBER(P35),P35,0),"") -> 1600 | S35: -
A36: Laemchabang-Hamburg | B36: Air International Thermal Systems (Thailand) Ltd. 500/46 Moo 3, WHA Eastern Seaboard Industrial Estate 1, T. Tasit, A. Pluekdaeng, Rayong 21140 | C36: Air International Thermal (Slovakia) s.r.o. Prologis Park Nitra, DC3 Cez panske 4289/9, 949 01 Nitra, Slovakia | D36: Laemchabang | E36: Hamburg | F36: DDP | G36: 6 | H36: 70 | I36: 70 | J36: 140 | K36: 300 | L36: 30 | M36: 70 | N36: =SUM(H36:M36) -> 680 | O36: 2200 | P36: 2590 | Q36: 9-10 wks | R36: =IFERROR(N36+IF(ISNUMBER(O36),O36,0)+IF(ISNUMBER(P36),P36,0),"") -> 5470 | S36: Bondex
A37: AISK | Slovakia (Hamburg) | 3 条航线 | 月需求 3.5 HQ40
A38: SHA-Hamburg | B38: AINT- 666 Wenchang Road, Tongzhou District, Nantong City, China | C38: Air International Thermal (Slovakia) s.r.o. Prologis Park Nitra, DC3 Cez panske 4289/9, 949 01 Nitra, Slovakia | D38: SHA | E38: Hamburg | F38: EXW | G38: 1 | H38: 70 | I38: 70 | J38: 140 | K38: 400 | L38: 10 | M38: 70 | N38: =SUM(H38:M38) -> 760 | O38: 2200 | P38: 2250 | Q38: 8-9 wks | R38: =IFERROR(N38+IF(ISNUMBER(O38),O38,0)+IF(ISNUMBER(P38),P38,0),"") -> 5210 | S38: Bestunit
A39: Nhava Sheva-Hamburg | B39: Divine tooling | C39: Air International Thermal (Slovakia) s.r.o. Prologis Park Nitra, DC3 Cez panske 4289/9, 949 01 Nitra, Slovakia | D39: Nhava Sheva | E39: Hamburg | F39: EXW | G39: 2 | H39: 70 | I39: 70 | J39: 140 | K39: 300 | L39: 250 | M39: 70 | N39: =SUM(H39:M39) -> 900 | O39: 2200 | P39: 3300 | Q39: 8-10 wks | R39: =IFERROR(N39+IF(ISNUMBER(O39),O39,0)+IF(ISNUMBER(P39),P39,0),"") -> 6400 | S39: Superchain
A40: Bangkok-Hamburg | B40: Delta Electronics | C40: Air International Thermal (Slovakia) s.r.o. Prologis Park Nitra, DC3 Cez panske 4289/9, 949 01 Nitra, Slovakia | D40: Bangkok | E40: Hamburg | F40: EXW | G40: 0.5 | H40: 70 | I40: 70 | J40: 140 | K40: 300 | L40: 250 | M40: 70 | N40: =SUM(H40:M40) -> 900 | O40: 2200 | P40: 3190 | Q40: 9-10 wks | R40: =IFERROR(N40+IF(ISNUMBER(O40),O40,0)+IF(ISNUMBER(P40),P40,0),"") -> 6290 | S40: Bondex

Sheet 26.1月
A1: Lane | B1: Consignor | C1: Consignee | D1: POL | E1: POD | F1: Incoterm | G1: HQ40 Demand | H1: Booking | I1: Doc | J1: THC | K1: Loading | L1: Customs | M1: B/L | N1: Local Subtotal | O1: Dest Subtotal | P1: Sea Freight | Q1: Transit Time | R1: Total (USD) | S1: Winning Forwarder
A2: AI-Turkey | Turkey (Izmit) | 2 条航线 | 月需求 20 HQ40
A3: SHA-Izmit | B3: AINT - 666 Wenchang Rd, Tongzhou, Nantong | C3: AI Termal Sistemleri A.Ş., İstanbul | D3: SHA | E3: Izmit | F3: DAP | G3: 16 | H3: 70 | I3: 70 | J3: 140 | K3: 400 | L3: 10 | M3: 70 | N3: =SUM(H3:M3) -> 760 | O3: 950 | P3: 3330 | Q3: 8-10 wks | R3: =IFERROR(N3+IF(ISNUMBER(O3),O3,0)+IF(ISNUMBER(P3),P3,0),"") -> 5040 | S3: Bestunit
A4: SAI-Izmit | B4: SAI - 3 Gaobao Lake East Rd, Yubei, Chongqing | C4: AI Termal Sistemleri A.Ş., İstanbul | D4: SHA | E4: Izmit | F4: EXW | G4: 4 | H4: 70 | I4: 70 | J4: 170 | K4: 250 | L4: 50 | M4: 50 | N4: =SUM(H4:M4) -> 660 | O4: 950 | P4: 4171 | Q4: 9-11 wks | R4: =IFERROR(N4+IF(ISNUMBER(O4),O4,0)+IF(ISNUMBER(P4),P4,0),"") -> 5781 | S4: Bestunit
A5: AIMX | Mexico (Manzanillo) | 17 条航线 | 月需求 31 HQ40
A6: Laem-Manzanillo | B6: AITH | C6: Puebla + Saltillo | D6: Laemchabang | E6: MANZANILLO | F6: CIF | G6: 9 | H6: 70 | I6: 50 | J6: 260 | K6: 250 | L6: 90 | M6: 80 | N6: =SUM(H6:M6) -> 800 | O6: N/A | P6: 1940 | Q6: 45-50 days | R6: =IFERROR(N6+IF(ISNUMBER(O6),O6,0)+IF(ISNUMBER(P6),P6,0),"") -> 2740 | S6: Bondex
A7: Bangkok-Manzanillo | B7: DELTA | C7: Saltillo | D7: Bangkok | E7: MANZANILLO | F7: CIF | G7: 2 | H7: 70 | I7: 50 | J7: 260 | K7: 325 | L7: 90 | M7: 80 | N7: =SUM(H7:M7) -> 875 | O7: N/A | P7: 1940 | Q7: 35-45 days | R7: =IFERROR(N7+IF(ISNUMBER(O7),O7,0)+IF(ISNUMBER(P7),P7,0),"") -> 2815 | S7: Bondex
A8: Laem-Manzanillo (TNC) | B8: TNC | C8: Puebla | D8: Laemchabang | E8: MANZANILLO | F8: CIF | G8: 1 | H8: 70 | I8: 50 | J8: 260 | K8: 250 | L8: 90 | M8: 80 | N8: =SUM(H8:M8) -> 800 | O8: N/A | P8: 1940 | Q8: 35-45 days | R8: =IFERROR(N8+IF(ISNUMBER(O8),O8,0)+IF(ISNUMBER(P8),P8,0),"") -> 2740 | S8: Bondex
A9: Nhava-Manzanillo | B9: Creative Components | C9: Saltillo | D9: Nhava Sheva | E9: MANZANILLO | F9: CIF | G9: 2 | H9: 70 | I9: 80 | J9: 160 | K9: 1000 | L9: 50 | M9: 75 | N9: =SUM(H9:M9) -> 1435 | O9: N/A | P9: 2800 | Q9: 50-55 days | R9: =IFERROR(N9+IF(ISNUMBER(O9),O9,0)+IF(ISNUMBER(P9),P9,0),"") -> 4235 | S9: Bondex
A10: Incheon-Manzanillo | B10: WOORY | C10: Saltillo | D10: INCHEON | E10: MANZANILLO | F10: CIF | G10: 1 | H10: 70 | I10: 35 | J10: 145 | K10: 350 | L10: 150 | M10: 50 | N10: =SUM(H10:M10) -> 800 | O10: N/A | P10: 2340 | Q10: 25-30 days | R10: =IFERROR(N10+IF(ISNUMBER(O10),O10,0)+IF(ISNUMBER(P10),P10,0),"") -> 3140 | S10: Bondex
A11: SHA-Manzanillo (Chao Li) | B11: Jiangsu Chao Li | C11: Puebla | D11: SHA | E11: MANZANILLO | F11: FOB | G11: 2 | H11: 70 | I11: 70 | J11: 145 | K11: 550 | L11: 15 | M11: 60 | N11: =SUM(H11:M11) -> 910 | O11: N/A | P11: 1840 | Q11: 18-23 days | R11: =IFERROR(N11+IF(ISNUMBER(O11),O11,0)+IF(ISNUMBER(P11),P11,0),"") -> 2750 | S11: Bondex
A12: SHA-Manzanillo (Yangzhou) | B12: Yangzhou RSL | C12: Puebla | D12: SHA | E12: MANZANILLO | F12: CIF | G12: 1 | H12: 70 | I12: 70 | J12: 145 | K12: 550 | L12: 15 | M12: 60 | N12: =SUM(H12:M12) -> 910 | O12: N/A | P12: 1840 | Q12: 18-23 days | R12: =IFERROR(N12+IF(ISNUMBER(O12),O12,0)+IF(ISNUMBER(P12),P12,0),"") -> 2750 | S12: Bondex
A13: SHA-Manzanillo (Yuansheng) | B13: Zhejiang Yuansheng | C13: Puebla | D13: SHA | E13: MANZANILLO | F13: CIF | G13: 0.5 | H13: 70 | I13: 70 | J13: 145 | K13: 550 | L13: 15 | M13: 60 | N13: =SUM(H13:M13) -> 910 | O13: N/A | P13: 1840 | Q13: 18-23 days | R13: =IFERROR(N13+IF(ISNUMBER(O13),O13,0)+IF(ISNUMBER(P13),P13,0),"") -> 2750 | S13: Bondex
A14: SHA-Manzanillo (Huafon Coil) | B14: Shanghai Huafon Coil | C14: Puebla | D14: SHA | E14: MANZANILLO | F14: CIF | G14: 2 | H14: 70 | I14: 70 | J14: 145 | K14: 250 | L14: 15 | M14: 60 | N14: =SUM(H14:M14) -> 610 | O14: N/A | P14: 1840 | Q14: 18-23 days | R14: =IFERROR(N14+IF(ISNUMBER(O14),O14,0)+IF(ISNUMBER(P14),P14,0),"") -> 2450 | S14: Bondex
A15: SHA-Manzanillo (ABIC) | B15: Dalian ABIC | C15: Puebla | D15: SHA | E15: MANZANILLO | F15: CIF | G15: 2 | H15: 70 | I15: 70 | J15: 145 | K15: 200 | L15: 15 | M15: 50 | N15: =SUM(H15:M15) -> 550 | O15: N/A | P15: 1840 | Q15: 18-23 days | R15: =IFERROR(N15+IF(ISNUMBER(O15),O15,0)+IF(ISNUMBER(P15),P15,0),"") -> 2390 | S15: Bondex
A16: SHA-Manzanillo (Boling) | B16: Chongqing Boling | C16: Puebla | D16: SHA | E16: MANZANILLO | F16: CIF | G16: 0.5 | H16: 70 | I16: 70 | J16: 145 | K16: 1550 | L16: 15 | M16: 60 | N16: =SUM(H16:M16) -> 1910 | O16: N/A | P16: 1840 | Q16: 18-23 days | R16: =IFERROR(N16+IF(ISNUMBER(O16),O16,0)+IF(ISNUMBER(P16),P16,0),"") -> 3750 | S16: Bondex
A17: SHA-Manzanillo (AITD) | B17: AITD | C17: Saltillo | D17: SHA | E17: MANZANILLO | F17: CIF | G17: 1 | H17: 70 | I17: 70 | J17: 145 | K17: 350 | L17: 15 | M17: 60 | N17: =SUM(H17:M17) -> 710 | O17: N/A | P17: 1840 | Q17: 18-23 days | R17: =IFERROR(N17+IF(ISNUMBER(O17),O17,0)+IF(ISNUMBER(P17),P17,0),"") -> 2550 | S17: Bondex
... A22: SHA-Manzanillo (Shenda) | B22: Changsha Shenda | C22: Saltillo | D22: SHA | E22: MANZANILLO | F22: CIF | G22: 2 | H22: 70 | I22: 70 | J22: 145 | K22: 1500 | L22: 15 | M22: 60 | N22: =SUM(H22:M22) -> 1860 | O22: N/A | P22: 1840 | Q22: 18-23 days | R22: =IFERROR(N22+IF(ISNUMBER(O22),O22,0)+IF(ISNUMBER(P22),P22,0),"") -> 3700 | S22: Bondex
A23: AIUS | USA (HOU / Detroit / Savanna) | 5 条航线 | 月需求 14 HQ40
A24: SHA-HOU | B24: AINT - 666 Wenchang Rd, Tongzhou, Nantong | C24: AI Thermal System, GTZ Warehouse, McAllen TX | D24: SHA | E24: HOU | F24: EXW | G24: 2 | H24: 70 | I24: 70 | J24: 140 | K24: 400 | L24: 10 | M24: 70 | N24: =SUM(H24:M24) -> 760 | O24: 2685 | P24: 2390 | Q24: 8-10 wks | R24: =IFERROR(N24+IF(ISNUMBER(O24),O24,0)+IF(ISNUMBER(P24),P24,0),"") -> 5835 | S24: Bondex
A25: SHA-Detroit | B25: AISH - 108 Chunguang Rd, Minhang, Shanghai | C25: AI Thermal Systems, FTZ Metro Warehouse, Highland Park MI | D25: SHA | E25: Detroit | F25: EXW | G25: 2 | H25: 70 | I25: 70 | J25: 140 | K25: 250 | L25: 10 | M25: 70 | N25: =SUM(H25:M25) -> 610 | O25: 885 | P25: 3640 | R25: =IFERROR(N25+IF(ISNUMBER(O25),O25,0)+IF(ISNUMBER(P25),P25,0),"") -> 5135 | S25: Bondex
A26: Laem-Savanna | B26: AI Thermal Systems (Thailand) Ltd., Rayong | C26: AI Thermal Systems, 466 Baxter Lane, Winchester TN | D26: Laemchabang | E26: Savanna | F26: DAP | G26: 4 | H26: 70 | I26: 70 | J26: 140 | K26: 300 | L26: 30 | M26: 70 | N26: =SUM(H26:M26) -> 680 | O26: 2785 | P26: 2140 | Q26: 8-10 wks | R26: =IFERROR(N26+IF(ISNUMBER(O26),O26,0)+IF(ISNUMBER(P26),P26,0),"") -> 5605 | S26: Freetrans
A27: Nhava-Savanna | B27: Divine & Creative from India | C27: AI Thermal Systems, 466 Baxter Lane, Winchester TN | D27: Nhava Sheva | E27: Savanna | F27: DAP | G27: 3 | H27: 70 | I27: 80 | J27: 160 | K27: 1000 | L27: 50 | M27: 75 | N27: =SUM(H27:M27) -> 1435 | O27: 2785 | P27: 2490 | Q27: 7-9 wks | R27: =IFERROR(N27+IF(ISNUMBER(O27),O27,0)+IF(ISNUMBER(P27),P27,0),"") -> 6710 | S27: Freetrans
A28: SHA-Savanna | B28: AINT - 666 Wenchang Rd, Tongzhou, Nantong | C28: AI Thermal Systems, 466 Baxter Lane, Winchester TN | D28: SHA | E28: Savanna | F28: DAP | G28: 3 | H28: 70 | I28: 70 | J28: 140 | K28: 400 | L28: 10 | M28: 70 | N28: =SUM(H28:M28) -> 760 | O28: 2785 | P28: 2247 | Q28: 6-8 wks | R28: =IFERROR(N28+IF(ISNUMBER(O28),O28,0)+IF(ISNUMBER(P28),P28,0),"") -> 5792 | S28: Freetrans
A29: AISH | Asia → SHA (inbound) | 2 条航线 | 月需求 3 HQ40
A30: Bangkok-SHA | B30: Delta Electronics (Thailand), Chachoengsao | C30: AINT - 666 Wenchang Rd, Tongzhou, Nantong | D30: Bangkok | E30: SHA | F30: EXW | G30: 2 | H30: 70 | I30: 50 | J30: 260 | K30: 325 | L30: 90 | M30: 80 | N30: =SUM(H30:M30) -> 875 | O30: 600 | P30: 1 | Q30: 15-20 days | R30: =IFERROR(N30+IF(ISNUMBER(O30),O30,0)+IF(ISNUMBER(P30),P30,0),"") -> 1476 | S30: Superchain
A31: Incheon-SHA | B31: Woory Industrial Co., Yongin Korea | C31: AINT - 666 Wenchang Rd, Tongzhou, Nantong | D31: INCHEON | E31: SHA | F31: EXW | G31: 1 | H31: 70 | I31: 35 | J31: 145 | K31: 350 | L31: 150 | M31: 50 | N31: =SUM(H31:M31) -> 800 | O31: 600 | P31: 1 | Q31: 5-10 days | R31: =IFERROR(N31+IF(ISNUMBER(O31),O31,0)+IF(ISNUMBER(P31),P31,0),"") -> 1401 | S31: Superchain
A32: AITH | Thailand (Laemchabang) | 5 条航线 | 月需求 11 HQ40
A33: SHA-Laem | B33: AI (Shanghai), Minhang | C33: AI Thermal Systems (Thailand), Chonburi | D33: SHA | E33: Laemchabang | F33: EXW | G33: 1 | H33: 70 | I33: 70 | J33: 140 | K33: 250 | L33: 10 | M33: 70 | N33: =SUM(H33:M33) -> 610 | O33: 800 | P33: 1140 | Q33: 15-20 days | R33: =IFERROR(N33+IF(ISNUMBER(O33),O33,0)+IF(ISNUMBER(P33),P33,0),"") -> 2550 | S33: Bondex
A34: SHA-Laem (Huafon) | B34: Shanghai Huafon Aluminium, Jinshan | C34: AI Thermal Systems (Thailand), Rayong | D34: SHA | E34: Laemchabang | F34: EXW | G34: 3 | H34: 70 | I34: 70 | J34: 140 | K34: 250 | L34: 10 | M34: 70 | N34: =SUM(H34:M34) -> 610 | O34: 800 | P34: 1140 | Q34: 15-20 days | R34: =IFERROR(N34+IF(ISNUMBER(O34),O34,0)+IF(ISNUMBER(P34),P34,0),"") -> 2550 | S34: Bondex
A35: Tianjin-Laem | B35: Hyo Seong Electric (Tianjin) | C35: AI Thermal Systems (Thailand), Chonburi | D35: Tianjin | E35: Laemchabang | F35: EXW | G35: 0.5 | H35: 70 | I35: 70 | J35: 140 | K35: 420 | L35: 30 | M35: 70 | N35: =SUM(H35:M35) -> 800 | O35: 800 | P35: 1340 | Q35: 18-23 days | R35: =IFERROR(N35+IF(ISNUMBER(O35),O35,0)+IF(ISNUMBER(P35),P35,0),"") -> 2940 | S35: Bondex
A36: Dubai-Laem | B36: OSE Industries LLC, Dubai | C36: AI Thermal Systems (Thailand), Rayong | D36: Dubai | E36: Laemchabang | F36: EXW | G36: 0.5 | H36: 70 | I36: 70 | J36: 140 | K36: 420 | L36: 30 | M36: 70 | N36: =SUM(H36:M36) -> 800 | O36: 800 | P36: - | Q36: 20-25 days | R36: =IFERROR(N36+IF(ISNUMBER(O36),O36,0)+IF(ISNUMBER(P36),P36,0),"") -> 1600
A37: Laem-Hamburg | B37: AI Thermal Systems (Thailand), Rayong | C37: AI Thermal (Slovakia), Nitra | D37: Laemchabang | E37: Hamburg | F37: DDP | G37: 6 | H37: 70 | I37: 70 | J37: 140 | K37: 300 | L37: 30 | M37: 70 | N37: =SUM(H37:M37) -> 680 | O37: 2200 | P37: 3490 | Q37: 9-10 wks | R37: =IFERROR(N37+IF(ISNUMBER(O37),O37,0)+IF(ISNUMBER(P37),P37,0),"") -> 6370 | S37: Bondex
A38: AISK | Slovakia (Hamburg) | 3 条航线 | 月需求 3.5 HQ40
A39: SHA-Hamburg | B39: AINT - 666 Wenchang Rd, Tongzhou, Nantong | C39: AI Thermal (Slovakia), Nitra | D39: SHA | E39: Hamburg | F39: EXW | G39: 1 | H39: 70 | I39: 70 | J39: 140 | K39: 400 | L39: 10 | M39: 70 | N39: =SUM(H39:M39) -> 760 | O39: 2200 | P39: 2200 | Q39: 8-9 wks | R39: =IFERROR(N39+IF(ISNUMBER(O39),O39,0)+IF(ISNUMBER(P39),P39,0),"") -> 5160 | S39: Bestunit
A40: Nhava-Hamburg | B40: Divine tooling | C40: AI Thermal (Slovakia), Nitra | D40: Nhava Sheva | E40: Hamburg | F40: EXW | G40: 2 | H40: 70 | I40: 70 | J40: 140 | K40: 300 | L40: 250 | M40: 70 | N40: =SUM(H40:M40) -> 900 | O40: 2200 | P40: 1900 | Q40: 8-10 wks | R40: =IFERROR(N40+IF(ISNUMBER(O40),O40,0)+IF(ISNUMBER(P40),P40,0),"") -> 5000 | S40: Bestunit
A41: Bangkok-Hamburg | B41: Delta Electronics | C41: AI Thermal (Slovakia), Nitra | D41: Bangkok | E41: Hamburg | F41: EXW | G41: 0.5 | H41: 70 | I41: 70 | J41: 140 | K41: 300 | L41: 250 | M41: 70 | N41: =SUM(H41:M41) -> 900 | O41: 2200 | P41: 2690 | Q41: 9-10 wks | R41: =IFERROR(N41+IF(ISNUMBER(O41),O41,0)+IF(ISNUMBER(P41),P41,0),"") -> 5790 | S41: Bondex

Sheet 26.2月
A1: Lane | B1: Consignor | C1: Consignee | D1: POL | E1: POD | F1: Incoterm | G1: HQ40 Demand | H1: Booking | I1: Doc | J1: THC | K1: Loading | L1: Customs | M1: B/L | N1: Local Subtotal | O1: Dest Subtotal | P1: Sea Freight | Q1: Transit Time | R1: Total (USD) | S1: Winning Forwarder
A2: AI-Turkey | Turkey (Izmit) | 2 条航线 | 月需求 9 HQ40
A3: SHA-Izmit | B3: AINT - 666 Wenchang Rd, Tongzhou, Nantong | C3: AI Termal Sistemleri A.Ş., İstanbul | D3: SHA | E3: Izmit | F3: DAP | G3: 8 | H3: 70 | I3: 70 | J3: 140 | K3: 400 | L3: 10 | M3: 70 | N3: =SUM(H3:M3) -> 760 | O3: 950 | P3: 4000 | Q3: 8-10 wks | R3: =IFERROR(N3+IF(ISNUMBER(O3),O3,0)+IF(ISNUMBER(P3),P3,0),"") -> 5710 | S3: Bestunit/Holiton
A4: SAI-Izmit | B4: SAI - 3 Gaobao Lake East Rd, Yubei, Chongqing | C4: AI Termal Sistemleri A.Ş., İstanbul | D4: SHA | E4: Izmit | F4: EXW | G4: 1 | H4: 70 | I4: 70 | J4: 170 | K4: 250 | L4: 50 | M4: 50 | N4: =SUM(H4:M4) -> 660 | O4: 950 | P4: 5000 | Q4: 10-12 wks | R4: =IFERROR(N4+IF(ISNUMBER(O4),O4,0)+IF(ISNUMBER(P4),P4,0),"") -> 6610 | S4: Bestunit
A5: AIMX | Mexico (Manzanillo) | 17 条航线 | 月需求 15.5 HQ40
A6: Laem-Manzanillo | B6: AITH | C6: Puebla + Saltillo | D6: Laemchabang | E6: MANZANILLO | F6: CIF | G6: 4 | H6: 70 | I6: 50 | J6: 260 | K6: 250 | L6: 90 | M6: 80 | N6: =SUM(H6:M6) -> 800 | O6: N/A | P6: 1200 | Q6: 35-45 days | R6: =IFERROR(N6+IF(ISNUMBER(O6),O6,0)+IF(ISNUMBER(P6),P6,0),"") -> 2000 | S6: Freetrans
A7: Bangkok-Manzanillo | B7: DELTA | C7: Saltillo | D7: Bangkok | E7: MANZANILLO | F7: CIF | G7: 1 | H7: 70 | I7: 50 | J7: 260 | K7: 325 | L7: 90 | M7: 80 | N7: =SUM(H7:M7) -> 875 | O7: N/A | P7: 1200 | Q7: 35-45 days | R7: =IFERROR(N7+IF(ISNUMBER(O7),O7,0)+IF(ISNUMBER(P7),P7,0),"") -> 2075 | S7: Freetrans
A8: Laem-Manzanillo (TNC) | B8: TNC | C8: Puebla | D8: Laemchabang | E8: MANZANILLO | F8: CIF | G8: 0.5 | H8: 70 | I8: 50 | J8: 260 | K8: 250 | L8: 90 | M8: 80 | N8: =SUM(H8:M8) -> 800 | O8: N/A | P8: 1200 | Q8: 35-45 days | R8: =IFERROR(N8+IF(ISNUMBER(O8),O8,0)+IF(ISNUMBER(P8),P8,0),"") -> 2000 | S8: Freetrans
A9: Nhava-Manzanillo | B9: Creative Components | C9: Saltillo | D9: Nhava Sheva | E9: MANZANILLO | F9: CIF | G9: 1 | H9: 70 | I9: 80 | J9: 160 | K9: 1000 | L9: 50 | M9: 75 | N9: =SUM(H9:M9) -> 1435 | O9: N/A | P9: 2150 | Q9: 50-55 days | R9: =IFERROR(N9+IF(ISNUMBER(O9),O9,0)+IF(ISNUMBER(P9),P9,0),"") -> 3585 | S9: Bondex
A10: Incheon-Manzanillo | B10: WOORY | C10: Saltillo | D10: INCHEON | E10: MANZANILLO | F10: CIF | G10: 0.5 | H10: 70 | I10: 35 | J10: 145 | K10: 350 | L10: 150 | M10: 50 | N10: =SUM(H10:M10) -> 800 | O10: N/A | P10: 2150 | Q10: 25-30 days | R10: =IFERROR(N10+IF(ISNUMBER(O10),O10,0)+IF(ISNUMBER(P10),P10,0),"") -> 2950 | S10: Bondex
A11: SHA-Manzanillo (Chao Li) | B11: Jiangsu Chao Li | C11: Puebla | D11: SHA | E11: MANZANILLO | F11: FOB | G11: 1 | H11: 70 | I11: 70 | J11: 145 | K11: 550 | L11: 15 | M11: 60 | N11: =SUM(H11:M11) -> 910 | O11: N/A | P11: 1200 | Q11: 18-23 days | R11: =IFERROR(N11+IF(ISNUMBER(O11),O11,0)+IF(ISNUMBER(P11),P11,0),"") -> 2110 | S11: Bondex
A12: SHA-Manzanillo (Yangzhou) | B12: Yangzhou RSL | C12: Puebla | D12: SHA | E12: MANZANILLO | F12: CIF | G12: 0.5 | H12: 70 | I12: 70 | J12: 145 | K12: 550 | L12: 15 | M12: 60 | N12: =SUM(H12:M12) -> 910 | O12: N/A | P12: 1200 | Q12: 18-23 days | R12: =IFERROR(N12+IF(ISNUMBER(O12),O12,0)+IF(ISNUMBER(P12),P12,0),"") -> 2110 | S12: Bondex
A13: SHA-Manzanillo (Yuansheng) | B13: Zhejiang Yuansheng | C13: Puebla | D13: SHA | E13: MANZANILLO | F13: CIF | G13: 0.5 | H13: 70 | I13: 70 | J13: 145 | K13: 550 | L13: 15 | M13: 60 | N13: =SUM(H13:M13) -> 910 | O13: N/A | P13: 1200 | Q13: 18-23 days | R13: =IFERROR(N13+IF(ISNUMBER(O13),O13,0)+IF(ISNUMBER(P13),P13,0),"") -> 2110 | S13: Bondex
A14: SHA-Manzanillo (Huafon Coil) | B14: Shanghai Huafon Coil | C14: Puebla | D14: SHA | E14: MANZANILLO | F14: CIF | G14: 1 | H14: 70 | I14: 70 | J14: 145 | K14: 250 | L14: 15 | M14: 60 | N14: =SUM(H14:M14) -> 610 | O14: N/A | P14: 1200 | Q14: 18-23 days | R14: =IFERROR(N14+IF(ISNUMBER(O14),O14,0)+IF(ISNUMBER(P14),P14,0),"") -> 1810 | S14: Bondex
A15: SHA-Manzanillo (ABIC) | B15: Dalian ABIC | C15: Puebla | D15: SHA | E15: MANZANILLO | F15: CIF | G15: 1 | H15: 70 | I15: 70 | J15: 145 | K15: 200 | L15: 15 | M15: 50 | N15: =SUM(H15:M15) -> 550 | O15: N/A | P15: 1200 | Q15: 18-23 days | R15: =IFERROR(N15+IF(ISNUMBER(O15),O15,0)+IF(ISNUMBER(P15),P15,0),"") -> 1750 | S15: Bondex
A16: SHA-Manzanillo (Boling) | B16: Chongqing Boling | C16: Puebla | D16: SHA | E16: MANZANILLO | F16: CIF | G16: 0.5 | H16: 70 | I16: 70 | J16: 145 | K16: 1550 | L16: 15 | M16: 60 | N16: =SUM(H16:M16) -> 1910 | O16: N/A | P16: 1200 | Q16: 18-23 days | R16: =IFERROR(N16+IF(ISNUMBER(O16),O16,0)+IF(ISNUMBER(P16),P16,0),"") -> 3110 | S16: Bondex
A17: SHA-Manzanillo (AITD) | B17: AITD | C17: Saltillo | D17: SHA | E17: MANZANILLO | F17: CIF | G17: 0.5 | H17: 70 | I17: 70 | J17: 145 | K17: 350 | L17: 15 | M17: 60 | N17: =SUM(H17:M17) -> 710 | O17: N/A | P17: 1200 | Q17: 18-23 days | R17: =IFERROR(N17+IF(ISNUMBER(O17),O17,0)+IF(ISNUMBER(P17),P17,0),"") -> 1910 | S17: Bondex
... A22: SHA-Manzanillo (Shenda) | B22: Changsha Shenda | C22: Saltillo | D22: SHA | E22: MANZANILLO | F22: CIF | G22: 1 | H22: 70 | I22: 70 | J22: 145 | K22: 1500 | L22: 15 | M22: 60 | N22: =SUM(H22:M22) -> 1860 | O22: N/A | P22: 1200 | Q22: 18-23 days | R22: =IFERROR(N22+IF(ISNUMBER(O22),O22,0)+IF(ISNUMBER(P22),P22,0),"") -> 3060 | S22: Bondex
A23: AIUS | USA (HOU / Detroit / Savanna) | 5 条航线 | 月需求 3.5 HQ40
A24: SHA-HOU | B24: AINT - 666 Wenchang Rd, Tongzhou, Nantong | C24: GTZ WAREHOUSE LLC, McALLEN, TX | D24: SHA | E24: HOU | F24: EXW | G24: 1 | H24: 70 | I24: 70 | J24: 140 | K24: 400 | L24: 10 | M24: 70 | N24: =SUM(H24:M24) -> 760 | O24: 2685 | P24: 2450 | Q24: 6-8 wks | R24: =IFERROR(N24+IF(ISNUMBER(O24),O24,0)+IF(ISNUMBER(P24),P24,0),"") -> 5895 | S24: Bondex
A25: SHA-Detroit | B25: AISH - 108 Chunguang Rd, Minhang, Shanghai | C25: FTZ METRO WAREHOUSE, HIGHLAND PARK, MI | D25: SHA | E25: Detroit | F25: EXW | G25: 0 | H25: 70 | I25: 70 | J25: 140 | K25: 250 | L25: 10 | M25: 70 | N25: =SUM(H25:M25) -> 610 | O25: 885 | P25: 3750 | Q25: 6-8 wks | R25: =IFERROR(N25+IF(ISNUMBER(O25),O25,0)+IF(ISNUMBER(P25),P25,0),"") -> 5245 | S25: Bondex
A26: Laem-Savanna | B26: AITH (Thailand) | C26: AIUS Baxter, Winchester, TN | D26: Laem Chabang | E26: Savanna | F26: DAP | G26: 1 | H26: 70 | I26: 70 | J26: 140 | K26: 300 | L26: 30 | M26: 70 | N26: =SUM(H26:M26) -> 680 | O26: 2785 | P26: 2500 | Q26: 8-10 wks | R26: =IFERROR(N26+IF(ISNUMBER(O26),O26,0)+IF(ISNUMBER(P26),P26,0),"") -> 5965 | S26: Freetrans
A27: Nhava-Savanna | B27: Divine & Creative (India) | C27: AIUS Baxter, Winchester, TN | D27: Nhava Sheva | E27: Savanna | F27: DAP | G27: 0.5 | H27: 70 | I27: 80 | J27: 160 | K27: 1000 | L27: 50 | M27: 75 | N27: =SUM(H27:M27) -> 1435 | O27: 2785 | P27: 1950 | Q27: 7-9 wks | R27: =IFERROR(N27+IF(ISNUMBER(O27),O27,0)+IF(ISNUMBER(P27),P27,0),"") -> 6170 | S27: Freetrans
A28: SHA-Savanna | B28: AINT - 666 Wenchang Rd, Tongzhou, Nantong | C28: AIUS Baxter, Winchester, TN | D28: SHA | E28: Savanna | F28: DAP | G28: 1 | H28: 70 | I28: 70 | J28: 140 | K28: 400 | L28: 10 | M28: 70 | N28: =SUM(H28:M28) -> 760 | O28: 2785 | P28: 2200 | Q28: 6-8 wks | R28: =IFERROR(N28+IF(ISNUMBER(O28),O28,0)+IF(ISNUMBER(P28),P28,0),"") -> 5745 | S28: Freetrans
A29: AISH | Asia → SHA (inbound) | 2 条航线 | 月需求 2 HQ40
A30: Bangkok-SHA | B30: DELTA ELECTRONICS (Thailand) | C30: AINT - 666 Wenchang Rd, Tongzhou, Nantong | D30: Bangkok | E30: SHA | F30: EXW | G30: 1 | H30: 70 | I30: 50 | J30: 260 | K30: 325 | L30: 90 | M30: 80 | N30: =SUM(H30:M30) -> 875 | O30: 600 | P30: 1 | Q30: 15-20 days | R30: =IFERROR(N30+IF(ISNUMBER(O30),O30,0)+IF(ISNUMBER(P30),P30,0),"") -> 1476 | S30: Superchain
A31: Incheon-SHA | B31: Woory Industrial, Korea | C31: AINT - 666 Wenchang Rd, Tongzhou, Nantong | D31: INCHEON | E31: SHA | F31: EXW | G31: 1 | H31: 50 | I31: 35 | J31: 125 | K31: 280 | L31: 150 | M31: 50 | N31: =SUM(H31:M31) -> 690 | O31: 600 | P31: 1 | Q31: 5-10 days | R31: =IFERROR(N31+IF(ISNUMBER(O31),O31,0)+IF(ISNUMBER(P31),P31,0),"") -> 1291 | S31: Superchain
A32: AITH | Thailand (Laemchabang) | 5 条航线 | 月需求 4.5 HQ40
A33: SHA-Laem | B33: AISH - 108 Chunguang Rd, Minhang, Shanghai | C33: AITH, Chonburi 20230 Thailand | D33: SHA | E33: Laemchabang | F33: EXW | G33: 0.5 | H33: 70 | I33: 70 | J33: 140 | K33: 250 | L33: 10 | M33: 70 | N33: =SUM(H33:M33) -> 610 | O33: 800 | P33: 750 | Q33: 15-20 days | R33: =IFERROR(N33+IF(ISNUMBER(O33),O33,0)+IF(ISNUMBER(P33),P33,0),"") -> 2160 | S33: Superchain/Bondex
A34: SHA-Laem (Huafon) | B34: Shanghai Huafon Aluminium Corp. | C34: AITH, Rayong 21140 Thailand | D34: SHA | E34: Laemchabang | F34: EXW | G34: 1 | H34: 70 | I34: 70 | J34: 140 | K34: 250 | L34: 10 | M34: 70 | N34: =SUM(H34:M34) -> 610 | O34: 800 | P34: 750 | Q34: 15-20 days | R34: =IFERROR(N34+IF(ISNUMBER(O34),O34,0)+IF(ISNUMBER(P34),P34,0),"") -> 2160 | S34: Superchain/Bondex
A35: Tianjin-Laem | B35: Hyo Seong Electric (Tianjin) | C35: AITH, Chonburi 20230 Thailand | D35: Tianjin | E35: Laemchabang | F35: EXW | G35: 0.5 | H35: 70 | I35: 70 | J35: 140 | K35: 420 | L35: 30 | M35: 70 | N35: =SUM(H35:M35) -> 800 | O35: 800 | P35: 1150 | Q35: 18-23 days | R35: =IFERROR(N35+IF(ISNUMBER(O35),O35,0)+IF(ISNUMBER(P35),P35,0),"") -> 2750 | S35: Bondex
A36: Dubai-Laem | B36: OSE Industries LLC, Dubai | C36: AITH, Rayong 21140 Thailand | D36: Dubai | E36: Laemchabang | F36: EXW | G36: 0.5 | H36: 70 | I36: 70 | J36: 140 | K36: 420 | L36: 30 | M36: 70 | N36: =SUM(H36:M36) -> 800 | O36: 800 | P36: 1000 | Q36: 20-25 days | R36: =IFERROR(N36+IF(ISNUMBER(O36),O36,0)+IF(ISNUMBER(P36),P36,0),"") -> 2600 | S36: Kaifu
A37: Laem-Hamburg | B37: AITH, Rayong 21140 Thailand | C37: AISK, Nitra, Slovakia | D37: Laemchabang | E37: Hamburg | F37: DDP | G37: 2 | H37: 70 | I37: 70 | J37: 140 | K37: 300 | L37: 30 | M37: 70 | N37: =SUM(H37:M37) -> 680 | O37: 2200 | P37: 3800 | Q37: 9-10 wks | R37: =IFERROR(N37+IF(ISNUMBER(O37),O37,0)+IF(ISNUMBER(P37),P37,0),"") -> 6680 | S37: Bondex
A38: AISK | Slovakia (Hamburg) | 3 条航线 | 月需求 2 HQ40
A39: SHA-Hamburg | B39: AINT - 666 Wenchang Rd, Tongzhou, Nantong | C39: AISK, Nitra, Slovakia | D39: SHA | E39: Hamburg | F39: EXW | G39: 0.5 | H39: 70 | I39: 70 | J39: 140 | K39: 400 | L39: 10 | M39: 70 | N39: =SUM(H39:M39) -> 760 | O39: 2200 | P39: 2750 | Q39: 8-9 wks | R39: =IFERROR(N39+IF(ISNUMBER(O39),O39,0)+IF(ISNUMBER(P39),P39,0),"") -> 5710 | S39: Kaifu
A40: Nhava-Hamburg | B40: Divine Tooling | C40: AISK, Nitra, Slovakia | D40: Nhava Sheva | E40: Hamburg | F40: EXW | G40: 1 | H40: 70 | I40: 70 | J40: 140 | K40: 300 | L40: 250 | M40: 70 | N40: =SUM(H40:M40) -> 900 | O40: 2200 | P40: 2500 | Q40: 8-10 wks | R40: =IFERROR(N40+IF(ISNUMBER(O40),O40,0)+IF(ISNUMBER(P40),P40,0),"") -> 5600 | S40: Kaifu
A41: Bangkok-Hamburg | B41: Delta Electronics | C41: AISK, Nitra, Slovakia | D41: Bangkok | E41: Hamburg | F41: EXW | G41: 0.5 | H41: 70 | I41: 70 | J41: 140 | K41: 300 | L41: 250 | M41: 70 | N41: =SUM(H41:M41) -> 900 | O41: 2200 | P41: 3800 | Q41: 9-10 wks | R41: =IFERROR(N41+IF(ISNUMBER(O41),O41,0)+IF(ISNUMBER(P41),P41,0),"") -> 6900 | S41: Bondex

Sheet 26.3月
A1: Lane | B1: Consignor | C1: Consignee | D1: POL | E1: POD | F1: Incoterm | G1: HQ40 Demand | H1: Booking | I1: Doc | J1: THC | K1: Loading | L1: Customs | M1: B/L | N1: Local Subtotal | O1: Dest Subtotal | P1: Sea Freight | Q1: Transit Time | R1: Total (USD) | S1: Winning Forwarder
A2: AI-Turkey | Turkey (Izmit) | 2 条航线 | 月需求 22 HQ40
A3: SHA-Izmit | B3: AINT - 666 Wenchang Rd, Tongzhou, Nantong | C3: AI Termal Sistemleri A.Ş., İstanbul | D3: SHA | E3: Izmit | F3: DAP | G3: 18 | H3: 70 | I3: 70 | J3: 140 | K3: 400 | L3: 10 | M3: 70 | N3: =SUM(H3:M3) -> 760 | O3: 950 | P3: 3727 | Q3: 10-12 wks | R3: =IFERROR(N3+IF(ISNUMBER(O3),O3,0)+IF(ISNUMBER(P3),P3,0),"") -> 5437 | S3: Holiton/Bestunit (CW11/12/13)
A4: SAI-Izmit | B4: SAI - 3 Gaobao Lake East Rd, Yubei, Chongqing | C4: AI Termal Sistemleri A.Ş., İstanbul | D4: SHA | E4: Izmit | F4: EXW | G4: 4 | H4: 70 | I4: 70 | J4: 170 | K4: 250 | L4: 50 | M4: 50 | N4: =SUM(H4:M4) -> 660 | O4: 950 | P4: 5327 | Q4: 11-13 wks | R4: =IFERROR(N4+IF(ISNUMBER(O4),O4,0)+IF(ISNUMBER(P4),P4,0),"") -> 6937 | S4: Bestunit
A5: AIMX | Mexico (Manzanillo) | 17 条航线 | 月需求 31 HQ40
A6: Laem-Manzanillo | B6: AITH | C6: Puebla + Saltillo | D6: Laemchabang | E6: MANZANILLO | F6: CIF | G6: 9 | H6: 70 | I6: 50 | J6: 260 | K6: 250 | L6: 90 | M6: 80 | N6: =SUM(H6:M6) -> 800 | O6: N/A | P6: 2120 | Q6: 35-45 days | R6: =IFERROR(N6+IF(ISNUMBER(O6),O6,0)+IF(ISNUMBER(P6),P6,0),"") -> 2920 | S6: Kaifu
A7: Bangkok-Manzanillo | B7: DELTA | C7: Saltillo | D7: Bangkok | E7: MANZANILLO | F7: CIF | G7: 2 | H7: 70 | I7: 50 | J7: 260 | K7: 325 | L7: 90 | M7: 80 | N7: =SUM(H7:M7) -> 875 | O7: N/A | P7: 2000 | Q7: — | R7: =IFERROR(N7+IF(ISNUMBER(O7),O7,0)+IF(ISNUMBER(P7),P7,0),"") -> 2875 | S7: Kaifu
A8: Laem-Manzanillo (TNC) | B8: TNC | C8: Puebla | D8: Laemchabang | E8: MANZANILLO | F8: CIF | G8: 1 | H8: 70 | I8: 50 | J8: 260 | K8: 250 | L8: 90 | M8: 80 | N8: =SUM(H8:M8) -> 800 | O8: N/A | P8: 2239 | Q8: — | R8: =IFERROR(N8+IF(ISNUMBER(O8),O8,0)+IF(ISNUMBER(P8),P8,0),"") -> 3039 | S8: Kaifu
A9: Nhava-Manzanillo | B9: Creative Components | C9: Saltillo | D9: Nhava Sheva | E9: MANZANILLO | F9: CIF | G9: 2 | H9: 70 | I9: 80 | J9: 160 | K9: 1000 | L9: 50 | M9: 75 | N9: =SUM(H9:M9) -> 1435 | O9: N/A | P9: 2790 | Q9: 50-55 days | R9: =IFERROR(N9+IF(ISNUMBER(O9),O9,0)+IF(ISNUMBER(P9),P9,0),"") -> 4225 | S9: Kaifu
A10: Incheon-Manzanillo | B10: WOORY | C10: Saltillo | D10: INCHEON | E10: MANZANILLO | F10: CIF | G10: 1 | H10: 70 | I10: 35 | J10: 145 | K10: 350 | L10: 150 | M10: 50 | N10: =SUM(H10:M10) -> 800 | O10: N/A | P10: 3400 | Q10: 25-30 days | R10: =IFERROR(N10+IF(ISNUMBER(O10),O10,0)+IF(ISNUMBER(P10),P10,0),"") -> 4200 | S10: Kaifu
A11: SHA-Manzanillo (Chao Li) | B11: Jiangsu Chao Li | C11: Puebla | D11: SHA | E11: MANZANILLO | F11: FOB | G11: 2 | H11: 70 | I11: 70 | J11: 145 | K11: 550 | L11: 15 | M11: 60 | N11: =SUM(H11:M11) -> 910 | O11: N/A | P11: 1748 | Q11: 18-23 days | R11: =IFERROR(N11+IF(ISNUMBER(O11),O11,0)+IF(ISNUMBER(P11),P11,0),"") -> 2658 | S11: Freetrans
A12: SHA-Manzanillo (Yangzhou) | B12: Yangzhou RSL | C12: Puebla | D12: SHA | E12: MANZANILLO | F12: CIF | G12: 1 | H12: 70 | I12: 70 | J12: 145 | K12: 550 | L12: 15 | M12: 60 | N12: =SUM(H12:M12) -> 910 | O12: N/A | P12: 1749 | Q12: — | R12: =IFERROR(N12+IF(ISNUMBER(O12),O12,0)+IF(ISNUMBER(P12),P12,0),"") -> 2659 | S12: Freetrans
A13: SHA-Manzanillo (Yuansheng) | B13: Zhejiang Yuansheng | C13: Puebla | D13: SHA | E13: MANZANILLO | F13: CIF | G13: 0.5 | H13: 70 | I13: 70 | J13: 145 | K13: 550 | L13: 15 | M13: 60 | N13: =SUM(H13:M13) -> 910 | O13: N/A | P13: 1748 | Q13: — | R13: =IFERROR(N13+IF(ISNUMBER(O13),O13,0)+IF(ISNUMBER(P13),P13,0),"") -> 2658 | S13: Freetrans
A14: SHA-Manzanillo (Huafon Coil) | B14: Shanghai Huafon Coil | C14: Puebla | D14: SHA | E14: MANZANILLO | F14: CIF | G14: 2 | H14: 70 | I14: 70 | J14: 145 | K14: 250 | L14: 15 | M14: 60 | N14: =SUM(H14:M14) -> 610 | O14: N/A | P14: 1750 | Q14: — | R14: =IFERROR(N14+IF(ISNUMBER(O14),O14,0)+IF(ISNUMBER(P14),P14,0),"") -> 2360 | S14: Freetrans
A15: SHA-Manzanillo (ABIC) | B15: Dalian ABIC | C15: Puebla | D15: SHA | E15: MANZANILLO | F15: CIF | G15: 2 | H15: 70 | I15: 70 | J15: 145 | K15: 200 | L15: 15 | M15: 50 | N15: =SUM(H15:M15) -> 550 | O15: N/A | P15: 1750 | Q15: — | R15: =IFERROR(N15+IF(ISNUMBER(O15),O15,0)+IF(ISNUMBER(P15),P15,0),"") -> 2300 | S15: Freetrans
A16: SHA-Manzanillo (Boling) | B16: Chongqing Boling | C16: Puebla | D16: SHA | E16: MANZANILLO | F16: CIF | G16: 0.5 | H16: 70 | I16: 70 | J16: 145 | K16: 1550 | L16: 15 | M16: 60 | N16: =SUM(H16:M16) -> 1910 | O16: N/A | P16: 1750 | Q16: — | R16: =IFERROR(N16+IF(ISNUMBER(O16),O16,0)+IF(ISNUMBER(P16),P16,0),"") -> 3660 | S16: Freetrans
A17: SHA-Manzanillo (AITD) | B17: AITD | C17: Saltillo | D17: SHA | E17: MANZANILLO | F17: CIF | G17: 1 | H17: 70 | I17: 70 | J17: 145 | K17: 350 | L17: 15 | M17: 60 | N17: =SUM(H17:M17) -> 710 | O17: N/A | P17: 1750 | Q17: — | R17: =IFERROR(N17+IF(ISNUMBER(O17),O17,0)+IF(ISNUMBER(P17),P17,0),"") -> 2460 | S17: Freetrans
... A22: SHA-Manzanillo (Shenda) | B22: Changsha Shenda | C22: Saltillo | D22: SHA | E22: MANZANILLO | F22: CIF | G22: 2 | H22: 70 | I22: 70 | J22: 145 | K22: 1500 | L22: 15 | M22: 60 | N22: =SUM(H22:M22) -> 1860 | O22: N/A | P22: 1750 | Q22: — | R22: =IFERROR(N22+IF(ISNUMBER(O22),O22,0)+IF(ISNUMBER(P22),P22,0),"") -> 3610 | S22: Freetrans
A23: AIUS | USA (HOU / Detroit / Savanna) | 5 条航线 | 月需求 11 HQ40
A24: SHA-HOU | B24: AINT - 666 Wenchang Rd, Tongzhou, Nantong | C24: GTZ WAREHOUSE LLC, McALLEN, TX | D24: SHA | E24: HOU | F24: EXW | G24: 1 | H24: 70 | I24: 70 | J24: 140 | K24: 400 | L24: 10 | M24: 70 | N24: =SUM(H24:M24) -> 760 | O24: 2685 | P24: 2350 | Q24: 8-10 wks | R24: =IFERROR(N24+IF(ISNUMBER(O24),O24,0)+IF(ISNUMBER(P24),P24,0),"") -> 5795 | S24: Bondex
A25: SHA-Detroit | B25: AISH - 108 Chunguang Rd, Minhang, Shanghai | C25: FTZ METRO WAREHOUSE, HIGHLAND PARK, MI | D25: SHA | E25: Detroit | F25: EXW | G25: 1 | H25: 70 | I25: 70 | J25: 140 | K25: 250 | L25: 10 | M25: 70 | N25: =SUM(H25:M25) -> 610 | O25: 885 | P25: 3750 | Q25: — | R25: =IFERROR(N25+IF(ISNUMBER(O25),O25,0)+IF(ISNUMBER(P25),P25,0),"") -> 5245 | S25: Bondex
A26: Laem-Savanna | B26: AITH (Thailand) | C26: AIUS Baxter, Winchester, TN | D26: Laem Chabang | E26: Savanna | F26: DAP | G26: 3 | H26: 70 | I26: 70 | J26: 140 | K26: 300 | L26: 30 | M26: 70 | N26: =SUM(H26:M26) -> 680 | O26: 2785 | P26: 2200 | Q26: 8-10 wks | R26: =IFERROR(N26+IF(ISNUMBER(O26),O26,0)+IF(ISNUMBER(P26),P26,0),"") -> 5665 | S26: Freetrans
A27: Nhava-Savanna | B27: Divine & Creative (India) | C27: AIUS Baxter, Winchester, TN | D27: Nhava Sheva | E27: Savanna | F27: DAP | G27: 3 | H27: 70 | I27: 80 | J27: 160 | K27: 1000 | L27: 50 | M27: 75 | N27: =SUM(H27:M27) -> 1435 | O27: 2785 | P27: 2193 | Q27: 7-9 wks | R27: =IFERROR(N27+IF(ISNUMBER(O27),O27,0)+IF(ISNUMBER(P27),P27,0),"") -> 6413 | S27: Freetrans
A28: SHA-Savanna | B28: AINT - 666 Wenchang Rd, Tongzhou, Nantong | C28: AIUS Baxter, Winchester, TN | D28: SHA | E28: Savanna | F28: DAP | G28: 3 | H28: 70 | I28: 70 | J28: 140 | K28: 400 | L28: 10 | M28: 70 | N28: =SUM(H28:M28) -> 760 | O28: 2785 | P28: 2193 | Q28: 6-8 wks | R28: =IFERROR(N28+IF(ISNUMBER(O28),O28,0)+IF(ISNUMBER(P28),P28,0),"") -> 5738 | S28: Freetrans
A29: AISH | Asia → SHA (inbound) | 2 条航线 | 月需求 3 HQ40
A30: Bangkok-SHA | B30: DELTA ELECTRONICS (Thailand) | C30: AINT - 666 Wenchang Rd, Tongzhou, Nantong | D30: Bangkok | E30: SHA | F30: EXW | G30: 1 | H30: 70 | I30: 50 | J30: 260 | K30: 325 | L30: 90 | M30: 80 | N30: =SUM(H30:M30) -> 875 | O30: 600 | P30: 1 | Q30: 15-20 days | R30: =IFERROR(N30+IF(ISNUMBER(O30),O30,0)+IF(ISNUMBER(P30),P30,0),"") -> 1476 | S30: Superchain
A31: Incheon-SHA | B31: Woory Industrial, Korea | C31: AINT - 666 Wenchang Rd, Tongzhou, Nantong | D31: INCHEON | E31: SHA | F31: EXW | G31: 2 | H31: 50 | I31: 35 | J31: 125 | K31: 280 | L31: 150 | M31: 50 | N31: =SUM(H31:M31) -> 690 | O31: 600 | P31: 1 | Q31: 5-10 days | R31: =IFERROR(N31+IF(ISNUMBER(O31),O31,0)+IF(ISNUMBER(P31),P31,0),"") -> 1291 | S31: Superchain
A32: AITH | Thailand (Laemchabang) | 5 条航线 | 月需求 11 HQ40
A33: SHA-Laem | B33: AISH - 108 Chunguang Rd, Minhang, Shanghai | C33: AITH, Chonburi 20230 Thailand | D33: SHA | E33: Laemchabang | F33: EXW | G33: 1 | H33: 70 | I33: 70 | J33: 140 | K33: 250 | L33: 10 | M33: 70 | N33: =SUM(H33:M33) -> 610 | O33: 800 | P33: 650 | Q33: 15-20 days | R33: =IFERROR(N33+IF(ISNUMBER(O33),O33,0)+IF(ISNUMBER(P33),P33,0),"") -> 2060 | S33: Bondex/Bestunit
A34: SHA-Laem (Huafon) | B34: Shanghai Huafon Aluminium Corp. | C34: AITH, Rayong 21140 Thailand | D34: SHA | E34: Laemchabang | F34: EXW | G34: 3 | H34: 70 | I34: 70 | J34: 140 | K34: 250 | L34: 10 | M34: 70 | N34: =SUM(H34:M34) -> 610 | O34: 800 | P34: 650 | Q34: 15-20 days | R34: =IFERROR(N34+IF(ISNUMBER(O34),O34,0)+IF(ISNUMBER(P34),P34,0),"") -> 2060 | S34: Bondex/Bestunit
A35: Tianjin-Laem | B35: Hyo Seong Electric (Tianjin) | C35: AITH, Chonburi 20230 Thailand | D35: Tianjin | E35: Laemchabang | F35: EXW | G35: 0.5 | H35: 70 | I35: 70 | J35: 140 | K35: 420 | L35: 30 | M35: 70 | N35: =SUM(H35:M35) -> 800 | O35: 800 | P35: 600 | Q35: 18-23 days | R35: =IFERROR(N35+IF(ISNUMBER(O35),O35,0)+IF(ISNUMBER(P35),P35,0),"") -> 2200 | S35: Bondex
A36: Dubai-Laem | B36: OSE Industries LLC, Dubai | C36: AITH, Rayong 21140 Thailand | D36: Dubai | E36: Laemchabang | F36: EXW | G36: 0.5 | H36: 70 | I36: 70 | J36: 140 | K36: 420 | L36: 30 | M36: 70 | N36: =SUM(H36:M36) -> 800 | O36: 800 | P36: 600 | Q36: 20-25 days | R36: =IFERROR(N36+IF(ISNUMBER(O36),O36,0)+IF(ISNUMBER(P36),P36,0),"") -> 2200 | S36: Kaifu
A37: Laem-Hamburg | B37: AITH, Rayong 21140 Thailand | C37: AISK, Nitra, Slovakia | D37: Laemchabang | E37: Hamburg | F37: DDP | G37: 6 | H37: 70 | I37: 70 | J37: 140 | K37: 300 | L37: 30 | M37: 70 | N37: =SUM(H37:M37) -> 680 | O37: 2200 | P37: 3300 | Q37: 9-10 wks | R37: =IFERROR(N37+IF(ISNUMBER(O37),O37,0)+IF(ISNUMBER(P37),P37,0),"") -> 6180 | S37: Bondex
A38: AISK | Slovakia (Hamburg) | 3 条航线 | 月需求 3.5 HQ40
A39: SHA-Hamburg | B39: AINT - 666 Wenchang Rd, Tongzhou, Nantong | C39: AISK, Nitra, Slovakia | D39: SHA | E39: Hamburg | F39: EXW | G39: 1 | H39: 70 | I39: 70 | J39: 140 | K39: 400 | L39: 10 | M39: 70 | N39: =SUM(H39:M39) -> 760 | O39: 2200 | P39: 1800 | Q39: 8-9 wks | R39: =IFERROR(N39+IF(ISNUMBER(O39),O39,0)+IF(ISNUMBER(P39),P39,0),"") -> 4760 | S39: Bestunit
A40: Nhava-Hamburg | B40: Divine Tooling | C40: AISK, Nitra, Slovakia | D40: Nhava Sheva | E40: Hamburg | F40: EXW | G40: 2 | H40: 70 | I40: 70 | J40: 140 | K40: 300 | L40: 250 | M40: 70 | N40: =SUM(H40:M40) -> 900 | O40: 2200 | P40: 2100 | Q40: 8-10 wks | R40: =IFERROR(N40+IF(ISNUMBER(O40),O40,0)+IF(ISNUMBER(P40),P40,0),"") -> 5200 | S40: Kaifu
A41: Bangkok-Hamburg | B41: Delta Electronics | C41: AISK, Nitra, Slovakia | D41: Bangkok | E41: Hamburg | F41: EXW | G41: 0.5 | H41: 70 | I41: 70 | J41: 140 | K41: 300 | L41: 250 | M41: 70 | N41: =SUM(H41:M41) -> 900 | O41: 2200 | P41: 2400 | Q41: 9-10 wks | R41: =IFERROR(N41+IF(ISNUMBER(O41),O41,0)+IF(ISNUMBER(P41),P41,0),"") -> 5500 | S41: Kaifu

Sheet 26.3.30-4.12
A1: Lane | B1: Consignor | C1: Consignee | D1: POL | E1: POD | F1: Incoterm | G1: HQ40 Demand | H1: Booking | I1: Doc | J1: THC | K1: Loading | L1: Customs | M1: B/L | N1: Local Subtotal | O1: Dest Subtotal | P1: Sea Freight | Q1: Transit Time | R1: Total (USD) | S1: Winning Forwarder
A2: AI-Turkey | Turkey (Izmit) | 2 条航线 | 两周需求 13 HQ40 (5+5 / 2+1)
A3: SHA-Izmit | B3: AINT - 666 Wenchang Rd, Tongzhou, Nantong | C3: AI Termal Sistemleri A.Ş., İstanbul | D3: SHA | E3: Izmit | F3: DAP | G3: 5+5 | H3: 70 | I3: 70 | J3: 140 | K3: 400 | L3: 10 | M3: 70 | N3: =SUM(H3:M3) -> 760 | O3: 950 | P3: 3350 | Q3: 10-12 wks | R3: =IFERROR(N3+IF(ISNUMBER(O3),O3,0)+IF(ISNUMBER(P3),P3,0),"") -> 5060 | S3: BU + Holiton
A4: SAI-Izmit | B4: SAI - 3 Gaobao Lake East Rd, Yubei, Chongqing | C4: AI Termal Sistemleri A.Ş., İstanbul | D4: SHA | E4: Izmit | F4: EXW | G4: 2+1 | H4: 70 | I4: 70 | J4: 170 | K4: 250 | L4: 50 | M4: 50 | N4: =SUM(H4:M4) -> 660 | O4: 950 | P4: 4925 | Q4: 11-13 wks | R4: =IFERROR(N4+IF(ISNUMBER(O4),O4,0)+IF(ISNUMBER(P4),P4,0),"") -> 6535 | S4: Freetrans
A5: =_xlfn.CONCAT("AIMX | Mexico (Manzanillo) | 17 条航线 | 两周需求 ", TEXT(SUM(G6:G22),"0.0")," HQ40") -> AIMX | Mexico (Manzanillo) | 17 条航线 | 两周需求 18.0 HQ40
A6: Laem-Manzanillo | B6: AITH | C6: Puebla + Saltillo | D6: Laemchabang | E6: MANZANILLO | F6: CIF | G6: 4 | H6: 70 | I6: 50 | J6: 260 | K6: 250 | L6: 90 | M6: 80 | N6: =SUM(H6:M6) -> 800 | O6: N/A | P6: 2590 | Q6: 35-45 days | R6: =IFERROR(N6+IF(ISNUMBER(O6),O6,0)+IF(ISNUMBER(P6),P6,0),"") -> 3390 | S6: Bondex
A7: Bangkok-Manzanillo | B7: DELTA | C7: Saltillo | D7: Bangkok | E7: MANZANILLO | F7: CIF | G7: 2 | H7: 70 | I7: 50 | J7: 260 | K7: 325 | L7: 90 | M7: 80 | N7: =SUM(H7:M7) -> 875 | O7: N/A | P7: 2590 | Q7: 35-45 days | R7: =IFERROR(N7+IF(ISNUMBER(O7),O7,0)+IF(ISNUMBER(P7),P7,0),"") -> 3465 | S7: Bondex
A8: Laem-Manzanillo (TNC) | B8: TNC | C8: Puebla | D8: Laemchabang | E8: MANZANILLO | F8: CIF | G8: 1 | H8: 70 | I8: 50 | J8: 260 | K8: 250 | L8: 90 | M8: 80 | N8: =SUM(H8:M8) -> 800 | O8: N/A | P8: 2590 | Q8: 35-45 days | R8: =IFERROR(N8+IF(ISNUMBER(O8),O8,0)+IF(ISNUMBER(P8),P8,0),"") -> 3390 | S8: Bondex
A9: Nhava-Manzanillo | B9: Creative Components | C9: Saltillo | D9: Nhava Sheva | E9: MANZANILLO | F9: CIF | G9: 1 | H9: 70 | I9: 80 | J9: 160 | K9: 1000 | L9: 50 | M9: 75 | N9: =SUM(H9:M9) -> 1435 | O9: N/A | P9: 3200 | Q9: 50-55 days | R9: =IFERROR(N9+IF(ISNUMBER(O9),O9,0)+IF(ISNUMBER(P9),P9,0),"") -> 4635 | S9: KF
A10: Incheon-Manzanillo | B10: WOORY | C10: Saltillo | D10: INCHEON | E10: MANZANILLO | F10: CIF | G10: 1 | H10: 70 | I10: 35 | J10: 145 | K10: 350 | L10: 150 | M10: 50 | N10: =SUM(H10:M10) -> 800 | O10: N/A | P10: 2990 | Q10: 25-30 days | R10: =IFERROR(N10+IF(ISNUMBER(O10),O10,0)+IF(ISNUMBER(P10),P10,0),"") -> 3790 | S10: Bondex
A11: SHA-Manzanillo (Chao Li) | B11: Jiangsu Chao Li | C11: Puebla | D11: SHA | E11: MANZANILLO | F11: FOB | G11: 1 | H11: 70 | I11: 70 | J11: 145 | K11: 550 | L11: 15 | M11: 60 | N11: =SUM(H11:M11) -> 910 | O11: N/A | P11: 2800 | Q11: 18-23 days | R11: =IFERROR(N11+IF(ISNUMBER(O11),O11,0)+IF(ISNUMBER(P11),P11,0),"") -> 3710 | S11: Freetrans
A12: SHA-Manzanillo (Yangzhou) | B12: Yangzhou RSL | C12: Puebla | D12: SHA | E12: MANZANILLO | F12: CIF | G12: 1 | H12: 70 | I12: 70 | J12: 145 | K12: 550 | L12: 15 | M12: 60 | N12: =SUM(H12:M12) -> 910 | O12: N/A | P12: 2800 | Q12: 18-23 days | R12: =IFERROR(N12+IF(ISNUMBER(O12),O12,0)+IF(ISNUMBER(P12),P12,0),"") -> 3710 | S12: Freetrans
A13: SHA-Manzanillo (Yuansheng) | B13: Zhejiang Yuansheng | C13: Puebla | D13: SHA | E13: MANZANILLO | F13: CIF | G13: 0.5 | H13: 70 | I13: 70 | J13: 145 | K13: 550 | L13: 15 | M13: 60 | N13: =SUM(H13:M13) -> 910 | O13: N/A | P13: 2800 | Q13: 18-23 days | R13: =IFERROR(N13+IF(ISNUMBER(O13),O13,0)+IF(ISNUMBER(P13),P13,0),"") -> 3710 | S13: Freetrans
A14: SHA-Manzanillo (Huafon Coil) | B14: Shanghai Huafon Coil | C14: Puebla | D14: SHA | E14: MANZANILLO | F14: CIF | G14: 1 | H14: 70 | I14: 70 | J14: 145 | K14: 250 | L14: 15 | M14: 60 | N14: =SUM(H14:M14) -> 610 | O14: N/A | P14: 2800 | Q14: 18-23 days | R14: =IFERROR(N14+IF(ISNUMBER(O14),O14,0)+IF(ISNUMBER(P14),P14,0),"") -> 3410 | S14: Freetrans
A15: SHA-Manzanillo (ABIC) | B15: Dalian ABIC | C15: Puebla | D15: SHA | E15: MANZANILLO | F15: CIF | G15: 1 | H15: 70 | I15: 70 | J15: 145 | K15: 200 | L15: 15 | M15: 50 | N15: =SUM(H15:M15) -> 550 | O15: N/A | P15: 2800 | Q15: 18-23 days | R15: =IFERROR(N15+IF(ISNUMBER(O15),O15,0)+IF(ISNUMBER(P15),P15,0),"") -> 3350 | S15: Freetrans
A16: SHA-Manzanillo (Boling) | B16: Chongqing Boling | C16: Puebla | D16: SHA | E16: MANZANILLO | F16: CIF | G16: 0.5 | H16: 70 | I16: 70 | J16: 145 | K16: 1550 | L16: 15 | M16: 60 | N16: =SUM(H16:M16) -> 1910 | O16: N/A | P16: 2800 | Q16: 18-23 days | R16: =IFERROR(N16+IF(ISNUMBER(O16),O16,0)+IF(ISNUMBER(P16),P16,0),"") -> 4710 | S16: Freetrans
A17: SHA-Manzanillo (AITD) | B17: AITD | C17: Saltillo | D17: SHA | E17: MANZANILLO | F17: CIF | G17: 0 | H17: 70 | I17: 70 | J17: 145 | K17: 350 | L17: 15 | M17: 60 | N17: =SUM(H17:M17) -> 710 | O17: N/A | P17: 2800 | Q17: 18-23 days | R17: =IFERROR(N17+IF(ISNUMBER(O17),O17,0)+IF(ISNUMBER(P17),P17,0),"") -> 3510 | S17: Freetrans
... A22: SHA-Manzanillo (Shenda) | B22: Changsha Shenda | C22: Saltillo | D22: SHA | E22: MANZANILLO | F22: CIF | G22: 1 | H22: 70 | I22: 70 | J22: 145 | K22: 1500 | L22: 15 | M22: 60 | N22: =SUM(H22:M22) -> 1860 | O22: N/A | P22: 2800 | Q22: 18-23 days | R22: =IFERROR(N22+IF(ISNUMBER(O22),O22,0)+IF(ISNUMBER(P22),P22,0),"") -> 4660 | S22: Freetrans
A23: =_xlfn.CONCAT("AIUS | USA (HOU / Detroit / Savanna) | 5 条航线 | 两周需求 ", TEXT(SUM(G24:G28),"0.0")," HQ40") -> AIUS | USA (HOU / Detroit / Savanna) | 5 条航线 | 两周需求 5.0 HQ40
A24: SHA-HOU | B24: AINT - 666 Wenchang Rd, Tongzhou, Nantong | C24: AIUS TOC c/o GTZ, McAllen TX 78503 | D24: SHA | E24: HOU | F24: EXW | G24: 1 | H24: 70 | I24: 70 | J24: 140 | K24: 400 | L24: 10 | M24: 70 | N24: =SUM(H24:M24) -> 760 | O24: 2685 | P24: 3590 | Q24: 8-10 wks | R24: =IFERROR(N24+IF(ISNUMBER(O24),O24,0)+IF(ISNUMBER(P24),P24,0),"") -> 7035 | S24: KF
A25: SHA-Detroit | B25: AISH - 108 Chunguang Rd, Minhang, Shanghai | C25: AIUS c/o FTZ Metro, Highland Park MI | D25: SHA | E25: Detroit | F25: EXW | G25: 1 | H25: 70 | I25: 70 | J25: 140 | K25: 250 | L25: 10 | M25: 70 | N25: =SUM(H25:M25) -> 610 | O25: 885 | P25: 3969 | R25: =IFERROR(N25+IF(ISNUMBER(O25),O25,0)+IF(ISNUMBER(P25),P25,0),"") -> 5464 | S25: KF
A26: Laem-Savanna | B26: AITH, Rayong (WHA ESIE 1) | C26: AIUS Baxter, Winchester TN 37398 | D26: Laemchabang | E26: Savanna | F26: DAP | G26: 1 | H26: 70 | I26: 70 | J26: 140 | K26: 300 | L26: 30 | M26: 70 | N26: =SUM(H26:M26) -> 680 | O26: 2785 | P26: 3570 | Q26: 8-10 wks | R26: =IFERROR(N26+IF(ISNUMBER(O26),O26,0)+IF(ISNUMBER(P26),P26,0),"") -> 7035 | S26: KF
A27: Nhava-Savanna | B27: Divine & Creative (India) | C27: AIUS Baxter, Winchester TN | D27: Nhava Sheva | E27: Savanna | F27: DAP | G27: 1 | H27: 70 | I27: 80 | J27: 160 | K27: 1000 | L27: 50 | M27: 75 | N27: =SUM(H27:M27) -> 1435 | O27: 2785 | P27: 3088 | Q27: 7-9 wks | R27: =IFERROR(N27+IF(ISNUMBER(O27),O27,0)+IF(ISNUMBER(P27),P27,0),"") -> 7308 | S27: KF
A28: SHA-Savanna | B28: AINT - 666 Wenchang Rd, Tongzhou, Nantong | C28: AIUS Baxter, Winchester TN | D28: SHA | E28: Savanna | F28: DAP | G28: 1 | H28: 70 | I28: 70 | J28: 140 | K28: 400 | L28: 10 | M28: 70 | N28: =SUM(H28:M28) -> 760 | O28: 2785 | P28: 3390 | Q28: 6-8 wks | R28: =IFERROR(N28+IF(ISNUMBER(O28),O28,0)+IF(ISNUMBER(P28),P28,0),"") -> 6935 | S28: KF
A29: =_xlfn.CONCAT("AISH | Asia → SHA (inbound) | 2 条航线 | 两周需求 ", TEXT(SUM(G30:G31),"0.0")," HQ40") -> AISH | Asia → SHA (inbound) | 2 条航线 | 两周需求 5.0 HQ40
A30: Bangkok-SHA | B30: Delta Electronics (Thailand), Chachoengsao | C30: AINT - 666 Wenchang Rd, Nantong | D30: Bangkok | E30: SHA | F30: EXW | G30: 2 | H30: 70 | I30: 50 | J30: 260 | K30: 325 | L30: 90 | M30: 80 | N30: =SUM(H30:M30) -> 875 | O30: 600 | P30: 1 | Q30: 15-20 days | R30: =IFERROR(N30+IF(ISNUMBER(O30),O30,0)+IF(ISNUMBER(P30),P30,0),"") -> 1476 | S30: Superchain
A31: Incheon-SHA | B31: Woory Industrial, Yongin Korea | C31: AINT - 666 Wenchang Rd, Nantong | D31: INCHEON | E31: SHA | F31: EXW | G31: 3 | H31: 50 | I31: 35 | J31: 125 | K31: 280 | L31: 150 | M31: 50 | N31: =SUM(H31:M31) -> 690 | O31: 600 | P31: 1 | Q31: 5-10 days | R31: =IFERROR(N31+IF(ISNUMBER(O31),O31,0)+IF(ISNUMBER(P31),P31,0),"") -> 1291 | S31: Superchain
A32: =_xlfn.CONCAT("AITH | Thailand (Laemchabang) | 5 条航线 | 两周需求 ", TEXT(SUM(G33:G37),"0.0")," HQ40") -> AITH | Thailand (Laemchabang) | 5 条航线 | 两周需求 5.0 HQ40
A33: SHA-Laem | B33: AISH - 108 Chunguang Rd, Minhang, Shanghai | C33: AI Thermal Systems (Thailand), Chonburi | D33: SHA | E33: Laemchabang | F33: EXW | G33: 1 | H33: 70 | I33: 70 | J33: 140 | K33: 250 | L33: 10 | M33: 70 | N33: =SUM(H33:M33) -> 610 | O33: 800 | P33: 890 | Q33: 15-20 days | R33: =IFERROR(N33+IF(ISNUMBER(O33),O33,0)+IF(ISNUMBER(P33),P33,0),"") -> 2300 | S33: Bondex
A34: SHA-Laem (Huafon) | B34: Shanghai Huafon Aluminium, Jinshan | C34: AITH, Rayong (WHA ESIE 1) | D34: SHA | E34: Laemchabang | F34: EXW | G34: 1 | H34: 70 | I34: 70 | J34: 140 | K34: 250 | L34: 10 | M34: 70 | N34: =SUM(H34:M34) -> 610 | O34: 800 | P34: 890 | Q34: 15-20 days | R34: =IFERROR(N34+IF(ISNUMBER(O34),O34,0)+IF(ISNUMBER(P34),P34,0),"") -> 2300 | S34: Bondex
A35: Tianjin-Laem | B35: Hyo Seong Electric (Tianjin) | C35: AITH, Chonburi | D35: Tianjin | E35: Laemchabang | F35: EXW | G35: 0 | H35: 70 | I35: 70 | J35: 140 | K35: 420 | L35: 30 | M35: 70 | N35: =SUM(H35:M35) -> 800 | O35: 800 | P35: 940 | Q35: 18-23 days | R35: =IFERROR(N35+IF(ISNUMBER(O35),O35,0)+IF(ISNUMBER(P35),P35,0),"") -> 2540 | S35: Bondex
A36: Dubai-Laem | B36: OSE Industries LLC, Dubai | C36: AITH, Rayong (WHA ESIE 1) | D36: Dubai | E36: Laemchabang | F36: EXW | G36: 0 | H36: 70 | I36: 70 | J36: 140 | K36: 420 | L36: 30 | M36: 70 | N36: =SUM(H36:M36) -> 800 | O36: 800 | P36: - | Q36: 20-25 days | R36: =IFERROR(N36+IF(ISNUMBER(O36),O36,0)+IF(ISNUMBER(P36),P36,0),"") -> 1600 | S36: -
A37: Laem-Hamburg | B37: AITH, Rayong (WHA ESIE 1) | C37: AI Thermal (Slovakia) s.r.o., Nitra | D37: Laemchabang | E37: Hamburg | F37: DDP | G37: 3 | H37: 70 | I37: 70 | J37: 140 | K37: 300 | L37: 30 | M37: 70 | N37: =SUM(H37:M37) -> 680 | O37: 2200 | P37: 3870 | Q37: 9-10 wks | R37: =IFERROR(N37+IF(ISNUMBER(O37),O37,0)+IF(ISNUMBER(P37),P37,0),"") -> 6750 | S37: Bondex
A38: =_xlfn.CONCAT("AISK | Slovakia (Hamburg) | 3 条航线 | 两周需求 ", TEXT(SUM(G39:G41),"0.0")," HQ40") -> AISK | Slovakia (Hamburg) | 3 条航线 | 两周需求 2.0 HQ40
A39: SHA-Hamburg | B39: AINT - 666 Wenchang Rd, Nantong | C39: AI Thermal (Slovakia) s.r.o., Nitra | D39: SHA | E39: Hamburg | F39: EXW | G39: 1 | H39: 70 | I39: 70 | J39: 140 | K39: 400 | L39: 10 | M39: 70 | N39: =SUM(H39:M39) -> 760 | O39: 2200 | P39: 3090 | Q39: 8-9 wks | R39: =IFERROR(N39+IF(ISNUMBER(O39),O39,0)+IF(ISNUMBER(P39),P39,0),"") -> 6050 | S39: Bondex
A40: Nhava-Hamburg | B40: Divine Tooling (India) | C40: AI Thermal (Slovakia), Nitra | D40: Nhava Sheva | E40: Hamburg | F40: EXW | G40: 1 | H40: 70 | I40: 70 | J40: 140 | K40: 300 | L40: 250 | M40: 70 | N40: =SUM(H40:M40) -> 900 | O40: 2200 | P40: - | Q40: 8-10 wks | R40: =IFERROR(N40+IF(ISNUMBER(O40),O40,0)+IF(ISNUMBER(P40),P40,0),"") -> 3100 | S40: -
A41: Bangkok-Hamburg | B41: Delta Electronics (Thailand) | C41: AI Thermal (Slovakia), Nitra | D41: Bangkok | E41: Hamburg | F41: EXW | G41: 0 | H41: 70 | I41: 70 | J41: 140 | K41: 300 | L41: 250 | M41: 70 | N41: =SUM(H41:M41) -> 900 | O41: 2200 | P41: 3870 | Q41: 9-10 wks | R41: =IFERROR(N41+IF(ISNUMBER(O41),O41,0)+IF(ISNUMBER(P41),P41,0),"") -> 6970 | S41: Bondex

Sheet 26.4.13-4.26
A1: Lane | B1: Consignor | C1: Consignee | D1: POL | E1: POD | F1: Incoterm | G1: HQ40 Demand | H1: Booking | I1: Doc | J1: THC | K1: Loading | L1: Customs | M1: B/L | N1: Local Subtotal | O1: Dest Subtotal | P1: Sea Freight | Q1: Transit Time | R1: Total (USD) | S1: Winning Forwarder
A2: AI-Turkey | Turkey (Izmit) | 2 条航线 | 两周需求 12 HQ40 (5+5 / 1+1)
A3: SHA-Izmit | B3: AINT - 666 Wenchang Rd, Tongzhou, Nantong | C3: AI Termal Sistemleri A.Ş., İstanbul | D3: SHA | E3: Izmit | F3: DAP | G3: 5+5 | H3: 70 | I3: 70 | J3: 140 | K3: 400 | L3: 10 | M3: 70 | N3: =SUM(H3:M3) -> 760 | O3: 950 | P3: 2745 | Q3: 10-12 wks | R3: =IFERROR(N3+IF(ISNUMBER(O3),O3,0)+IF(ISNUMBER(P3),P3,0),"") -> 4455 | S3: BU / CW17
A4: SAI-Izmit | B4: SAI - 3 Gaobao Lake East Rd, Yubei, Chongqing | C4: AI Termal Sistemleri A.Ş., İstanbul | D4: SHA | E4: Izmit | F4: EXW | G4: 1+1 | H4: 70 | I4: 70 | J4: 170 | K4: 250 | L4: 50 | M4: 50 | N4: =SUM(H4:M4) -> 660 | O4: 950 | P4: 4400 | Q4: 11-13 wks | R4: =IFERROR(N4+IF(ISNUMBER(O4),O4,0)+IF(ISNUMBER(P4),P4,0),"") -> 6010 | S4: Bondex / CW17
A5: =_xlfn.CONCAT("AIMX | Mexico (Manzanillo) | 17 条航线 | 两周需求 ", TEXT(SUM(G6:G22),"0.0")," HQ40") -> AIMX | Mexico (Manzanillo) | 17 条航线 | 两周需求 17.0 HQ40
A6: Laem-Manzanillo | B6: AITH | C6: Puebla + Saltillo | D6: Laemchabang | E6: MANZANILLO | F6: CIF | G6: 4 | H6: 70 | I6: 50 | J6: 260 | K6: 250 | L6: 90 | M6: 80 | N6: =SUM(H6:M6) -> 800 | O6: N/A | P6: 2500 | Q6: 35-45 days | R6: =IFERROR(N6+IF(ISNUMBER(O6),O6,0)+IF(ISNUMBER(P6),P6,0),"") -> 3300 | S6: Bondex
A7: Bangkok-Manzanillo | B7: DELTA | C7: Saltillo | D7: Bangkok | E7: MANZANILLO | F7: CIF | G7: 2 | H7: 70 | I7: 50 | J7: 260 | K7: 325 | L7: 90 | M7: 80 | N7: =SUM(H7:M7) -> 875 | O7: N/A | P7: 2600 | Q7: 35-45 days | R7: =IFERROR(N7+IF(ISNUMBER(O7),O7,0)+IF(ISNUMBER(P7),P7,0),"") -> 3475 | S7: Bondex
A8: Laem-Manzanillo (TNC) | B8: TNC | C8: Puebla | D8: Laemchabang | E8: MANZANILLO | F8: CIF | G8: 1 | H8: 70 | I8: 50 | J8: 260 | K8: 250 | L8: 90 | M8: 80 | N8: =SUM(H8:M8) -> 800 | O8: N/A | P8: 2500 | Q8: 35-45 days | R8: =IFERROR(N8+IF(ISNUMBER(O8),O8,0)+IF(ISNUMBER(P8),P8,0),"") -> 3300 | S8: Bondex
A9: Nhava-Manzanillo | B9: Creative Components | C9: Saltillo | D9: Nhava Sheva | E9: MANZANILLO | F9: CIF | G9: 1 | H9: 70 | I9: 80 | J9: 160 | K9: 1000 | L9: 50 | M9: 75 | N9: =SUM(H9:M9) -> 1435 | O9: N/A | P9: 3200 | Q9: 50-55 days | R9: =IFERROR(N9+IF(ISNUMBER(O9),O9,0)+IF(ISNUMBER(P9),P9,0),"") -> 4635 | S9: Kaifu
A10: Incheon-Manzanillo | B10: WOORY | C10: Saltillo | D10: INCHEON | E10: MANZANILLO | F10: CIF | G10: 0 | H10: 70 | I10: 35 | J10: 145 | K10: 350 | L10: 150 | M10: 50 | N10: =SUM(H10:M10) -> 800 | O10: N/A | P10: 2800 | Q10: 25-30 days | R10: =IFERROR(N10+IF(ISNUMBER(O10),O10,0)+IF(ISNUMBER(P10),P10,0),"") -> 3600 | S10: Bondex
A11: SHA-Manzanillo (Chao Li) | B11: Jiangsu Chao Li | C11: Puebla | D11: SHA | E11: MANZANILLO | F11: FOB | G11: 1 | H11: 70 | I11: 70 | J11: 145 | K11: 550 | L11: 15 | M11: 60 | N11: =SUM(H11:M11) -> 910 | O11: N/A | P11: 2300 | Q11: 18-23 days | R11: =IFERROR(N11+IF(ISNUMBER(O11),O11,0)+IF(ISNUMBER(P11),P11,0),"") -> 3210 | S11: Freetrans
A12: SHA-Manzanillo (Yangzhou) | B12: Yangzhou RSL | C12: Puebla | D12: SHA | E12: MANZANILLO | F12: CIF | G12: 1 | H12: 70 | I12: 70 | J12: 145 | K12: 550 | L12: 15 | M12: 60 | N12: =SUM(H12:M12) -> 910 | O12: N/A | P12: 2300 | Q12: 18-23 days | R12: =IFERROR(N12+IF(ISNUMBER(O12),O12,0)+IF(ISNUMBER(P12),P12,0),"") -> 3210 | S12: Freetrans
A13: SHA-Manzanillo (Yuansheng) | B13: Zhejiang Yuansheng | C13: Puebla | D13: SHA | E13: MANZANILLO | F13: CIF | G13: 0.5 | H13: 70 | I13: 70 | J13: 145 | K13: 550 | L13: 15 | M13: 60 | N13: =SUM(H13:M13) -> 910 | O13: N/A | P13: 2300 | Q13: 18-23 days | R13: =IFERROR(N13+IF(ISNUMBER(O13),O13,0)+IF(ISNUMBER(P13),P13,0),"") -> 3210 | S13: Freetrans
A14: SHA-Manzanillo (Huafon Coil) | B14: Shanghai Huafon Coil | C14: Puebla | D14: SHA | E14: MANZANILLO | F14: CIF | G14: 1 | H14: 70 | I14: 70 | J14: 145 | K14: 250 | L14: 15 | M14: 60 | N14: =SUM(H14:M14) -> 610 | O14: N/A | P14: 2300 | Q14: 18-23 days | R14: =IFERROR(N14+IF(ISNUMBER(O14),O14,0)+IF(ISNUMBER(P14),P14,0),"") -> 2910 | S14: Freetrans
A15: SHA-Manzanillo (ABIC) | B15: Dalian ABIC | C15: Puebla | D15: SHA | E15: MANZANILLO | F15: CIF | G15: 1 | H15: 70 | I15: 70 | J15: 145 | K15: 200 | L15: 15 | M15: 50 | N15: =SUM(H15:M15) -> 550 | O15: N/A | P15: 2300 | Q15: 18-23 days | R15: =IFERROR(N15+IF(ISNUMBER(O15),O15,0)+IF(ISNUMBER(P15),P15,0),"") -> 2850 | S15: Freetrans
A16: SHA-Manzanillo (Boling) | B16: Chongqing Boling | C16: Puebla | D16: SHA | E16: MANZANILLO | F16: CIF | G16: 0.5 | H16: 70 | I16: 70 | J16: 145 | K16: 1550 | L16: 15 | M16: 60 | N16: =SUM(H16:M16) -> 1910 | O16: N/A | P16: 2300 | Q16: 18-23 days | R16: =IFERROR(N16+IF(ISNUMBER(O16),O16,0)+IF(ISNUMBER(P16),P16,0),"") -> 4210 | S16: Freetrans
A17: SHA-Manzanillo (AITD) | B17: AITD | C17: Saltillo | D17: SHA | E17: MANZANILLO | F17: CIF | G17: 1 | H17: 70 | I17: 70 | J17: 145 | K17: 350 | L17: 15 | M17: 60 | N17: =SUM(H17:M17) -> 710 | O17: N/A | P17: 2300 | Q17: 18-23 days | R17: =IFERROR(N17+IF(ISNUMBER(O17),O17,0)+IF(ISNUMBER(P17),P17,0),"") -> 3010 | S17: Freetrans
... A20: SHA-Manzanillo (Yida) | B20: Zhejiang Yida | C20: Puebla | D20: SHA | E20: MANZANILLO | F20: CIF | G20: 1 | H20: 70 | I20: 70 | J20: 145 | K20: 550 | L20: 15 | M20: 60 | N20: =SUM(H20:M20) -> 910 | O20: N/A | P20: 2300 | Q20: 18-23 days | R20: =IFERROR(N20+IF(ISNUMBER(O20),O20,0)+IF(ISNUMBER(P20),P20,0),"") -> 3210 | S20: Freetrans
A21: SHA-Manzanillo (PMC) | B21: Nanjing PMC | C21: Saltillo | D21: SHA | E21: MANZANILLO | F21: CIF | G21: 0 | H21: 70 | I21: 70 | J21: 145 | K21: 550 | L21: 15 | M21: 60 | N21: =SUM(H21:M21) -> 910 | O21: N/A | P21: - | Q21: 18-23 days | R21: =IFERROR(N21+IF(ISNUMBER(O21),O21,0)+IF(ISNUMBER(P21),P21,0),"") -> 910 | S21: 宇航
A22: SHA-Manzanillo (Shenda) | B22: Changsha Shenda | C22: Saltillo | D22: SHA | E22: MANZANILLO | F22: CIF | G22: 0 | H22: 70 | I22: 70 | J22: 145 | K22: 1500 | L22: 15 | M22: 60 | N22: =SUM(H22:M22) -> 1860 | O22: N/A | P22: - | Q22: 18-23 days | R22: =IFERROR(N22+IF(ISNUMBER(O22),O22,0)+IF(ISNUMBER(P22),P22,0),"") -> 1860 | S22: 宇航
A23: =_xlfn.CONCAT("AIUS | USA (HOU / Detroit / Savanna) | 5 条航线 | 两周需求 ", TEXT(SUM(G24:G28),"0.0")," HQ40") -> AIUS | USA (HOU / Detroit / Savanna) | 5 条航线 | 两周需求 3.0 HQ40
A24: SHA-HOU | B24: AINT - 666 Wenchang Rd, Tongzhou, Nantong | C24: AIUS TOC c/o GTZ, McAllen TX 78503 | D24: SHA | E24: HOU | F24: EXW | G24: 1 | H24: 70 | I24: 70 | J24: 140 | K24: 400 | L24: 10 | M24: 70 | N24: =SUM(H24:M24) -> 760 | O24: 2685 | P24: 3450 | Q24: 8-10 wks | R24: =IFERROR(N24+IF(ISNUMBER(O24),O24,0)+IF(ISNUMBER(P24),P24,0),"") -> 6895 | S24: KF
A25: SHA-Detroit | B25: AISH - 108 Chunguang Rd, Minhang, Shanghai | C25: AIUS c/o FTZ Metro, Highland Park MI | D25: SHA | E25: Detroit | F25: EXW | G25: 0 | H25: 70 | I25: 70 | J25: 140 | K25: 250 | L25: 10 | M25: 70 | N25: =SUM(H25:M25) -> 610 | O25: 885 | P25: - | R25: =IFERROR(N25+IF(ISNUMBER(O25),O25,0)+IF(ISNUMBER(P25),P25,0),"") -> 1495 | S25: -
A26: Laem-Savanna | B26: AITH, Rayong (WHA ESIE 1) | C26: AIUS Baxter, Winchester TN 37398 | D26: Laemchabang | E26: Savanna | F26: DAP | G26: 2 | H26: 70 | I26: 70 | J26: 140 | K26: 300 | L26: 30 | M26: 70 | N26: =SUM(H26:M26) -> 680 | O26: 2785 | P26: 3400 | Q26: 8-10 wks | R26: =IFERROR(N26+IF(ISNUMBER(O26),O26,0)+IF(ISNUMBER(P26),P26,0),"") -> 6865 | S26: Freetrans
A27: Nhava-Savanna | B27: Divine & Creative (India) | C27: AIUS Baxter, Winchester TN | D27: Nhava Sheva | E27: Savanna | F27: DAP | G27: 0 | H27: 70 | I27: 80 | J27: 160 | K27: 1000 | L27: 50 | M27: 75 | N27: =SUM(H27:M27) -> 1435 | O27: 2785 | P27: - | Q27: 7-9 wks | R27: =IFERROR(N27+IF(ISNUMBER(O27),O27,0)+IF(ISNUMBER(P27),P27,0),"") -> 4220 | S27: -
A28: SHA-Savanna | B28: AINT - 666 Wenchang Rd, Tongzhou, Nantong | C28: AIUS Baxter, Winchester TN | D28: SHA | E28: Savanna | F28: DAP | G28: 0 | H28: 70 | I28: 70 | J28: 140 | K28: 400 | L28: 10 | M28: 70 | N28: =SUM(H28:M28) -> 760 | O28: 2785 | P28: - | Q28: 6-8 wks | R28: =IFERROR(N28+IF(ISNUMBER(O28),O28,0)+IF(ISNUMBER(P28),P28,0),"") -> 3545 | S28: -
A29: =_xlfn.CONCAT("AISH | Asia → SHA (inbound) | 2 条航线 | 两周需求 ", TEXT(SUM(G30:G31),"0.0")," HQ40") -> AISH | Asia → SHA (inbound) | 2 条航线 | 两周需求 3.0 HQ40
A30: Bangkok-SHA | B30: Delta Electronics (Thailand), Chachoengsao | C30: AINT - 666 Wenchang Rd, Nantong | D30: Bangkok | E30: SHA | F30: EXW | G30: 1 | H30: 70 | I30: 50 | J30: 260 | K30: 325 | L30: 90 | M30: 80 | N30: =SUM(H30:M30) -> 875 | O30: 600 | P30: 1 | Q30: 15-20 days | R30: =IFERROR(N30+IF(ISNUMBER(O30),O30,0)+IF(ISNUMBER(P30),P30,0),"") -> 1476 | S30: Superchain
A31: Incheon-SHA | B31: Woory Industrial, Yongin Korea | C31: AINT - 666 Wenchang Rd, Nantong | D31: INCHEON | E31: SHA | F31: EXW | G31: 2 | H31: 50 | I31: 35 | J31: 125 | K31: 280 | L31: 150 | M31: 50 | N31: =SUM(H31:M31) -> 690 | O31: 600 | P31: 1 | Q31: 5-10 days | R31: =IFERROR(N31+IF(ISNUMBER(O31),O31,0)+IF(ISNUMBER(P31),P31,0),"") -> 1291 | S31: Superchain
A32: =_xlfn.CONCAT("AITH | Thailand (Laemchabang) | 5 条航线 | 两周需求 ", TEXT(SUM(G33:G37),"0.0")," HQ40") -> AITH | Thailand (Laemchabang) | 5 条航线 | 两周需求 5.0 HQ40
A33: SHA-Laem | B33: AISH - 108 Chunguang Rd, Minhang, Shanghai | C33: AI Thermal Systems (Thailand), Chonburi | D33: SHA | E33: Laemchabang | F33: EXW | G33: 1 | H33: 70 | I33: 70 | J33: 140 | K33: 250 | L33: 10 | M33: 70 | N33: =SUM(H33:M33) -> 610 | O33: 800 | P33: 900 | Q33: 15-20 days | R33: =IFERROR(N33+IF(ISNUMBER(O33),O33,0)+IF(ISNUMBER(P33),P33,0),"") -> 2310 | S33: Bondex
A34: SHA-Laem (Huafon) | B34: Shanghai Huafon Aluminium, Jinshan | C34: AITH, Rayong (WHA ESIE 1) | D34: SHA | E34: Laemchabang | F34: EXW | G34: 1 | H34: 70 | I34: 70 | J34: 140 | K34: 250 | L34: 10 | M34: 70 | N34: =SUM(H34:M34) -> 610 | O34: 800 | P34: 900 | Q34: 15-20 days | R34: =IFERROR(N34+IF(ISNUMBER(O34),O34,0)+IF(ISNUMBER(P34),P34,0),"") -> 2310 | S34: Bondex
A35: Tianjin-Laem | B35: Hyo Seong Electric (Tianjin) | C35: AITH, Chonburi | D35: Tianjin | E35: Laemchabang | F35: EXW | G35: 0 | H35: 70 | I35: 70 | J35: 140 | K35: 420 | L35: 30 | M35: 70 | N35: =SUM(H35:M35) -> 800 | O35: 800 | P35: 1100 | Q35: 18-23 days | R35: =IFERROR(N35+IF(ISNUMBER(O35),O35,0)+IF(ISNUMBER(P35),P35,0),"") -> 2700 | S35: Bondex
A36: Dubai-Laem | B36: OSE Industries LLC, Dubai | C36: AITH, Rayong (WHA ESIE 1) | D36: Dubai | E36: Laemchabang | F36: EXW | G36: 0 | H36: 70 | I36: 70 | J36: 140 | K36: 420 | L36: 30 | M36: 70 | N36: =SUM(H36:M36) -> 800 | O36: 800 | P36: - | Q36: 20-25 days | R36: =IFERROR(N36+IF(ISNUMBER(O36),O36,0)+IF(ISNUMBER(P36),P36,0),"") -> 1600 | S36: -
A37: Laem-Hamburg | B37: AITH, Rayong (WHA ESIE 1) | C37: AI Thermal (Slovakia) s.r.o., Nitra | D37: Laemchabang | E37: Hamburg | F37: DDP | G37: 3 | H37: 70 | I37: 70 | J37: 140 | K37: 300 | L37: 30 | M37: 70 | N37: =SUM(H37:M37) -> 680 | O37: 2200 | P37: 4000 | Q37: 9-10 wks | R37: =IFERROR(N37+IF(ISNUMBER(O37),O37,0)+IF(ISNUMBER(P37),P37,0),"") -> 6880 | S37: Bondex
A38: =_xlfn.CONCAT("AISK | Slovakia (Hamburg) | 3 条航线 | 两周需求 ", TEXT(SUM(G39:G41),"0.0")," HQ40") -> AISK | Slovakia (Hamburg) | 3 条航线 | 两周需求 2.0 HQ40
A39: SHA-Hamburg | B39: AINT - 666 Wenchang Rd, Nantong | C39: AI Thermal (Slovakia) s.r.o., Nitra | D39: SHA | E39: Hamburg | F39: EXW | G39: 1 | H39: 70 | I39: 70 | J39: 140 | K39: 400 | L39: 10 | M39: 70 | N39: =SUM(H39:M39) -> 760 | O39: 2200 | P39: 2000 | Q39: 8-9 wks | R39: =IFERROR(N39+IF(ISNUMBER(O39),O39,0)+IF(ISNUMBER(P39),P39,0),"") -> 4960 | S39: Bestunit
A40: Nhava-Hamburg | B40: Divine Tooling (India) | C40: AI Thermal (Slovakia), Nitra | D40: Nhava Sheva | E40: Hamburg | F40: EXW | G40: 1 | H40: 70 | I40: 70 | J40: 140 | K40: 300 | L40: 250 | M40: 70 | N40: =SUM(H40:M40) -> 900 | O40: 2200 | P40: - | Q40: 8-10 wks | R40: =IFERROR(N40+IF(ISNUMBER(O40),O40,0)+IF(ISNUMBER(P40),P40,0),"") -> 3100 | S40: -
A41: Bangkok-Hamburg | B41: Delta Electronics (Thailand) | C41: AI Thermal (Slovakia), Nitra | D41: Bangkok | E41: Hamburg | F41: EXW | G41: 0 | H41: 70 | I41: 70 | J41: 140 | K41: 300 | L41: 250 | M41: 70 | N41: =SUM(H41:M41) -> 900 | O41: 2200 | P41: 4000 | Q41: 9-10 wks | R41: =IFERROR(N41+IF(ISNUMBER(O41),O41,0)+IF(ISNUMBER(P41),P41,0),"") -> 7100 | S41: Bondex

Sheet 26.5月
A1: Lane | B1: Consignor | C1: Consignee | D1: POL | E1: POD | F1: Incoterm | G1: HQ40 Demand | H1: Booking | I1: Doc | J1: THC | K1: Loading | L1: Customs | M1: B/L | N1: Local Subtotal | O1: Dest Subtotal | P1: Sea Freight | Q1: Transit Time | R1: Total (USD) | S1: Winning Forwarder
A2: AI-Turkey | Turkey (Izmit) | 2 条航线 | 月需求 19 HQ40
A3: SHA-Izmit | B3: AINT - 666 Wenchang Rd, Tongzhou, Nantong | C3: AI Termal Sistemleri A.Ş., İstanbul | D3: SHA | E3: Izmit | F3: DAP | G3: 16 | H3: 70 | I3: 70 | J3: 140 | K3: 400 | L3: 10 | M3: 70 | N3: =SUM(H3:M3) -> 760 | O3: 950 | P3: 2899 | Q3: 10-12 wks | R3: =IFERROR(N3+IF(ISNUMBER(O3),O3,0)+IF(ISNUMBER(P3),P3,0),"") -> 4609 | S3: BESTUNIT
A4: SAI-Izmit | B4: SAI - 3 Gaobao Lake East Rd, Yubei, Chongqing | C4: AI Termal Sistemleri A.Ş., İstanbul | D4: SHA | E4: Izmit | F4: EXW | G4: 3 | H4: 70 | I4: 70 | J4: 170 | K4: 250 | L4: 50 | M4: 50 | N4: =SUM(H4:M4) -> 660 | O4: 950 | P4: 2949 | Q4: 11-13 wks | R4: =IFERROR(N4+IF(ISNUMBER(O4),O4,0)+IF(ISNUMBER(P4),P4,0),"") -> 4559 | S4: BESTUNIT
A5: AIMX | Mexico (Manzanillo) | 17 条航线 | 月需求 31 HQ40
A6: Laem-Manzanillo | B6: AITH | C6: Puebla + Saltillo | D6: Laemchabang | E6: MANZANILLO | F6: CIF | G6: 9 | H6: 70 | I6: 50 | J6: 260 | K6: 250 | L6: 90 | M6: 80 | N6: =SUM(H6:M6) -> 800 | O6: N/A | P6: 2430 | Q6: 35-45 days | R6: =IFERROR(N6+IF(ISNUMBER(O6),O6,0)+IF(ISNUMBER(P6),P6,0),"") -> 3230 | S6: Bondex
A7: Bangkok-Manzanillo | B7: DELTA | C7: Saltillo | D7: Bangkok | E7: MANZANILLO | F7: CIF | G7: 2 | H7: 70 | I7: 50 | J7: 260 | K7: 325 | L7: 90 | M7: 80 | N7: =SUM(H7:M7) -> 875 | O7: N/A | P7: 2430 | Q7: 35-45 days | R7: =IFERROR(N7+IF(ISNUMBER(O7),O7,0)+IF(ISNUMBER(P7),P7,0),"") -> 3305 | S7: Bondex
A8: Laem-Manzanillo (TNC) | B8: TNC | C8: Puebla | D8: Laemchabang | E8: MANZANILLO | F8: CIF | G8: 1 | H8: 70 | I8: 50 | J8: 260 | K8: 250 | L8: 90 | M8: 80 | N8: =SUM(H8:M8) -> 800 | O8: N/A | P8: 2430 | Q8: 35-45 days | R8: =IFERROR(N8+IF(ISNUMBER(O8),O8,0)+IF(ISNUMBER(P8),P8,0),"") -> 3230 | S8: Bondex
A9: Nhava-Manzanillo | B9: Creative Components | C9: Saltillo | D9: Nhava Sheva | E9: MANZANILLO | F9: CIF | G9: 2 | H9: 70 | I9: 80 | J9: 160 | K9: 1000 | L9: 50 | M9: 75 | N9: =SUM(H9:M9) -> 1435 | O9: N/A | P9: 3389 | Q9: 50-55 days | R9: =IFERROR(N9+IF(ISNUMBER(O9),O9,0)+IF(ISNUMBER(P9),P9,0),"") -> 4824 | S9: Kaifu
A10: Incheon-Manzanillo | B10: WOORY | C10: Saltillo | D10: INCHEON | E10: MANZANILLO | F10: CIF | G10: 1 | H10: 70 | I10: 35 | J10: 145 | K10: 350 | L10: 150 | M10: 50 | N10: =SUM(H10:M10) -> 800 | O10: N/A | P10: 2800 | Q10: 25-30 days | R10: =IFERROR(N10+IF(ISNUMBER(O10),O10,0)+IF(ISNUMBER(P10),P10,0),"") -> 3600 | S10: Bondex
A11: SHA-Manzanillo (Chao Li) | B11: Jiangsu Chao Li | C11: Puebla | D11: SHA | E11: MANZANILLO | F11: FOB | G11: 2 | H11: 70 | I11: 70 | J11: 145 | K11: 550 | L11: 15 | M11: 60 | N11: =SUM(H11:M11) -> 910 | O11: N/A | P11: 2300 | Q11: 18-23 days | R11: =IFERROR(N11+IF(ISNUMBER(O11),O11,0)+IF(ISNUMBER(P11),P11,0),"") -> 3210 | S11: Freetrans
A12: SHA-Manzanillo (Yangzhou) | B12: Yangzhou RSL | C12: Puebla | D12: SHA | E12: MANZANILLO | F12: CIF | G12: 1 | H12: 70 | I12: 70 | J12: 145 | K12: 550 | L12: 15 | M12: 60 | N12: =SUM(H12:M12) -> 910 | O12: N/A | P12: 2300 | Q12: 18-23 days | R12: =IFERROR(N12+IF(ISNUMBER(O12),O12,0)+IF(ISNUMBER(P12),P12,0),"") -> 3210 | S12: Freetrans
A13: SHA-Manzanillo (Yuansheng) | B13: Zhejiang Yuansheng | C13: Puebla | D13: SHA | E13: MANZANILLO | F13: CIF | G13: 0.5 | H13: 70 | I13: 70 | J13: 145 | K13: 550 | L13: 15 | M13: 60 | N13: =SUM(H13:M13) -> 910 | O13: N/A | P13: 2300 | Q13: 18-23 days | R13: =IFERROR(N13+IF(ISNUMBER(O13),O13,0)+IF(ISNUMBER(P13),P13,0),"") -> 3210 | S13: Freetrans
A14: SHA-Manzanillo (Huafon Coil) | B14: Shanghai Huafon Coil | C14: Puebla | D14: SHA | E14: MANZANILLO | F14: CIF | G14: 2 | H14: 70 | I14: 70 | J14: 145 | K14: 250 | L14: 15 | M14: 60 | N14: =SUM(H14:M14) -> 610 | O14: N/A | P14: 2300 | Q14: 18-23 days | R14: =IFERROR(N14+IF(ISNUMBER(O14),O14,0)+IF(ISNUMBER(P14),P14,0),"") -> 2910 | S14: Freetrans
A15: SHA-Manzanillo (ABIC) | B15: Dalian ABIC | C15: Puebla | D15: SHA | E15: MANZANILLO | F15: CIF | G15: 2 | H15: 70 | I15: 70 | J15: 145 | K15: 200 | L15: 15 | M15: 50 | N15: =SUM(H15:M15) -> 550 | O15: N/A | P15: 2300 | Q15: 18-23 days | R15: =IFERROR(N15+IF(ISNUMBER(O15),O15,0)+IF(ISNUMBER(P15),P15,0),"") -> 2850 | S15: Freetrans
A16: SHA-Manzanillo (Boling) | B16: Chongqing Boling | C16: Puebla | D16: SHA | E16: MANZANILLO | F16: CIF | G16: 0.5 | H16: 70 | I16: 70 | J16: 145 | K16: 1550 | L16: 15 | M16: 60 | N16: =SUM(H16:M16) -> 1910 | O16: N/A | P16: 2300 | Q16: 18-23 days | R16: =IFERROR(N16+IF(ISNUMBER(O16),O16,0)+IF(ISNUMBER(P16),P16,0),"") -> 4210 | S16: Freetrans
A17: SHA-Manzanillo (AITD) | B17: AITD | C17: Saltillo | D17: SHA | E17: MANZANILLO | F17: CIF | G17: 1 | H17: 70 | I17: 70 | J17: 145 | K17: 350 | L17: 15 | M17: 60 | N17: =SUM(H17:M17) -> 710 | O17: N/A | P17: 2300 | Q17: 18-23 days | R17: =IFERROR(N17+IF(ISNUMBER(O17),O17,0)+IF(ISNUMBER(P17),P17,0),"") -> 3010 | S17: Freetrans
... A22: SHA-Manzanillo (Shenda) | B22: Changsha Shenda | C22: Saltillo | D22: SHA | E22: MANZANILLO | F22: CIF | G22: 2 | H22: 70 | I22: 70 | J22: 145 | K22: 1500 | L22: 15 | M22: 60 | N22: =SUM(H22:M22) -> 1860 | O22: N/A | P22: 2300 | Q22: 18-23 days | R22: =IFERROR(N22+IF(ISNUMBER(O22),O22,0)+IF(ISNUMBER(P22),P22,0),"") -> 4160 | S22: Freetrans
A23: AIUS | USA (HOU / Detroit / Savanna) | 5 条航线 | 月需求 8 HQ40
A24: SHA-HOU | B24: AINT - 666 Wenchang Rd, Tongzhou, Nantong | C24: AIUS TOC c/o GTZ, McAllen TX 78503 | D24: SHA | E24: HOU | F24: EXW | G24: 2 | H24: 70 | I24: 70 | J24: 140 | K24: 400 | L24: 10 | M24: 70 | N24: =SUM(H24:M24) -> 760 | O24: 2685 | P24: 3249 | Q24: 8-10 wks | R24: =IFERROR(N24+IF(ISNUMBER(O24),O24,0)+IF(ISNUMBER(P24),P24,0),"") -> 6694 | S24: Kaifu
A25: SHA-Detroit | B25: AISH - 108 Chunguang Rd, Minhang, Shanghai | C25: AIUS c/o FTZ Metro, Highland Park MI | D25: SHA | E25: Detroit | F25: EXW | G25: 0 | H25: 70 | I25: 70 | J25: 140 | K25: 250 | L25: 10 | M25: 70 | N25: =SUM(H25:M25) -> 610 | O25: 885 | P25: 4169 | Q25: 8-10 wks | R25: =IFERROR(N25+IF(ISNUMBER(O25),O25,0)+IF(ISNUMBER(P25),P25,0),"") -> 5664 | S25: Kaifu
A26: Laem-Savanna | B26: AITH, Rayong (WHA ESIE 1) | C26: AIUS Baxter, Winchester TN 37398 | D26: Laemchabang | E26: Savanna | F26: DAP | G26: 3 | H26: 70 | I26: 70 | J26: 140 | K26: 300 | L26: 30 | M26: 70 | N26: =SUM(H26:M26) -> 680 | O26: 2785 | P26: 3830 | Q26: 8-10 wks | R26: =IFERROR(N26+IF(ISNUMBER(O26),O26,0)+IF(ISNUMBER(P26),P26,0),"") -> 7295 | S26: Kaifu
A27: Nhava-Savanna | B27: Divine & Creative (India) | C27: AIUS Baxter, Winchester TN | D27: Nhava Sheva | E27: Savanna | F27: DAP | G27: 1 | H27: 70 | I27: 80 | J27: 160 | K27: 1000 | L27: 50 | M27: 75 | N27: =SUM(H27:M27) -> 1435 | O27: 2785 | P27: 2999 | Q27: 7-9 wks | R27: =IFERROR(N27+IF(ISNUMBER(O27),O27,0)+IF(ISNUMBER(P27),P27,0),"") -> 7219 | S27: Kaifu
A28: SHA-Savanna | B28: AINT - 666 Wenchang Rd, Tongzhou, Nantong | C28: AIUS Baxter, Winchester TN | D28: SHA | E28: Savanna | F28: DAP | G28: 2 | H28: 70 | I28: 70 | J28: 140 | K28: 400 | L28: 10 | M28: 70 | N28: =SUM(H28:M28) -> 760 | O28: 2785 | P28: 3250 | Q28: 6-8 wks | R28: =IFERROR(N28+IF(ISNUMBER(O28),O28,0)+IF(ISNUMBER(P28),P28,0),"") -> 6795 | S28: Kaifu
A29: AISH | Asia → SHA (inbound) | 2 条航线 | 月需求 6 HQ40
A30: Bangkok-SHA | B30: Delta Electronics (Thailand), Chachoengsao | C30: AINT - 666 Wenchang Rd, Nantong | D30: Bangkok | E30: SHA | F30: EXW | G30: 3 | H30: 70 | I30: 50 | J30: 260 | K30: 325 | L30: 90 | M30: 80 | N30: =SUM(H30:M30) -> 875 | O30: 600 | P30: 1 | Q30: 15-20 days | R30: =IFERROR(N30+IF(ISNUMBER(O30),O30,0)+IF(ISNUMBER(P30),P30,0),"") -> 1476 | S30: Superchain
A31: Incheon-SHA | B31: Woory Industrial, Yongin Korea | C31: AINT - 666 Wenchang Rd, Nantong | D31: INCHEON | E31: SHA | F31: EXW | G31: 3 | H31: 50 | I31: 35 | J31: 125 | K31: 280 | L31: 150 | M31: 50 | N31: =SUM(H31:M31) -> 690 | O31: 600 | P31: 1 | Q31: 5-10 days | R31: =IFERROR(N31+IF(ISNUMBER(O31),O31,0)+IF(ISNUMBER(P31),P31,0),"") -> 1291 | S31: Superchain
A32: AITH | Thailand (Laemchabang) | 5 条航线 | 月需求 11 HQ40
A33: SHA-Laem | B33: AISH - 108 Chunguang Rd, Minhang, Shanghai | C33: AI Thermal Systems (Thailand), Chonburi | D33: SHA | E33: Laemchabang | F33: EXW | G33: 1 | H33: 70 | I33: 70 | J33: 140 | K33: 250 | L33: 10 | M33: 70 | N33: =SUM(H33:M33) -> 610 | O33: 800 | P33: 1230 | Q33: 15-20 days | R33: =IFERROR(N33+IF(ISNUMBER(O33),O33,0)+IF(ISNUMBER(P33),P33,0),"") -> 2640 | S33: Bondex
A34: SHA-Laem (Huafon) | B34: Shanghai Huafon Aluminium, Jinshan | C34: AITH, Rayong (WHA ESIE 1) | D34: SHA | E34: Laemchabang | F34: EXW | G34: 3 | H34: 70 | I34: 70 | J34: 140 | K34: 250 | L34: 10 | M34: 70 | N34: =SUM(H34:M34) -> 610 | O34: 800 | P34: 1230 | Q34: 15-20 days | R34: =IFERROR(N34+IF(ISNUMBER(O34),O34,0)+IF(ISNUMBER(P34),P34,0),"") -> 2640 | S34: Bondex
A35: Tianjin-Laem | B35: Hyo Seong Electric (Tianjin) | C35: AITH, Chonburi | D35: Tianjin | E35: Laemchabang | F35: EXW | G35: 0.5 | H35: 70 | I35: 70 | J35: 140 | K35: 420 | L35: 30 | M35: 70 | N35: =SUM(H35:M35) -> 800 | O35: 800 | P35: 1380 | Q35: 18-23 days | R35: =IFERROR(N35+IF(ISNUMBER(O35),O35,0)+IF(ISNUMBER(P35),P35,0),"") -> 2980 | S35: Bondex
A36: Dubai-Laem | B36: OSE Industries LLC, Dubai | C36: AITH, Rayong (WHA ESIE 1) | D36: Dubai | E36: Laemchabang | F36: EXW | G36: 0.5 | H36: 70 | I36: 70 | J36: 140 | K36: 420 | L36: 30 | M36: 70 | N36: =SUM(H36:M36) -> 800 | O36: 800 | Q36: 20-25 days | R36: =IFERROR(N36+IF(ISNUMBER(O36),O36,0)+IF(ISNUMBER(P36),P36,0),"") -> 1600
A37: Laem-Hamburg | B37: AITH, Rayong (WHA ESIE 1) | C37: AI Thermal (Slovakia) s.r.o., Nitra | D37: Laemchabang | E37: Hamburg | F37: DDP | G37: 6 | H37: 70 | I37: 70 | J37: 140 | K37: 300 | L37: 30 | M37: 70 | N37: =SUM(H37:M37) -> 680 | O37: 2200 | P37: 3580 | Q37: 9-10 wks | R37: =IFERROR(N37+IF(ISNUMBER(O37),O37,0)+IF(ISNUMBER(P37),P37,0),"") -> 6460 | S37: Bondex
A38: AISK | Slovakia (Hamburg) | 3 条航线 | 月需求 3.5 HQ40
A39: SHA-Hamburg | B39: AINT - 666 Wenchang Rd, Nantong | C39: AI Thermal (Slovakia) s.r.o., Nitra | D39: SHA | E39: Hamburg | F39: EXW | G39: 1 | H39: 70 | I39: 70 | J39: 140 | K39: 400 | L39: 10 | M39: 70 | N39: =SUM(H39:M39) -> 760 | O39: 2200 | P39: 2000 | Q39: 8-9 wks | R39: =IFERROR(N39+IF(ISNUMBER(O39),O39,0)+IF(ISNUMBER(P39),P39,0),"") -> 4960 | S39: Bestunit
A40: Nhava-Hamburg | B40: Divine Tooling (India) | C40: AI Thermal (Slovakia), Nitra | D40: Nhava Sheva | E40: Hamburg | F40: EXW | G40: 2 | H40: 70 | I40: 70 | J40: 140 | K40: 300 | L40: 250 | M40: 70 | N40: =SUM(H40:M40) -> 900 | O40: 2200 | P40: 3149 | Q40: 8-10 wks | R40: =IFERROR(N40+IF(ISNUMBER(O40),O40,0)+IF(ISNUMBER(P40),P40,0),"") -> 6249 | S40: Kaifu
A41: Bangkok-Hamburg | B41: Delta Electronics (Thailand) | C41: AI Thermal (Slovakia), Nitra | D41: Bangkok | E41: Hamburg | F41: EXW | G41: 0.5 | H41: 70 | I41: 70 | J41: 140 | K41: 300 | L41: 250 | M41: 70 | N41: =SUM(H41:M41) -> 900 | O41: 2200 | P41: 3530 | Q41: 9-10 wks | R41: =IFERROR(N41+IF(ISNUMBER(O41),O41,0)+IF(ISNUMBER(P41),P41,0),"") -> 6630 | S41: Bondex

Sheet 26.6月
A1: Lane | B1: Consignor | C1: Consignee | D1: POL | E1: POD | F1: Incoterm | G1: HQ40 Demand | H1: Booking | I1: Doc | J1: THC | K1: Loading | L1: Customs | M1: B/L | N1: Local Subtotal | O1: Dest Subtotal | P1: Sea Freight | Q1: Transit Time | R1: Total (USD) | S1: Winning Forwarder
A2: AI-Turkey | Turkey (Izmit) | 2 条航线 | 月需求 19 HQ40
A3: SHA-Izmit | B3: AINT - 666 Wenchang Rd, Tongzhou, Nantong | C3: AI Termal Sistemleri A.Ş., İstanbul | D3: SHA | E3: Izmit | F3: DAP | G3: 16 | H3: 70 | I3: 70 | J3: 140 | K3: 400 | L3: 10 | M3: 70 | N3: =SUM(H3:M3) -> 760 | O3: 950 | P3: 4990 | Q3: 10-12 wks | R3: =IFERROR(N3+IF(ISNUMBER(O3),O3,0)+IF(ISNUMBER(P3),P3,0),"") -> 6700 | S3: BESTUNIT
A4: SAI-Izmit | B4: SAI - 3 Gaobao Lake East Rd, Yubei, Chongqing | C4: AI Termal Sistemleri A.Ş., İstanbul | D4: SHA | E4: Izmit | F4: EXW | G4: 3 | H4: 70 | I4: 70 | J4: 170 | K4: 250 | L4: 50 | M4: 50 | N4: =SUM(H4:M4) -> 660 | O4: 950 | P4: 6940 | Q4: 11-13 wks | R4: =IFERROR(N4+IF(ISNUMBER(O4),O4,0)+IF(ISNUMBER(P4),P4,0),"") -> 8550 | S4: BESTUNIT
A5: AIMX | Mexico (Manzanillo) | 17 条航线 | 月需求 31 HQ40
A6: Laem-Manzanillo | B6: AITH | C6: Puebla + Saltillo | D6: Laemchabang | E6: MANZANILLO | F6: CIF | G6: 9 | H6: 70 | I6: 50 | J6: 260 | K6: 250 | L6: 90 | M6: 80 | N6: =SUM(H6:M6) -> 800 | O6: N/A | P6: 4180 | Q6: 35-45 days | R6: =IFERROR(N6+IF(ISNUMBER(O6),O6,0)+IF(ISNUMBER(P6),P6,0),"") -> 4980 | S6: Bondex
A7: Bangkok-Manzanillo | B7: DELTA | C7: Saltillo | D7: Bangkok | E7: MANZANILLO | F7: CIF | G7: 2 | H7: 70 | I7: 50 | J7: 260 | K7: 325 | L7: 90 | M7: 80 | N7: =SUM(H7:M7) -> 875 | O7: N/A | P7: 4180 | Q7: 35-45 days | R7: =IFERROR(N7+IF(ISNUMBER(O7),O7,0)+IF(ISNUMBER(P7),P7,0),"") -> 5055 | S7: Bondex
A8: Laem-Manzanillo (TNC) | B8: TNC | C8: Puebla | D8: Laemchabang | E8: MANZANILLO | F8: CIF | G8: 1 | H8: 70 | I8: 50 | J8: 260 | K8: 250 | L8: 90 | M8: 80 | N8: =SUM(H8:M8) -> 800 | O8: N/A | P8: 4180 | Q8: 35-45 days | R8: =IFERROR(N8+IF(ISNUMBER(O8),O8,0)+IF(ISNUMBER(P8),P8,0),"") -> 4980 | S8: Bondex
A9: Nhava-Manzanillo | B9: Creative Components | C9: Saltillo | D9: Nhava Sheva | E9: MANZANILLO | F9: CIF | G9: 2 | H9: 70 | I9: 80 | J9: 160 | K9: 1000 | L9: 50 | M9: 75 | N9: =SUM(H9:M9) -> 1435 | O9: N/A | P9: 4500 | Q9: 50-55 days | R9: =IFERROR(N9+IF(ISNUMBER(O9),O9,0)+IF(ISNUMBER(P9),P9,0),"") -> 5935 | S9: Kaifu
A10: Incheon-Manzanillo | B10: WOORY | C10: Saltillo | D10: INCHEON | E10: MANZANILLO | F10: CIF | G10: 1 | H10: 70 | I10: 35 | J10: 145 | K10: 350 | L10: 150 | M10: 50 | N10: =SUM(H10:M10) -> 800 | O10: N/A | P10: 5440 | Q10: 25-30 days | R10: =IFERROR(N10+IF(ISNUMBER(O10),O10,0)+IF(ISNUMBER(P10),P10,0),"") -> 6240 | S10: Bondex
A11: SHA-Manzanillo (Chao Li) | B11: Jiangsu Chao Li | C11: Puebla | D11: SHA | E11: MANZANILLO | F11: FOB | G11: 2 | H11: 70 | I11: 70 | J11: 145 | K11: 550 | L11: 15 | M11: 60 | N11: =SUM(H11:M11) -> 910 | O11: N/A | P11: 4520 | Q11: 18-23 days | R11: =IFERROR(N11+IF(ISNUMBER(O11),O11,0)+IF(ISNUMBER(P11),P11,0),"") -> 5430 | S11: Freetrans
A12: SHA-Manzanillo (Yangzhou) | B12: Yangzhou RSL | C12: Puebla | D12: SHA | E12: MANZANILLO | F12: CIF | G12: 1 | H12: 70 | I12: 70 | J12: 145 | K12: 550 | L12: 15 | M12: 60 | N12: =SUM(H12:M12) -> 910 | O12: N/A | P12: 4520 | Q12: 18-23 days | R12: =IFERROR(N12+IF(ISNUMBER(O12),O12,0)+IF(ISNUMBER(P12),P12,0),"") -> 5430 | S12: Freetrans
A13: SHA-Manzanillo (Yuansheng) | B13: Zhejiang Yuansheng | C13: Puebla | D13: SHA | E13: MANZANILLO | F13: CIF | G13: 0.5 | H13: 70 | I13: 70 | J13: 145 | K13: 550 | L13: 15 | M13: 60 | N13: =SUM(H13:M13) -> 910 | O13: N/A | P13: 4520 | Q13: 18-23 days | R13: =IFERROR(N13+IF(ISNUMBER(O13),O13,0)+IF(ISNUMBER(P13),P13,0),"") -> 5430 | S13: Freetrans
A14: SHA-Manzanillo (Huafon Coil) | B14: Shanghai Huafon Coil | C14: Puebla | D14: SHA | E14: MANZANILLO | F14: CIF | G14: 2 | H14: 70 | I14: 70 | J14: 145 | K14: 250 | L14: 15 | M14: 60 | N14: =SUM(H14:M14) -> 610 | O14: N/A | P14: 4520 | Q14: 18-23 days | R14: =IFERROR(N14+IF(ISNUMBER(O14),O14,0)+IF(ISNUMBER(P14),P14,0),"") -> 5130 | S14: Freetrans
A15: SHA-Manzanillo (ABIC) | B15: Dalian ABIC | C15: Puebla | D15: SHA | E15: MANZANILLO | F15: CIF | G15: 2 | H15: 70 | I15: 70 | J15: 145 | K15: 200 | L15: 15 | M15: 50 | N15: =SUM(H15:M15) -> 550 | O15: N/A | P15: 4560 | Q15: 18-23 days | R15: =IFERROR(N15+IF(ISNUMBER(O15),O15,0)+IF(ISNUMBER(P15),P15,0),"") -> 5110 | S15: Freetrans
A16: SHA-Manzanillo (Boling) | B16: Chongqing Boling | C16: Puebla | D16: SHA | E16: MANZANILLO | F16: CIF | G16: 0.5 | H16: 70 | I16: 70 | J16: 145 | K16: 1550 | L16: 15 | M16: 60 | N16: =SUM(H16:M16) -> 1910 | O16: N/A | P16: 4520 | Q16: 18-23 days | R16: =IFERROR(N16+IF(ISNUMBER(O16),O16,0)+IF(ISNUMBER(P16),P16,0),"") -> 6430 | S16: Freetrans
A17: SHA-Manzanillo (AITD) | B17: AITD | C17: Saltillo | D17: SHA | E17: MANZANILLO | F17: CIF | G17: 1 | H17: 70 | I17: 70 | J17: 145 | K17: 350 | L17: 15 | M17: 60 | N17: =SUM(H17:M17) -> 710 | O17: N/A | P17: 4520 | Q17: 18-23 days | R17: =IFERROR(N17+IF(ISNUMBER(O17),O17,0)+IF(ISNUMBER(P17),P17,0),"") -> 5230 | S17: Freetrans
... A22: SHA-Manzanillo (Shenda) | B22: Changsha Shenda | C22: Saltillo | D22: SHA | E22: MANZANILLO | F22: CIF | G22: 2 | H22: 70 | I22: 70 | J22: 145 | K22: 1500 | L22: 15 | M22: 60 | N22: =SUM(H22:M22) -> 1860 | O22: N/A | P22: 4520 | Q22: 18-23 days | R22: =IFERROR(N22+IF(ISNUMBER(O22),O22,0)+IF(ISNUMBER(P22),P22,0),"") -> 6380 | S22: Freetrans
A23: AIUS | USA (HOU / Detroit / Savanna) | 5 条航线 | 月需求 8 HQ40
A24: SHA-HOU | B24: AINT - 666 Wenchang Rd, Tongzhou, Nantong | C24: AIUS TOC c/o GTZ, McAllen TX 78503 | D24: SHA | E24: HOU | F24: EXW | G24: 2 | H24: 70 | I24: 70 | J24: 140 | K24: 400 | L24: 10 | M24: 70 | N24: =SUM(H24:M24) -> 760 | O24: 2685 | P24: 4800 | Q24: 8-10 wks | R24: =IFERROR(N24+IF(ISNUMBER(O24),O24,0)+IF(ISNUMBER(P24),P24,0),"") -> 8245 | S24: Kaifu
A25: SHA-Detroit | B25: AISH - 108 Chunguang Rd, Minhang, Shanghai | C25: AIUS c/o FTZ Metro, Highland Park MI | D25: SHA | E25: Detroit | F25: EXW | G25: 0 | H25: 70 | I25: 70 | J25: 140 | K25: 250 | L25: 10 | M25: 70 | N25: =SUM(H25:M25) -> 610 | O25: 885 | P25: 5800 | Q25: 8-10 wks | R25: =IFERROR(N25+IF(ISNUMBER(O25),O25,0)+IF(ISNUMBER(P25),P25,0),"") -> 7295 | S25: Kaifu
A26: Laem-Savanna | B26: AITH, Rayong (WHA ESIE 1) | C26: AIUS Baxter, Winchester TN 37398 | D26: Laemchabang | E26: Savanna | F26: DAP | G26: 3 | H26: 70 | I26: 70 | J26: 140 | K26: 300 | L26: 30 | M26: 70 | N26: =SUM(H26:M26) -> 680 | O26: 2785 | P26: 5300 | Q26: 8-10 wks | R26: =IFERROR(N26+IF(ISNUMBER(O26),O26,0)+IF(ISNUMBER(P26),P26,0),"") -> 8765 | S26: Kaifu
A27: Nhava-Savanna | B27: Divine & Creative (India) | C27: AIUS Baxter, Winchester TN | D27: Nhava Sheva | E27: Savanna | F27: DAP | G27: 1 | H27: 70 | I27: 80 | J27: 160 | K27: 1000 | L27: 50 | M27: 75 | N27: =SUM(H27:M27) -> 1435 | O27: 2785 | P27: 5200 | Q27: 7-9 wks | R27: =IFERROR(N27+IF(ISNUMBER(O27),O27,0)+IF(ISNUMBER(P27),P27,0),"") -> 9420 | S27: Kaifu
A28: SHA-Savanna | B28: AINT - 666 Wenchang Rd, Tongzhou, Nantong | C28: AIUS Baxter, Winchester TN | D28: SHA | E28: Savanna | F28: DAP | G28: 2 | H28: 70 | I28: 70 | J28: 140 | K28: 400 | L28: 10 | M28: 70 | N28: =SUM(H28:M28) -> 760 | O28: 2785 | P28: 5200 | Q28: 6-8 wks | R28: =IFERROR(N28+IF(ISNUMBER(O28),O28,0)+IF(ISNUMBER(P28),P28,0),"") -> 8745 | S28: Kaifu
A29: AISH | Asia → SHA (inbound) | 2 条航线 | 月需求 6 HQ40
A30: Bangkok-SHA | B30: Delta Electronics (Thailand), Chachoengsao | C30: AINT - 666 Wenchang Rd, Nantong | D30: Bangkok | E30: SHA | F30: EXW | G30: 3 | H30: 70 | I30: 50 | J30: 260 | K30: 325 | L30: 90 | M30: 80 | N30: =SUM(H30:M30) -> 875 | O30: 600 | P30: 1 | Q30: 15-20 days | R30: =IFERROR(N30+IF(ISNUMBER(O30),O30,0)+IF(ISNUMBER(P30),P30,0),"") -> 1476 | S30: Superchain
A31: Incheon-SHA | B31: Woory Industrial, Yongin Korea | C31: AINT - 666 Wenchang Rd, Nantong | D31: INCHEON | E31: SHA | F31: EXW | G31: 3 | H31: 50 | I31: 35 | J31: 125 | K31: 280 | L31: 150 | M31: 50 | N31: =SUM(H31:M31) -> 690 | O31: 600 | P31: 1 | Q31: 5-10 days | R31: =IFERROR(N31+IF(ISNUMBER(O31),O31,0)+IF(ISNUMBER(P31),P31,0),"") -> 1291 | S31: Superchain
A32: AITH | Thailand (Laemchabang) | 5 条航线 | 月需求 11 HQ40
A33: SHA-Laem | B33: AISH - 108 Chunguang Rd, Minhang, Shanghai | C33: AI Thermal Systems (Thailand), Chonburi | D33: SHA | E33: Laemchabang | F33: EXW | G33: 1 | H33: 70 | I33: 70 | J33: 140 | K33: 250 | L33: 10 | M33: 70 | N33: =SUM(H33:M33) -> 610 | O33: 800 | P33: 1340 | Q33: 15-20 days | R33: =IFERROR(N33+IF(ISNUMBER(O33),O33,0)+IF(ISNUMBER(P33),P33,0),"") -> 2750 | S33: Bondex
A34: SHA-Laem (Huafon) | B34: Shanghai Huafon Aluminium, Jinshan | C34: AITH, Rayong (WHA ESIE 1) | D34: SHA | E34: Laemchabang | F34: EXW | G34: 3 | H34: 70 | I34: 70 | J34: 140 | K34: 250 | L34: 10 | M34: 70 | N34: =SUM(H34:M34) -> 610 | O34: 800 | P34: 1340 | Q34: 15-20 days | R34: =IFERROR(N34+IF(ISNUMBER(O34),O34,0)+IF(ISNUMBER(P34),P34,0),"") -> 2750 | S34: Bondex
A35: Tianjin-Laem | B35: Hyo Seong Electric (Tianjin) | C35: AITH, Chonburi | D35: Tianjin | E35: Laemchabang | F35: EXW | G35: 0.5 | H35: 70 | I35: 70 | J35: 140 | K35: 420 | L35: 30 | M35: 70 | N35: =SUM(H35:M35) -> 800 | O35: 800 | P35: 1600 | Q35: 18-23 days | R35: =IFERROR(N35+IF(ISNUMBER(O35),O35,0)+IF(ISNUMBER(P35),P35,0),"") -> 3200 | S35: Bondex
A36: Dubai-Laem | B36: OSE Industries LLC, Dubai | C36: AITH, Rayong (WHA ESIE 1) | D36: Dubai | E36: Laemchabang | F36: EXW | G36: 0.5 | H36: 70 | I36: 70 | J36: 140 | K36: 420 | L36: 30 | M36: 70 | N36: =SUM(H36:M36) -> 800 | O36: 800 | P36: 150 | Q36: 20-25 days | R36: =IFERROR(N36+IF(ISNUMBER(O36),O36,0)+IF(ISNUMBER(P36),P36,0),"") -> 1750
A37: Laem-Hamburg | B37: AITH, Rayong (WHA ESIE 1) | C37: AI Thermal (Slovakia) s.r.o., Nitra | D37: Laemchabang | E37: Hamburg | F37: DDP | G37: 6 | H37: 70 | I37: 70 | J37: 140 | K37: 300 | L37: 30 | M37: 70 | N37: =SUM(H37:M37) -> 680 | O37: 2200 | P37: 3380 | Q37: 9-10 wks | R37: =IFERROR(N37+IF(ISNUMBER(O37),O37,0)+IF(ISNUMBER(P37),P37,0),"") -> 6260 | S37: Bondex
A38: AISK | Slovakia (Hamburg) | 3 条航线 | 月需求 3.5 HQ40
A39: SHA-Hamburg | B39: AINT - 666 Wenchang Rd, Nantong | C39: AI Thermal (Slovakia) s.r.o., Nitra | D39: SHA | E39: Hamburg | F39: EXW | G39: 1 | H39: 70 | I39: 70 | J39: 140 | K39: 400 | L39: 10 | M39: 70 | N39: =SUM(H39:M39) -> 760 | O39: 2200 | P39: 3500 | Q39: 8-9 wks | R39: =IFERROR(N39+IF(ISNUMBER(O39),O39,0)+IF(ISNUMBER(P39),P39,0),"") -> 6460 | S39: Bestunit
A40: Nhava-Hamburg | B40: Divine Tooling (India) | C40: AI Thermal (Slovakia), Nitra | D40: Nhava Sheva | E40: Hamburg | F40: EXW | G40: 2 | H40: 70 | I40: 70 | J40: 140 | K40: 300 | L40: 250 | M40: 70 | N40: =SUM(H40:M40) -> 900 | O40: 2200 | P40: 3380 | Q40: 8-10 wks | R40: =IFERROR(N40+IF(ISNUMBER(O40),O40,0)+IF(ISNUMBER(P40),P40,0),"") -> 6480 | S40: Kaifu
A41: Bangkok-Hamburg | B41: Delta Electronics (Thailand) | C41: AI Thermal (Slovakia), Nitra | D41: Bangkok | E41: Hamburg | F41: EXW | G41: 0.5 | H41: 70 | I41: 70 | J41: 140 | K41: 300 | L41: 250 | M41: 70 | N41: =SUM(H41:M41) -> 900 | O41: 2200 | P41: 3530 | Q41: 9-10 wks | R41: =IFERROR(N41+IF(ISNUMBER(O41),O41,0)+IF(ISNUMBER(P41),P41,0),"") -> 6630 | S41: Bondex

Sheet 招标需求
B1: Consignor | C1: Consignee | D1: Port of Origin | E1: Port of Destination | F1: Incoterm | G1: May. HQ40 Demand | H1: D2D Transit Time (Normal vessel) | I1: Sea Freight Cost (Normal Vessel) | J1: D2D Transit Time (Express vessel) | L1: Basic requirements | M1: 竞标价为 after-tax
A2: AI-Turkey | B2: AINT- 666 Wenchang Road, Tongzhou District, Nantong City | C2: AIR INTERNATIONAL TERMAL SİSTEMLERİ A. Ş.ESENTEPE MAH. ALİ KAYA SK. POLAT PLAZA B BLOK NO: 1/1İÇ KAPI NO:69 ŞİŞLİ/İSTANBUL | D2: SHA | E2: Izmit | F2: DAP | G2: 16 | H2: 10-12 wks | J2: - | K2: - | L2: 1. Online tracking system 2. Only accept railway transportation from SAI to SHA port 3. No Israel vessels 4. All deposits are coverd by the forwarder. | M2: 分开招标
B3: SAI-No. 3 Gaobao Lake East Road, Yubei District, Chongqing | C3: AIR INTERNATIONAL TERMAL SİSTEMLERİ A. Ş.ESENTEPE MAH. ALİ KAYA SK. POLAT PLAZA B BLOK NO: 1/1İÇ KAPI NO:69 ŞİŞLİ/İSTANBUL | D3: SHA | E3: Izmit | F3: EXW | G3: 3 | H3: 11-13 wks | J3: - | K3: -
A5: AIUS TOC | B5: AINT- 666 Wenchang Road, Tongzhou District, Nantong City | C5: Air International Thermal System-c/o GTZ WAREHOUSE LLC-662 SOUTH 33rd STREET, BUILDING -J, McALLEN, TX 78503 | D5: SHA | E5: HOU | F5: EXW | G5: 2 | H5: 8-10 wks | J5: - | K5: - | L5: 1. Online tracking system (Mandatory requirement) 2. Experienced with 'Foreign trade zone' application process
B6: AISH-108 Chunguang Road, Minhang District, Shanghai | C6: Air International Thermal Systems-c/o FTZ METRO WAREHOUSE-1200 E. McNICHOLS RD, HIGHLAND PARK, MI 48203. | D6: SHA | E6: Detroit | F6: EXW | G6: 0
A7: AIUS Baxter | B7: Air International Thermal Systems (Thailand) Ltd. (Head Office) 500/46 Moo 3, WHA Eastern Seaboard Industrial Estate 1 Tambol Tasit, Amphur Pluak Daeng, Rayong 21140 Thailand | C7: Air International Thermal Systems 466 Baxter Lane Winchester ,TN,USA ,37398 | D7: Laem Chabang | E7: Savanna | F7: DAP | G7: 3 | H7: 8-10 wks | J7: - | K7: - | L7: 1. Forwarder needs to contact with our designated US customs broker Rohlig for clearance. | M7: 固定清关broker：Rohlig
B8: Divine & Creative from India | C8: Air International Thermal Systems 466 Baxter Lane Winchester ,TN,USA ,37398 | D8: Nhava Sheva | E8: Savanna | F8: DAP | G8: 1 | H8: 7-9 wks | J8: - | K8: -
B9: AINT- 666 Wenchang Road, Tongzhou District, Nantong City | C9: Air International Thermal Systems 466 Baxter Lane Winchester ,TN,USA ,37398 | D9: SHA | E9: Savanna | F9: DAP | G9: 2 | H9: 6-8 wks | J9: - | K9: -
A11: AISK | B11: AINT- 666 Wenchang Road, Tongzhou District, Nantong City,China | C11: Air International Thermal (Slovakia) s.r.o. Prologis Park Nitra, DC3 Cez panske 4289/9 949 01 Nitra Slovakia | D11: SHA | E11: Hamburg | F11: EXW | G11: 1 | H11: 8-9 wks | J11: - | K11: - | L11: 1. Online tracking system (Mandatory required by Ford) 2. Prefer Port of Hamburg rather than Koper, which provides better service | M11: 当地自行招标 国内仅供对比参考
B12: Divine tooling | C12: Air International Thermal (Slovakia) s.r.o. Prologis Park Nitra, DC3 Cez panske 4289/9 949 01 Nitra Slovakia | D12: Nhava Sheva | E12: Hamburg | F12: EXW | G12: 2 | H12: 8-10 wks | J12: - | K12: -
B13: Delta Electronics | C13: Air International Thermal (Slovakia) s.r.o. Prologis Park Nitra, DC3 Cez panske 4289/9 949 01 Nitra Slovakia | D13: Bangkok | E13: Hamburg | F13: EXW | G13: 0.5 | H13: 9-10 wks | J13: - | K13: -
A15: AITH | B15: Air International (Shanghai) Co.,Ltd. No. 108 Chun guang Road, XinZhuang Industrial Zone Minhang, Shanghai P.R. China 201108 | C15: Air International Thermal Systems (Thailand) Ltd. 41/17,18,19 MOO 8,T.BOWIN,A.SRIRACHA,CHONBURI,20230 THAILAND | D15: SHA | E15: Laemchabang | F15: EXW | G15: 1 | H15: 15-20 days | J15: - | K15: - | L15: 1. Only accept 1 local broker 2. No significant bad history (Delay, waiting time too long, etc) | M15: 当地自行招标 国内仅供对比参考
B16: Shanghai Huafon Aluminium Corporati 1111# yuegong road Jinshan district Shanghai Zip Code: 201506 | C16: Air International Thermal Systems (Thailand) Ltd. 500/46 Moo 3, WHA Eastern Seaboard Industrial Estate 1, T. Tasit, A. Pluekdaeng, Rayong 21140 | D16: SHA | E16: Laemchabang | F16: EXW | G16: 3 | H16: 15-20 days | J16: - | K16: -
B17: Hyo Seong Electric (Toanjin) Co.,Ltd No.99, Xi San Dao, Tianjin Airport Industrial Park, TPFTZ, Tianjin, P.R. China | C17: Air International Thermal Systems (Thailand) Ltd. 41/17,18,19 MOO 8,T.BOWIN,A.SRIRACHA,CHONBURI,20230 THAILAND | D17: Tianjin | E17: Laemchabang | F17: EXW | G17: 0.5 | H17: 18-23 days | J17: - | K17: -
B18: OSE Industries LLC. Dubai Industrial Park, Office#103, First Floor, Building 1, Dubai Industrial City, Dubai, UAE, Post Box 126344 | C18: Air International Thermal Systems (Thailand) Ltd. 500/46 Moo 3, WHA Eastern Seaboard Industrial Estate 1, T. Tasit, A. Pluekdaeng, Rayong 21140 | D18: Dubai | E18: Laemchabang | F18: EXW | G18: 0.5 | H18: 20-25 days | J18: - | K18: -
B19: Air International Thermal Systems (Thailand) Ltd. 500/46 Moo 3, WHA Eastern Seaboard Industrial Estate 1, T. Tasit, A. Pluekdaeng, Rayong 21140 | C19: Air International Thermal (Slovakia) s.r.o. Prologis Park Nitra, DC3 Cez panske 4289/9 949 01 Nitra Slovakia | D19: Laemchabang | E19: Hamburg | F19: DDP | G19: 6 | H19: 9-10 wks | J19: - | K19: -
A21: AISH | B21: DELTA ELECTRONICS (THAILAND) PUBLIC COMPANY LIMITED 111 MOO 9,BANGNA-TRAD RD.,TAMBOL BANGWUA AMPHUR BANGPAKONG CHACHOENGSAO, 24180 THAILAND | C21: AINT- 666 Wenchang Road, Tongzhou District, Nantong City | D21: Bangkok | E21: SHA | F21: EXW | G21: 3 | H21: 15-20 days | J21: - | K21: - | L21: 1. Pre-classification HS CODE service Attention: Woory's container type is 20GP, not 40HQ
B22: Woory Industrial Co.,Ltd #531, Jigok-dong, Kihung-gu Yongin-city, Kyonggi-Do, Korea | C22: AINT- 666 Wenchang Road, Tongzhou District, Nantong City | D22: INCHEON | E22: SHA | F22: EXW | G22: 3 | H22: 5-10 days | J22: - | K22: -
H23: D2P Transit Time | I23: Sea Freight Cost (Normal Vessel) | J23: D2D Transit Time (Express vessel) | K23: Sea Freight Cost (Express Vessel)
A24: AIMX | B24: AITH | C24: Puebla + Saltillo | D24: Laemchabang | E24: MANZANILLO | F24: CIF | G24: 9 | H24: 45-50 days | J24: 35-45 days | L24: 1. MBL must consignee directly to Forwarder and assignee all the shipments with FW. 2. As the service is D2P, the MBL must be consigned to Local FW (TRANSLAQ). 3. Guarantee letter with every FW to avoid payment of guarantees. AIMX will not pay any guarantee. 4. The FW must finance the local charges at destination or assign a local forwarder. 5. We need 21 free days of demurrages 6. Send Pre-alerts and documents once the vessel departs (Invoice, PL, BL, Freight cost, EIR). If the arrival notification is sent 1 week before the arrival of vessel, the additional costs will be charged directly to the Forwarder (Storages and demurrages) 7. Do Not ship our load in a reefer container, because the cost of guarantees is higher than the regular containers. 8. Assignee containers in good conditions to avoid payment of damage´s containers. 9. Always send to us the EIR´S and pictures of container´s conditions that you place in origin with each supplier. 10. Able to combine light and heavy pallets from different suppliers into one container 11. SHA - MANZANILLO line only use express vessels and appointed shipping companies (Cosco, MSC, HPL, MSK, CMA) 12. 尽量两个 或者 双数货柜在同一条船里，节省码头调度费 13. 货代需免除or自垫押箱费。 | M24: 固定清关broker：Enciso
B25: DETLA | C25: Saltillo | D25: Bangkok | E25: MANZANILLO | F25: CIF | G25: 2
B26: TNC | C26: Puebla | D26: Laemchabang | E26: MANZANILLO | F26: CIF | G26: 1
B27: Creative Components | C27: Saltillo | D27: Nhava Sheva | E27: MANZANILLO | F27: CIF | G27: 2 | H27: 50-55 days | J27: - | K27: -
B28: WOORY | C28: Saltillo | D28: INCHEON | E28: MANZANILLO | F28: CIF | G28: 1 | H28: 25-30 days | J28: 25-30 days
B29: Jiangsu Chao Li | C29: Puebla | D29: SHA | E29: MANZANILLO | F29: FOB | G29: 2 | H29: 27-32 days | J29: 18-23 days
B30: Yangzhou RSL | C30: Puebla | D30: SHA | E30: MANZANILLO | F30: CIF | G30: 1
B31: Zhejiang Yuansheng | C31: Puebla | D31: SHA | E31: MANZANILLO | F31: CIF | G31: 0.5
B32: Shanghai Huafon Coil | C32: Puebla | D32: SHA | E32: MANZANILLO | F32: CIF | G32: 2
B33: Dalian ABIC | C33: Puebla | D33: SHA | E33: MANZANILLO | F33: CIF | G33: 2
B34: Chongqing Boling | C34: Puebla | D34: SHA | E34: MANZANILLO | F34: CIF | G34: 0.5
B35: AITD | C35: Saltillo | D35: SHA | E35: MANZANILLO | F35: CIF | G35: 1
B36: AITD-Spring | C36: Saltillo | D36: Tianjin | E36: MANZANILLO | F36: CIF | G36: 1
B37: Wuhu Bokang | C37: Saltillo | D37: SHA | E37: MANZANILLO | F37: FOB | G37: 1
B38: Zhejiang Yida | C38: Puebla | D38: SHA | E38: MANZANILLO | F38: CIF | G38: 1
B39: Nanjing PMC | C39: Saltillo | D39: SHA | E39: MANZANILLO | F39: CIF | G39: 2
B40: Changsha Shenda | C40: Saltillo | D40: SHA | E40: MANZANILLO | F40: CIF | G40: 2
B41: Shanghai Keboda | C41: Puebla | D41: SHA | E41: MANZANILLO | F41: CIF | M41: LCL / pallets | N41: 7
B42: Wuxi Liu He | C42: Puebla | D42: SHA | E42: MANZANILLO | F42: CIF | N42: 15
B43: Yangzhou Featry | C43: Puebla | D43: SHA | E43: MANZANILLO | F43: CIF | N43: 14
B44: Hunan Dong Li | C44: Puebla | D44: SHA | E44: MANZANILLO | F44: CIF | N44: 1
B45: Shanghai Ganglong | C45: Puebla + Saltillo | D45: SHA | E45: MANZANILLO | F45: CIF | N45: 8
B46: Hefei Shengyuan | C46: Puebla | D46: SHA | E46: MANZANILLO | F46: CIF | N46: 2
B47: Tianjin Yuanhe | C47: Puebla | D47: SHA | E47: MANZANILLO | F47: CIF | N47: 2
B48: Tianjin Sunhoo | C48: Puebla | D48: SHA | E48: MANZANILLO | F48: CIF | N48: 4
B49: Zhejiang Xinrui | C49: Saltillo | D49: SHA | E49: MANZANILLO | F49: CIF | N49: 2
B50: Tai Thai Rubber | C50: Puebla | D50: Laemchabang | E50: MANZANILLO | F50: CIF | H50: 45-50 days | J50: 35-45 days | N50: 1
B51: Thai Nihon Seals | C51: Puebla | D51: Laemchabang | E51: MANZANILLO | F51: CIF | N51: 1
B52: Pacific Rubber | C52: Puebla | D52: Laemchabang | E52: MANZANILLO | F52: CIF | N52: 3

Sheet _Backup_5月

Sheet _Backup_6月
G1: 发货人本地费用明细 | M1: 收货人本地费用
B2: Consignor | C2: Consignee | D2: Port of Origin | E2: Port of Destination | F2: Incoterm | G2: Booking Fee 订舱费 | H2: Documentation Fee 文件费 | I2: THC - Terminal Handling Charge码头操作费 | J2: Loading Fee 提货费 | K2: Customs Declaration Fee 报关费 | L2: B/L Fee 提单正本，电放操作费 | M2: Destination local cost | N2: June. HQ40 Demand | O2: D2D Transit Time (Normal vessel) | P2: Sea Freight Cost (Normal Vessel) | Q2: Forwarder (Normal Vessel) | R2: Basic requirements | S2: 竞标价为 after-tax
A3: AI-Turkey | B3: AINT- 666 Wenchang Road, Tongzhou District, Nantong City | C3: AIR INTERNATIONAL TERMAL SİSTEMLERİ A. Ş.ESENTEPE MAH. ALİ KAYA SK. POLAT PLAZA B BLOK NO: 1/1İÇ KAPI NO:69 ŞİŞLİ/İSTANBUL | D3: SHA | E3: Izmit | F3: DAP | G3: 70 | H3: 70 | I3: 140 | J3: 400 | K3: 10 | L3: 70 | M3: 950 | N3: 16 | O3: 10-12 wks | P3: 4990 | Q3: Bestunit+Holiton | R3: 1. Online tracking system 2. Only accept railway transportation from SAI to SHA port 3. No Israel vessels 4. All deposits are coverd by the forwarder. | S3: 分开招标
B4: SAI-No. 3 Gaobao Lake East Road, Yubei District, Chongqing | C4: AIR INTERNATIONAL TERMAL SİSTEMLERİ A. Ş.ESENTEPE MAH. ALİ KAYA SK. POLAT PLAZA B BLOK NO: 1/1İÇ KAPI NO:69 ŞİŞLİ/İSTANBUL | D4: SHA | E4: Izmit | F4: EXW | G4: 70 | H4: 70 | I4: 170 | J4: 250 | K4: 50 | L4: 50 | M4: 950 | N4: 3 | O4: 11-13 wks | P4: 6940 | Q4: Bondex
A6: AIUS TOC | B6: AINT- 666 Wenchang Road, Tongzhou District, Nantong City | C6: Air International Thermal System-c/o GTZ WAREHOUSE LLC-662 SOUTH 33rd STREET, BUILDING -J, McALLEN, TX 78503 | D6: SHA | E6: HOU | F6: EXW | G6: 70 | H6: 70 | I6: 140 | J6: 400 | K6: 10 | L6: 70 | M6: 2685 | N6: 2 | O6: 8-10 wks | P6: 4800 | Q6: KF | R6: 1. Online tracking system (Mandatory requirement) 2. Experienced with 'Foreign trade zone' application process
B7: AISH-108 Chunguang Road, Minhang District, Shanghai | C7: Air International Thermal Systems-c/o FTZ METRO WAREHOUSE-1200 E. McNICHOLS RD, HIGHLAND PARK, MI 48203. | D7: SHA | E7: Detroit | F7: EXW | G7: 70 | H7: 70 | I7: 140 | J7: 250 | K7: 10 | L7: 70 | M7: 885 | N7: 0 | P7: 5800 | Q7: KF
A8: AIUS Baxter | B8: Air International Thermal Systems (Thailand) Ltd. (Head Office) 500/46 Moo 3, WHA Eastern Seaboard Industrial Estate 1 Tambol Tasit, Amphur Pluak Daeng, Rayong 21140 Thailand | C8: Air International Thermal Systems 466 Baxter Lane Winchester ,TN,USA ,37398 | D8: Laem Chabang | E8: Savanna | F8: DAP | G8: 70 | H8: 70 | I8: 140 | J8: 300 | K8: 30 | L8: 70 | M8: 2785 | N8: 4 | O8: 8-10 wks | P8: 5300 | Q8: KF | R8: 1. Forwarder needs to contact with our designated US customs broker Rohlig for clearance. | S8: 固定清关broker：Rohlig
B9: Divine & Creative from India | C9: Air International Thermal Systems 466 Baxter Lane Winchester ,TN,USA ,37398 | D9: Nhava Sheva | E9: Savanna | F9: DAP | G9: 70 | H9: 80 | I9: 160 | J9: 1000 | K9: 50 | L9: 75 | M9: 2785 | N9: 3 | O9: 7-9 wks | P9: 5200 | Q9: KF
B10: AINT- 666 Wenchang Road, Tongzhou District, Nantong City | C10: Air International Thermal Systems 466 Baxter Lane Winchester ,TN,USA ,37398 | D10: SHA | E10: Savanna | F10: DAP | G10: 70 | H10: 70 | I10: 140 | J10: 400 | K10: 10 | L10: 70 | M10: 2785 | N10: 1 | O10: 6-8 wks | P10: 5200 | Q10: KF
A12: AISK | B12: AINT- 666 Wenchang Road, Tongzhou District, Nantong City,China | C12: Air International Thermal (Slovakia) s.r.o. Prologis Park Nitra, DC3 Cez panske 4289/9 949 01 Nitra Slovakia | D12: SHA | E12: Hamburg | F12: EXW | G12: 70 | H12: 70 | I12: 140 | J12: 400 | K12: 10 | L12: 70 | M12: 2200 | N12: 1 | O12: 8-9 wks | P12: 3500 | Q12: Bondex | R12: 1. Online tracking system (Mandatory required by Ford) 2. Prefer Port of Hamburg rather than Koper, which provides better service
B13: Divine tooling | C13: Air International Thermal (Slovakia) s.r.o. Prologis Park Nitra, DC3 Cez panske 4289/9 949 01 Nitra Slovakia | D13: Nhava Sheva | E13: Hamburg | F13: EXW | G13: 70 | H13: 70 | I13: 140 | J13: 300 | K13: 250 | L13: 70 | M13: 2200 | N13: 2 | O13: 8-10 wks | P13: - | Q13: -
B14: Delta Electronics | C14: Air International Thermal (Slovakia) s.r.o. Prologis Park Nitra, DC3 Cez panske 4289/9 949 01 Nitra Slovakia | D14: Bangkok | E14: Hamburg | F14: EXW | G14: 70 | H14: 70 | I14: 140 | J14: 300 | K14: 250 | L14: 70 | M14: 2200 | N14: 0.5 | O14: 9-10 wks | P14: 3380 | Q14: Bondex
A16: AITH | B16: Air International (Shanghai) Co.,Ltd. No. 108 Chun guang Road, XinZhuang Industrial Zone Minhang, Shanghai P.R. China 201108 | C16: Air International Thermal Systems (Thailand) Ltd. 41/17,18,19 MOO 8,T.BOWIN,A.SRIRACHA,CHONBURI,20230 THAILAND | D16: SHA | E16: Laemchabang | F16: EXW | G16: 70 | H16: 70 | I16: 140 | J16: 250 | K16: 10 | L16: 70 | M16: 800 | N16: 1 | O16: 15-20 days | P16: 1340 | Q16: Bondex | R16: 1. Only accept 1 local broker 2. No significant bad history (Delay, waiting time too long, etc)
B17: Shanghai Huafon Aluminium Corporati 1111# yuegong road Jinshan district Shanghai Zip Code: 201506 | C17: Air International Thermal Systems (Thailand) Ltd. 500/46 Moo 3, WHA Eastern Seaboard Industrial Estate 1, T. Tasit, A. Pluekdaeng, Rayong 21140 | D17: SHA | E17: Laemchabang | F17: EXW | G17: 70 | H17: 70 | I17: 140 | J17: 250 | K17: 10 | L17: 70 | M17: 800 | N17: 3 | O17: 15-20 days | P17: 1340 | Q17: Bondex
B18: Hyo Seong Electric (Toanjin) Co.,Ltd No.99, Xi San Dao, Tianjin Airport Industrial Park, TPFTZ, Tianjin, P.R. China | C18: Air International Thermal Systems (Thailand) Ltd. 41/17,18,19 MOO 8,T.BOWIN,A.SRIRACHA,CHONBURI,20230 THAILAND | D18: Tianjin | E18: Laemchabang | F18: EXW | G18: 70 | H18: 70 | I18: 140 | J18: 420 | K18: 30 | L18: 70 | M18: 800 | N18: 0.5 | O18: 18-23 days | P18: 1600 | Q18: Bondex
B19: OSE Industries LLC. Dubai Industrial Park, Office#103, First Floor, Building 1, Dubai Industrial City, Dubai, UAE, Post Box 126344 | C19: Air International Thermal Systems (Thailand) Ltd. 500/46 Moo 3, WHA Eastern Seaboard Industrial Estate 1, T. Tasit, A. Pluekdaeng, Rayong 21140 | D19: Dubai | E19: Laemchabang | F19: EXW | G19: 70 | H19: 70 | I19: 140 | J19: 420 | K19: 30 | L19: 70 | M19: 800 | N19: 0.5 | O19: 20-25 days | P19: - | Q19: -
B20: Air International Thermal Systems (Thailand) Ltd. 500/46 Moo 3, WHA Eastern Seaboard Industrial Estate 1, T. Tasit, A. Pluekdaeng, Rayong 21140 | C20: Air International Thermal (Slovakia) s.r.o. Prologis Park Nitra, DC3 Cez panske 4289/9 949 01 Nitra Slovakia | D20: Laemchabang | E20: Hamburg | F20: DDP | G20: 70 | H20: 70 | I20: 140 | J20: 300 | K20: 30 | L20: 70 | M20: 2200 | N20: 6 | O20: 9-10 wks | P20: 3380 | Q20: Bondex
A22: AISH | B22: DELTA ELECTRONICS (THAILAND) PUBLIC COMPANY LIMITED 111 MOO 9,BANGNA-TRAD RD.,TAMBOL BANGWUA AMPHUR BANGPAKONG CHACHOENGSAO, 24180 THAILAND | C22: AINT- 666 Wenchang Road, Tongzhou District, Nantong City | D22: Bangkok | E22: SHA | F22: EXW | G22: 70 | H22: 50 | I22: 260 | J22: 325 | K22: 90 | L22: 80 | M22: 600 | N22: 3 | O22: 15-20 days | P22: 1 | Q22: Superchain | R22: 1. Pre-classification HS CODE service Attention: Woory's container type is 20GP, not 40HQ
B23: Woory Industrial Co.,Ltd #531, Jigok-dong, Kihung-gu Yongin-city, Kyonggi-Do, Korea | C23: AINT- 666 Wenchang Road, Tongzhou District, Nantong City | D23: INCHEON | E23: SHA | F23: EXW | G23: 50 | H23: 35 | I23: 125 | J23: 280 | K23: 150 | L23: 50 | M23: 600 | N23: 1 | O23: 5-10 days | P23: 1 | Q23: Superchain
O24: D2D Transit Time (Express vessel) | P24: Sea Freight Cost (Express Vessel) | Q24: Forwarder (Express Vessel)
A25: AIMX | B25: AITH | C25: Puebla + Saltillo | D25: Laemchabang | E25: MANZANILLO | F25: CIF | G25: 70 | H25: 50 | I25: 260 | J25: 250 | K25: 90 | L25: 80 | M25: N/A | N25: 8 | O25: 35-45 days | P25: 4180 | Q25: Bondex | R25: 1. MBL must consignee directly to Forwarder and assignee all the shipments with FW. 2. As the service is D2P, the MBL must be consigned to Local FW (TRANSLAQ). 3. Guarantee letter with every FW to avoid payment of guarantees. AIMX will not pay any guarantee. 4. The FW must finance the local charges at destination or assign a local forwarder. 5. We need 21 free days of demurrages 6. Send Pre-alerts and documents once the vessel departs (Invoice, PL, BL, Freight cost, EIR). If the arrival notification is sent 1 week before the arrival of vessel, the additional costs will be charged directly to the Forwarder (Storages and demurrages) 7. Do Not ship our load in a reefer container, because the cost of guarantees is higher than the regular containers. 8. Assignee containers in good conditions to avoid payment of damage´s containers. 9. Always send to us the EIR´S and pictures of container´s conditions that you place in origin with each supplier. 10. Able to combine light and heavy pallets from different suppliers into one container 11. SHA - MANZANILLO line only use express vessels and appointed shipping companies (Cosco, MSC, HPL, MSK, CMA) 12. 尽量两个 或者 双数货柜在同一条船里，节省码头调度费 13. 货代需免除or自垫押箱费。 | S25: 固定清关broker：Enciso
B26: DETLA | C26: Saltillo | D26: Bangkok | E26: MANZANILLO | F26: CIF | G26: 70 | H26: 50 | I26: 260 | J26: 325 | K26: 90 | L26: 80 | M26: N/A | N26: 2 | P26: 4180 | Q26: Bondex
B27: TNC | C27: Puebla | D27: Laemchabang | E27: MANZANILLO | F27: CIF | G27: 70 | H27: 50 | I27: 260 | J27: 250 | K27: 90 | L27: 80 | M27: N/A | N27: 1 | P27: 4180 | Q27: Bondex
B28: Creative Components | C28: Saltillo | D28: Nhava Sheva | E28: MANZANILLO | F28: CIF | G28: 70 | H28: 80 | I28: 160 | J28: 1000 | K28: 50 | L28: 75 | M28: N/A | N28: 2 | O28: 50-55 days | P28: 4500 | Q28: KF
B29: WOORY | C29: Saltillo | D29: INCHEON | E29: MANZANILLO | F29: CIF | G29: 70 | H29: 35 | I29: 145 | J29: 350 | K29: 150 | L29: 50 | M29: N/A | N29: 1 | O29: 25-30 days | P29: 5440 | Q29: Bondex
B30: Jiangsu Chao Li | C30: Puebla | D30: SHA | E30: MANZANILLO | F30: FOB | G30: 70 | H30: 70 | I30: 145 | J30: 550 | K30: 15 | L30: 60 | M30: N/A | N30: 2 | O30: 18-23 days | P30: 4520 | Q30: Freetrans
B31: Yangzhou RSL | C31: Puebla | D31: SHA | E31: MANZANILLO | F31: CIF | G31: 70 | H31: 70 | I31: 145 | J31: 550 | K31: 15 | L31: 60 | M31: N/A | N31: 1 | P31: 4520 | Q31: Freetrans
B32: Zhejiang Yuansheng | C32: Puebla | D32: SHA | E32: MANZANILLO | F32: CIF | G32: 70 | H32: 70 | I32: 145 | J32: 550 | K32: 15 | L32: 60 | M32: N/A | N32: 0.5 | P32: 4520 | Q32: Freetrans
B33: Shanghai Huafon Coil | C33: Puebla | D33: SHA | E33: MANZANILLO | F33: CIF | G33: 70 | H33: 70 | I33: 145 | J33: 250 | K33: 15 | L33: 60 | M33: N/A | N33: 2 | P33: 4520 | Q33: Freetrans
B34: Dalian ABIC | C34: Puebla | D34: SHA | E34: MANZANILLO | F34: CIF | G34: 70 | H34: 70 | I34: 145 | J34: 200 | K34: 15 | L34: 50 | M34: N/A | N34: 2 | P34: 4560 | Q34: Bondex
B35: Chongqing Boling | C35: Puebla | D35: SHA | E35: MANZANILLO | F35: CIF | G35: 70 | H35: 70 | I35: 145 | J35: 1550 | K35: 15 | L35: 60 | M35: N/A | N35: 0.5 | P35: 4520 | Q35: Freetrans
B36: AITD | C36: Saltillo | D36: SHA | E36: MANZANILLO | F36: CIF | G36: 70 | H36: 70 | I36: 145 | J36: 350 | K36: 15 | L36: 60 | M36: N/A | N36: 1 | P36: 4520 | Q36: Freetrans
B37: AITD-Spring | C37: Saltillo | D37: Tianjin | E37: MANZANILLO | F37: CIF | G37: 70 | H37: 70 | I37: 145 | J37: 200 | K37: 15 | L37: 50 | M37: N/A | N37: 1 | P37: 5440 | Q37: Bondex
B38: Wuhu Bokang | C38: Saltillo | D38: SHA | E38: MANZANILLO | F38: FOB | G38: 70 | H38: 70 | I38: 145 | J38: 50 | K38: 15 | L38: 60 | M38: N/A | N38: 1 | P38: 4520 | Q38: Freetrans
B39: Zhejiang Yida | C39: Puebla | D39: SHA | E39: MANZANILLO | F39: CIF | G39: 70 | H39: 70 | I39: 145 | J39: 550 | K39: 15 | L39: 60 | M39: N/A | N39: 1 | P39: 4520 | Q39: Freetrans
B40: Nanjing PMC | C40: Saltillo | D40: SHA | E40: MANZANILLO | F40: CIF | G40: 70 | H40: 70 | I40: 145 | J40: 550 | K40: 15 | L40: 60 | M40: N/A | N40: 2 | P40: 4520 | Q40: Freetrans
B41: Changsha Shenda | C41: Saltillo | D41: SHA | E41: MANZANILLO | F41: CIF | G41: 70 | H41: 70 | I41: 145 | J41: 1500 | K41: 15 | L41: 60 | M41: N/A | N41: 2 | P41: 4520 | Q41: Freetrans

Sheet _Backup_1月
G1: 发货人本地费用明细 | M1: 收货人本地费用
B2: Consignor | C2: Consignee | D2: Port of Origin | E2: Port of Destination | F2: Incoterm | G2: Booking Fee 订舱费 | H2: Documentation Fee 文件费 | I2: THC - Terminal Handling Charge码头操作费 | J2: Loading Fee 提货费 | K2: Customs Declaration Fee 报关费 | L2: B/L Fee 提单正本，电放操作费 | M2: Destination local cost | N2: Jan. HQ40 Demand | O2: D2D Transit Time (Normal vessel) | P2: Sea Freight Cost(Normal Vessel) | Q2: Forwarder | R2: Basic requirements | S2: 竞标价为 after-tax
A3: AI-Turkey | B3: AINT- 666 Wenchang Road, Tongzhou District, Nantong City | C3: AIR INTERNATIONAL TERMAL SİSTEMLERİ A. Ş.ESENTEPE MAH. ALİ KAYA SK. POLAT PLAZA B BLOK NO: 1/1İÇ KAPI NO:69 ŞİŞLİ/İSTANBUL | D3: SHA | E3: Izmit | F3: DAP | G3: 70 | H3: 70 | I3: 140 | J3: 400 | K3: 10 | L3: 70 | M3: 950 | N3: 16 | O3: 8-10 wks | P3: 3330 | Q3: Bestunit | R3: 1. Online tracking system 2. Only accept railway transportation from SAI to SHA port 3. Transit time should be between 8-10 weeks (any additional cost will be borne by the forwarder if vessel delayed more than 2 weeks) 4. No Israel vessels | S3: 分开招标
B4: SAI-No. 3 Gaobao Lake East Road, Yubei District, Chongqing | C4: AIR INTERNATIONAL TERMAL SİSTEMLERİ A. Ş.ESENTEPE MAH. ALİ KAYA SK. POLAT PLAZA B BLOK NO: 1/1İÇ KAPI NO:69 ŞİŞLİ/İSTANBUL | D4: SHA | E4: Izmit | F4: EXW | G4: 70 | H4: 70 | I4: 170 | J4: 250 | K4: 50 | L4: 50 | M4: 950 | N4: 4 | O4: 9-11 wks | P4: 4171 | Q4: Bestunit
A6: AIUS TOC | B6: AINT- 666 Wenchang Road, Tongzhou District, Nantong City | C6: Air International Thermal System-c/o GTZ WAREHOUSE LLC-662 SOUTH 33rd STREET, BUILDING -J, McALLEN, TX 78503 | D6: SHA | E6: HOU | F6: EXW | G6: 70 | H6: 70 | I6: 140 | J6: 400 | K6: 10 | L6: 70 | M6: 2685 | N6: 2 | O6: 8-10 wks | P6: 2390 | Q6: Bondex | R6: 1. Online tracking system (Mandatory requirement) 2. Experienced with 'Foreign trade zone' application process
B7: AISH-108 Chunguang Road, Minhang District, Shanghai | C7: Air International Thermal Systems-c/o FTZ METRO WAREHOUSE-1200 E. McNICHOLS RD, HIGHLAND PARK, MI 48203. | D7: SHA | E7: Detroit | F7: EXW | G7: 70 | H7: 70 | I7: 140 | J7: 250 | K7: 10 | L7: 70 | M7: 885 | N7: 2 | P7: 3640 | Q7: Bondex
A8: AIUS Baxter | B8: Air International Thermal Systems (Thailand) Ltd. (Head Office) 500/46 Moo 3, WHA Eastern Seaboard Industrial Estate 1 Tambol Tasit, Amphur Pluak Daeng, Rayong 21140 Thailand | C8: Air International Thermal Systems 466 Baxter Lane Winchester ,TN,USA ,37398 | D8: Laem Chabang | E8: Savanna | F8: DAP | G8: 70 | H8: 70 | I8: 140 | J8: 300 | K8: 30 | L8: 70 | M8: 2785 | N8: 4 | O8: 8-10 wks | P8: 2140 | Q8: Freetrans | R8: No need to do the customs clearance and pre-pay duties anymore | S8: 固定清关broker：Rohlig
B9: Divine & Creative from India | C9: Air International Thermal Systems 466 Baxter Lane Winchester ,TN,USA ,37398 | D9: Nhava Sheva | E9: Savanna | F9: DAP | G9: 70 | H9: 80 | I9: 160 | J9: 1000 | K9: 50 | L9: 75 | M9: 2785 | N9: 3 | O9: 7-9 wks | P9: 2490 | Q9: Freetrans
B10: AINT- 666 Wenchang Road, Tongzhou District, Nantong City | C10: Air International Thermal Systems 466 Baxter Lane Winchester ,TN,USA ,37398 | D10: SHA | E10: Savanna | F10: DAP | G10: 70 | H10: 70 | I10: 140 | J10: 400 | K10: 10 | L10: 70 | M10: 2785 | N10: 3 | O10: 6-8 wks | P10: 2247 | Q10: Freetrans
A12: AISK | B12: AINT- 666 Wenchang Road, Tongzhou District, Nantong City,China | C12: Air International Thermal (Slovakia) s.r.o. Prologis Park Nitra, DC3 Cez panske 4289/9 949 01 Nitra Slovakia | D12: SHA | E12: Hamburg | F12: EXW | G12: 70 | H12: 70 | I12: 140 | J12: 400 | K12: 10 | L12: 70 | M12: 2200 | N12: 1 | O12: 8-9 wks | P12: 2200 | Q12: Bestunit | R12: 1. Online tracking system (Mandatory required by Ford) 2. Prefer Port of Hamburg rather than Koper, which provides better service | S12: 当地自行招标，结果需要低于招标价格。
B13: Divine tooling | C13: Air International Thermal (Slovakia) s.r.o. Prologis Park Nitra, DC3 Cez panske 4289/9 949 01 Nitra Slovakia | D13: Nhava Sheva | E13: Hamburg | F13: EXW | G13: 70 | H13: 70 | I13: 140 | J13: 300 | K13: 250 | L13: 70 | M13: 2200 | N13: 2 | O13: 8-10 wks | P13: 1900 | Q13: Bestunit
B14: Delta Electronics | C14: Air International Thermal (Slovakia) s.r.o. Prologis Park Nitra, DC3 Cez panske 4289/9 949 01 Nitra Slovakia | D14: Bangkok | E14: Hamburg | F14: EXW | G14: 70 | H14: 70 | I14: 140 | J14: 300 | K14: 250 | L14: 70 | M14: 2200 | N14: 0.5 | O14: 9-10 wks | P14: 2690 | Q14: Bondex
A16: AITH | B16: Air International (Shanghai) Co.,Ltd. No. 108 Chun guang Road, XinZhuang Industrial Zone Minhang, Shanghai P.R. China 201108 | C16: Air International Thermal Systems (Thailand) Ltd. 41/17,18,19 MOO 8,T.BOWIN,A.SRIRACHA,CHONBURI,20230 THAILAND | D16: SHA | E16: Laemchabang | F16: EXW | G16: 70 | H16: 70 | I16: 140 | J16: 250 | K16: 10 | L16: 70 | M16: 800 | N16: 1 | O16: 15-20 days | P16: 1140 | Q16: Bondex | R16: 1. Only accept 1 local broker 2. No significant bad history (Delay, waiting time too long, etc) | S16: 当地自行招标，结果需要低于招标价格。
B17: Shanghai Huafon Aluminium Corporati 1111# yuegong road Jinshan district Shanghai Zip Code: 201506 | C17: Air International Thermal Systems (Thailand) Ltd. 500/46 Moo 3, WHA Eastern Seaboard Industrial Estate 1, T. Tasit, A. Pluekdaeng, Rayong 21140 | D17: SHA | E17: Laemchabang | F17: EXW | G17: 70 | H17: 70 | I17: 140 | J17: 250 | K17: 10 | L17: 70 | M17: 800 | N17: 3 | O17: 15-20 days | P17: 1140 | Q17: Bondex
B18: Hyo Seong Electric (Toanjin) Co.,Ltd No.99, Xi San Dao, Tianjin Airport Industrial Park, TPFTZ, Tianjin, P.R. China | C18: Air International Thermal Systems (Thailand) Ltd. 41/17,18,19 MOO 8,T.BOWIN,A.SRIRACHA,CHONBURI,20230 THAILAND | D18: Tianjin | E18: Laemchabang | F18: EXW | G18: 70 | H18: 70 | I18: 140 | J18: 420 | K18: 30 | L18: 70 | M18: 800 | N18: 0.5 | O18: 18-23 days | P18: 1340 | Q18: Bondex
B19: OSE Industries LLC. Dubai Industrial Park, Office#103, First Floor, Building 1, Dubai Industrial City, Dubai, UAE, Post Box 126344 | C19: Air International Thermal Systems (Thailand) Ltd. 500/46 Moo 3, WHA Eastern Seaboard Industrial Estate 1, T. Tasit, A. Pluekdaeng, Rayong 21140 | D19: Dubai | E19: Laemchabang | F19: EXW | G19: 70 | H19: 70 | I19: 140 | J19: 420 | K19: 30 | L19: 70 | M19: 800 | N19: 0.5 | O19: 20-25 days | P19: /
B20: Air International Thermal Systems (Thailand) Ltd. 500/46 Moo 3, WHA Eastern Seaboard Industrial Estate 1, T. Tasit, A. Pluekdaeng, Rayong 21140 | C20: Air International Thermal (Slovakia) s.r.o. Prologis Park Nitra, DC3 Cez panske 4289/9 949 01 Nitra Slovakia | D20: Laemchabang | E20: Hamburg | F20: DDP | G20: 70 | H20: 70 | I20: 140 | J20: 300 | K20: 30 | L20: 70 | M20: 2200 | N20: 6 | O20: 9-10 wks | P20: 3490 | Q20: Bondex
A22: AISH | B22: DELTA ELECTRONICS (THAILAND) PUBLIC COMPANY LIMITED 111 MOO 9,BANGNA-TRAD RD.,TAMBOL BANGWUA AMPHUR BANGPAKONG CHACHOENGSAO, 24180 THAILAND | C22: AINT- 666 Wenchang Road, Tongzhou District, Nantong City | D22: Bangkok | E22: SHA | F22: EXW | G22: 70 | H22: 50 | I22: 260 | J22: 325 | K22: 90 | L22: 80 | M22: 600 | N22: 2 | O22: 15-20 days | P22: 1 | Q22: Superchain | R22: 1. Delta transit time should be within 20 days after pickup. 2. Woory transit time should be within 10 days after pickup. 3. Any additional cost will be borne by the forwarder if vessel delayed more than 7 days. 4. Pre-classification HS CODE service
B23: Woory Industrial Co.,Ltd #531, Jigok-dong, Kihung-gu Yongin-city, Kyonggi-Do, Korea | C23: AINT- 666 Wenchang Road, Tongzhou District, Nantong City | D23: INCHEON | E23: SHA | F23: EXW | G23: 70 | H23: 35 | I23: 145 | J23: 350 | K23: 150 | L23: 50 | M23: 600 | N23: 1 | O23: 5-10 days | P23: 1 | Q23: Superchain
O24: D2P Transit Time | P24: Sea Freight Cost(Normal Vessel)
A25: AIMX | B25: AITH | C25: Puebla + Saltillo | D25: Laemchabang | E25: MANZANILLO | F25: CIF | G25: 70 | H25: 50 | I25: 260 | J25: 250 | K25: 90 | L25: 80 | M25: N/A | N25: 9 | O25: 45-50 days | P25: 1940 | Q25: Bondex | R25: 1. MBL must consignee directly to Forwarder and assignee all the shipments with FW. 2. As the service is D2P, the MBL must be consigned to Local FW (TRANSLAQ). 3. Guarantee letter with every FW to avoid payment of guarantees. AIMX will not pay any guarantee. 4. The FW must finance the local charges at destination or assign a local forwarder. 5. We need 21 free days of demurrages 6. Send Pre-alerts and documents once the vessel departs (Invoice, PL, BL, Freight cost, EIR). If the arrival notification is sent 1 week before the arrival of vessel, the additional costs will be charged directly to the Forwarder (Storages and demurrages) 7. Do Not ship our load in a reefer container, because the cost of guarantees is higher than the regular containers. 8. Assignee containers in good conditions to avoid payment of damage´s containers. 9. Always send to us the EIR´S and pictures of container´s conditions that you place in origin with each supplier. 10. Able to combine light and heavy pallets from different suppliers into one container 11. SHA - MANZANILLO line only use express vessels and appointed shipping companies (Cosco, MSC, HPL, MSK, CMA) | S25: 固定清关broker：Enciso
B26: DETLA | C26: Saltillo | D26: Bangkok | E26: MANZANILLO | F26: CIF | G26: 70 | H26: 50 | I26: 260 | J26: 325 | K26: 90 | L26: 80 | M26: N/A | N26: 2 | P26: 1940 | Q26: Bondex
B27: TNC | C27: Puebla | D27: Laemchabang | E27: MANZANILLO | F27: CIF | G27: 70 | H27: 50 | I27: 260 | J27: 250 | K27: 90 | L27: 80 | M27: N/A | N27: 1 | P27: 1940 | Q27: Bondex
B28: Creative Components | C28: Saltillo | D28: Nhava Sheva | E28: MANZANILLO | F28: CIF | G28: 70 | H28: 80 | I28: 160 | J28: 1000 | K28: 50 | L28: 75 | M28: N/A | N28: 2 | O28: 50-55 days | P28: 2800 | Q28: Bondex
B29: WOORY | C29: Saltillo | D29: INCHEON | E29: MANZANILLO | F29: CIF | G29: 70 | H29: 35 | I29: 145 | J29: 350 | K29: 150 | L29: 50 | M29: N/A | N29: 1 | O29: 25-30 days | P29: 2340 | Q29: Bondex
B30: Jiangsu Chao Li | C30: Puebla | D30: SHA | E30: MANZANILLO | F30: FOB | G30: 70 | H30: 70 | I30: 145 | J30: 550 | K30: 15 | L30: 60 | M30: N/A | N30: 2 | O30: 18-23 days | P30: 1840 | Q30: Bondex
B31: Yangzhou RSL | C31: Puebla | D31: SHA | E31: MANZANILLO | F31: CIF | G31: 70 | H31: 70 | I31: 145 | J31: 550 | K31: 15 | L31: 60 | M31: N/A | N31: 1 | P31: 1840 | Q31: Bondex
B32: Zhejiang Yuansheng | C32: Puebla | D32: SHA | E32: MANZANILLO | F32: CIF | G32: 70 | H32: 70 | I32: 145 | J32: 550 | K32: 15 | L32: 60 | M32: N/A | N32: 0.5 | P32: 1840 | Q32: Bondex
B33: Shanghai Huafon Coil | C33: Puebla | D33: SHA | E33: MANZANILLO | F33: CIF | G33: 70 | H33: 70 | I33: 145 | J33: 250 | K33: 15 | L33: 60 | M33: N/A | N33: 2 | P33: 1840 | Q33: Bondex
B34: Dalian ABIC | C34: Puebla | D34: SHA | E34: MANZANILLO | F34: CIF | G34: 70 | H34: 70 | I34: 145 | J34: 200 | K34: 15 | L34: 50 | M34: N/A | N34: 2 | P34: 1840 | Q34: Bondex
B35: Chongqing Boling | C35: Puebla | D35: SHA | E35: MANZANILLO | F35: CIF | G35: 70 | H35: 70 | I35: 145 | J35: 1550 | K35: 15 | L35: 60 | M35: N/A | N35: 0.5 | P35: 1840 | Q35: Bondex
B36: AITD | C36: Saltillo | D36: SHA | E36: MANZANILLO | F36: CIF | G36: 70 | H36: 70 | I36: 145 | J36: 350 | K36: 15 | L36: 60 | M36: N/A | N36: 1 | P36: 1840 | Q36: Bondex
B37: AITD-Spring | C37: Saltillo | D37: Tianjin | E37: MANZANILLO | F37: CIF | G37: 70 | H37: 70 | I37: 145 | J37: 200 | K37: 15 | L37: 50 | M37: N/A | N37: 1 | P37: 2150 | Q37: Bondex
B38: Wuhu Bokang | C38: Saltillo | D38: SHA | E38: MANZANILLO | F38: FOB | G38: 70 | H38: 70 | I38: 145 | J38: 50 | K38: 15 | L38: 60 | M38: N/A | N38: 1 | P38: 1840 | Q38: Bondex
B39: Zhejiang Yida | C39: Puebla | D39: SHA | E39: MANZANILLO | F39: CIF | G39: 70 | H39: 70 | I39: 145 | J39: 550 | K39: 15 | L39: 60 | M39: N/A | N39: 1 | P39: 1840 | Q39: Bondex
B40: Nanjing PMC | C40: Saltillo | D40: SHA | E40: MANZANILLO | F40: CIF | G40: 70 | H40: 70 | I40: 145 | J40: 550 | K40: 15 | L40: 60 | M40: N/A | N40: 2 | P40: 1840 | Q40: Bondex
B41: Changsha Shenda | C41: Saltillo | D41: SHA | E41: MANZANILLO | F41: CIF | G41: 70 | H41: 70 | I41: 145 | J41: 1500 | K41: 15 | L41: 60 | M41: N/A | N41: 2 | P41: 1840 | Q41: Bondex

Sheet _Backup_2月
A1: Lane | B1: Consignor | C1: Consignee | D1: POL | E1: POD | F1: Incoterm | G1: HQ40 Demand | H1: Booking | I1: Doc | J1: THC | K1: Loading | L1: Customs | M1: B/L | N1: Local Subtotal | O1: Dest Subtotal | P1: Sea Freight | Q1: Transit Time | R1: Total (USD) | S1: Winning Forwarder

Sheet _Backup_3月
H1: 发货人本地费用明细 | N1: 收货人本地费用
C2: Consignor | D2: Consignee | E2: Port of Origin | F2: Port of Destination | G2: Incoterm | H2: Booking Fee 订舱费 | I2: Documentation Fee 文件费 | J2: THC - Terminal Handling Charge码头操作费 | K2: Loading Fee 提货费 | L2: Customs Declaration Fee 报关费 | M2: B/L Fee 提单正本，电放操作费 | N2: Destination local cost | O2: March HQ40 Demand | P2: D2D Transit Time (Normal vessel) | Q2: Sea Freight Cost(Normal Vessel) | R2: Forwarder | S2: Basic requirements | T2: 竞标价为 after-tax
A3: SHA-Izmit | B3: AI-Turkey | C3: AINT- 666 Wenchang Road, Tongzhou District, Nantong City | D3: AIR INTERNATIONAL TERMAL SİSTEMLERİ A. Ş.ESENTEPE MAH. ALİ KAYA SK. POLAT PLAZA B BLOK NO: 1/1İÇ KAPI NO:69 ŞİŞLİ/İSTANBUL | E3: SHA | F3: Izmit | G3: DAP | H3: 70 | I3: 70 | J3: 140 | K3: 400 | L3: 10 | M3: 70 | N3: 950 | O3: 18 | P3: 10-12 wks | Q3: 3726.6667 | R3: CW11 Holiton； CW12 Bestunit； CW13 BU 4 Ho 3； | S3: 1. Online tracking system 2. Only accept railway transportation from SAI to SHA port 3. Transit time should be between 8-10 weeks (any additional cost will be borne by the forwarder if vessel delayed more than 2 weeks) 4. No Israel vessels | T3: 分开招标
A4: SHA-Izmit | C4: SAI-No. 3 Gaobao Lake East Road, Yubei District, Chongqing | D4: AIR INTERNATIONAL TERMAL SİSTEMLERİ A. Ş.ESENTEPE MAH. ALİ KAYA SK. POLAT PLAZA B BLOK NO: 1/1İÇ KAPI NO:69 ŞİŞLİ/İSTANBUL | E4: SHA | F4: Izmit | G4: EXW | H4: 70 | I4: 70 | J4: 170 | K4: 250 | L4: 50 | M4: 50 | N4: 950 | O4: 4 | P4: 11-13 wks | Q4: 5326.6667 | R4: CW11 Bestunit； CW12 Bestunit； CW13 Bestunit；
A6: SHA-HOU | B6: AIUS TOC | C6: AINT- 666 Wenchang Road, Tongzhou District, Nantong City | D6: Air International Thermal System-c/o GTZ WAREHOUSE LLC-662 SOUTH 33rd STREET, BUILDING -J, McALLEN, TX 78503 | E6: SHA | F6: HOU | G6: EXW | H6: 70 | I6: 70 | J6: 140 | K6: 400 | L6: 10 | M6: 70 | N6: 2685 | O6: 1 | P6: 8-10 wks | Q6: 2350 | R6: Bondex | S6: 1. Online tracking system (Mandatory requirement) 2. Experienced with 'Foreign trade zone' application process
A7: SHA-Detroit | C7: AISH-108 Chunguang Road, Minhang District, Shanghai | D7: Air International Thermal Systems-c/o FTZ METRO WAREHOUSE-1200 E. McNICHOLS RD, HIGHLAND PARK, MI 48203. | E7: SHA | F7: Detroit | G7: EXW | H7: 70 | I7: 70 | J7: 140 | K7: 250 | L7: 10 | M7: 70 | N7: 885 | O7: 1 | Q7: 3750 | R7: Bondex
A8: Laem Chabang-Savanna | B8: AIUS Baxter | C8: Air International Thermal Systems (Thailand) Ltd. (Head Office) 500/46 Moo 3, WHA Eastern Seaboard Industrial Estate 1 Tambol Tasit, Amphur Pluak Daeng, Rayong 21140 Thailand | D8: Air International Thermal Systems 466 Baxter Lane Winchester ,TN,USA ,37398 | E8: Laem Chabang | F8: Savanna | G8: DAP | H8: 70 | I8: 70 | J8: 140 | K8: 300 | L8: 30 | M8: 70 | N8: 2785 | O8: 3 | P8: 8-10 wks | Q8: 2200 | R8: Freetrans | S8: No need to do the customs clearance and pre-pay duties anymore | T8: 固定清关broker：Rohlig
A9: Nhava Sheva-Savanna | C9: Divine & Creative from India | D9: Air International Thermal Systems 466 Baxter Lane Winchester ,TN,USA ,37398 | E9: Nhava Sheva | F9: Savanna | G9: DAP | H9: 70 | I9: 80 | J9: 160 | K9: 1000 | L9: 50 | M9: 75 | N9: 2785 | O9: 3 | P9: 7-9 wks | Q9: 2193 | R9: Freetrans
A10: SHA-Savanna | C10: AINT- 666 Wenchang Road, Tongzhou District, Nantong City | D10: Air International Thermal Systems 466 Baxter Lane Winchester ,TN,USA ,37398 | E10: SHA | F10: Savanna | G10: DAP | H10: 70 | I10: 70 | J10: 140 | K10: 400 | L10: 10 | M10: 70 | N10: 2785 | O10: 3 | P10: 6-8 wks | Q10: 2193 | R10: Freetrans
A12: SHA-Hamburg | B12: AISK | C12: AINT- 666 Wenchang Road, Tongzhou District, Nantong City,China | D12: Air International Thermal (Slovakia) s.r.o. Prologis Park Nitra, DC3 Cez panske 4289/9 949 01 Nitra Slovakia | E12: SHA | F12: Hamburg | G12: EXW | H12: 70 | I12: 70 | J12: 140 | K12: 400 | L12: 10 | M12: 70 | N12: 2200 | O12: 1 | P12: 8-9 wks | Q12: 1800 | R12: Bestunit | S12: 1. Online tracking system (Mandatory required by Ford) 2. Prefer Port of Hamburg rather than Koper, which provides better service | T12: 当地自行招标 国内仅供对比参考
A13: Nhava Sheva-Hamburg | C13: Divine tooling | D13: Air International Thermal (Slovakia) s.r.o. Prologis Park Nitra, DC3 Cez panske 4289/9 949 01 Nitra Slovakia | E13: Nhava Sheva | F13: Hamburg | G13: EXW | H13: 70 | I13: 70 | J13: 140 | K13: 300 | L13: 250 | M13: 70 | N13: 2200 | O13: 2 | P13: 8-10 wks | Q13: 2100 | R13: KF
A14: Bangkok-Hamburg | C14: Delta Electronics | D14: Air International Thermal (Slovakia) s.r.o. Prologis Park Nitra, DC3 Cez panske 4289/9 949 01 Nitra Slovakia | E14: Bangkok | F14: Hamburg | G14: EXW | H14: 70 | I14: 70 | J14: 140 | K14: 300 | L14: 250 | M14: 70 | N14: 2200 | O14: 0.5 | P14: 9-10 wks | Q14: 2400 | R14: KF
A16: SHA-Laemchabang | B16: AITH | C16: Air International (Shanghai) Co.,Ltd. No. 108 Chun guang Road, XinZhuang Industrial Zone Minhang, Shanghai P.R. China 201108 | D16: Air International Thermal Systems (Thailand) Ltd. 41/17,18,19 MOO 8,T.BOWIN,A.SRIRACHA,CHONBURI,20230 THAILAND | E16: SHA | F16: Laemchabang | G16: EXW | H16: 70 | I16: 70 | J16: 140 | K16: 250 | L16: 10 | M16: 70 | N16: 800 | O16: 1 | P16: 15-20 days | Q16: 650 | R16: Bondex/Bestunit | S16: 1. Only accept 1 local broker 2. No significant bad history (Delay, waiting time too long, etc) | T16: 当地自行招标 国内仅供对比参考
A17: SHA-Laemchabang | C17: Shanghai Huafon Aluminium Corporati 1111# yuegong road Jinshan district Shanghai Zip Code: 201506 | D17: Air International Thermal Systems (Thailand) Ltd. 500/46 Moo 3, WHA Eastern Seaboard Industrial Estate 1, T. Tasit, A. Pluekdaeng, Rayong 21140 | E17: SHA | F17: Laemchabang | G17: EXW | H17: 70 | I17: 70 | J17: 140 | K17: 250 | L17: 10 | M17: 70 | N17: 800 | O17: 3 | P17: 15-20 days | Q17: 650 | R17: Bondex/Bestunit
A18: Tianjin-Laemchabang | C18: Hyo Seong Electric (Toanjin) Co.,Ltd No.99, Xi San Dao, Tianjin Airport Industrial Park, TPFTZ, Tianjin, P.R. China | D18: Air International Thermal Systems (Thailand) Ltd. 41/17,18,19 MOO 8,T.BOWIN,A.SRIRACHA,CHONBURI,20230 THAILAND | E18: Tianjin | F18: Laemchabang | G18: EXW | H18: 70 | I18: 70 | J18: 140 | K18: 420 | L18: 30 | M18: 70 | N18: 800 | O18: 0.5 | P18: 18-23 days | Q18: 600 | R18: Bondex
A19: Dubai-Laemchabang | C19: OSE Industries LLC. Dubai Industrial Park, Office#103, First Floor, Building 1, Dubai Industrial City, Dubai, UAE, Post Box 126344 | D19: Air International Thermal Systems (Thailand) Ltd. 500/46 Moo 3, WHA Eastern Seaboard Industrial Estate 1, T. Tasit, A. Pluekdaeng, Rayong 21140 | E19: Dubai | F19: Laemchabang | G19: EXW | H19: 70 | I19: 70 | J19: 140 | K19: 420 | L19: 30 | M19: 70 | N19: 800 | O19: 0.5 | P19: 20-25 days | Q19: 600 | R19: KF
A20: Laemchabang-Hamburg | C20: Air International Thermal Systems (Thailand) Ltd. 500/46 Moo 3, WHA Eastern Seaboard Industrial Estate 1, T. Tasit, A. Pluekdaeng, Rayong 21140 | D20: Air International Thermal (Slovakia) s.r.o. Prologis Park Nitra, DC3 Cez panske 4289/9 949 01 Nitra Slovakia | E20: Laemchabang | F20: Hamburg | G20: DDP | H20: 70 | I20: 70 | J20: 140 | K20: 300 | L20: 30 | M20: 70 | N20: 2200 | O20: 6 | P20: 9-10 wks | Q20: 3300 | R20: Bondex
A22: Bangkok-SHA | B22: AISH | C22: DELTA ELECTRONICS (THAILAND) PUBLIC COMPANY LIMITED 111 MOO 9,BANGNA-TRAD RD.,TAMBOL BANGWUA AMPHUR BANGPAKONG CHACHOENGSAO, 24180 THAILAND | D22: AINT- 666 Wenchang Road, Tongzhou District, Nantong City | E22: Bangkok | F22: SHA | G22: EXW | H22: 70 | I22: 50 | J22: 260 | K22: 325 | L22: 90 | M22: 80 | N22: 600 | O22: 1 | P22: 15-20 days | Q22: 1 | R22: Superchain | S22: 1. Delta transit time should be within 20 days after pickup. 2. Woory transit time should be within 10 days after pickup. 3. Any additional cost will be borne by the forwarder if vessel delayed more than 7 days. 4. Pre-classification HS CODE service Woory改成20GP小柜子
A23: Incheon-SHA | C23: Woory Industrial Co.,Ltd #531, Jigok-dong, Kihung-gu Yongin-city, Kyonggi-Do, Korea | D23: AINT- 666 Wenchang Road, Tongzhou District, Nantong City | E23: INCHEON | F23: SHA | G23: EXW | H23: 50 | I23: 35 | J23: 125 | K23: 280 | L23: 150 | M23: 50 | N23: 600 | O23: 2 | P23: 5-10 days | Q23: 1 | R23: Superchain
P24: D2D Transit Time (Express vessel) | Q24: Sea Freight Cost(Express Vessel) | R24: Forwarder
A25: Laemchabang-Manzanillo(Normal Vessel) | B25: AIMX | C25: AITH | D25: Puebla + Saltillo | E25: Laemchabang | F25: MANZANILLO | G25: CIF | H25: 70 | I25: 50 | J25: 260 | K25: 250 | L25: 90 | M25: 80 | N25: N/A | O25: 9 | P25: 35-45 days | Q25: 2119.5 | R25: KF | S25: 1. MBL must consignee directly to Forwarder and assignee all the shipments with FW. 2. As the service is D2P, the MBL must be consigned to Local FW (TRANSLAQ). 3. Guarantee letter with every FW to avoid payment of guarantees. AIMX will not pay any guarantee. 4. The FW must finance the local charges at destination or assign a local forwarder. 5. We need 21 free days of demurrages 6. Send Pre-alerts and documents once the vessel departs (Invoice, PL, BL, Freight cost, EIR). If the arrival notification is sent 1 week before the arrival of vessel, the additional costs will be charged directly to the Forwarder (Storages and demurrages) 7. Do Not ship our load in a reefer container, because the cost of guarantees is higher than the regular containers. 8. Assignee containers in good conditions to avoid payment of damage´s containers. 9. Always send to us the EIR´S and pictures of container´s conditions that you place in origin with each supplier. 10. Able to combine light and heavy pallets from different suppliers into one container 11. SHA - MANZANILLO line only use express vessels and appointed shipping companies (Cosco, MSC, HPL, MSK, CMA) | T25: 固定清关broker：Enciso
A26: Bangkok-Manzanillo(Normal Vessel) | C26: DETLA | D26: Saltillo | E26: Bangkok | F26: MANZANILLO | G26: CIF | H26: 70 | I26: 50 | J26: 260 | K26: 325 | L26: 90 | M26: 80 | N26: N/A | O26: 2 | Q26: 2000 | R26: KF
A27: Laemchabang-Manzanillo(Normal Vessel) | C27: TNC | D27: Puebla | E27: Laemchabang | F27: MANZANILLO | G27: CIF | H27: 70 | I27: 50 | J27: 260 | K27: 250 | L27: 90 | M27: 80 | N27: N/A | O27: 1 | Q27: 2239 | R27: KF
A28: Nhava Sheva-Manzanillo(Normal Vessel) | C28: Creative Components | D28: Saltillo | E28: Nhava Sheva | F28: MANZANILLO | G28: CIF | H28: 70 | I28: 80 | J28: 160 | K28: 1000 | L28: 50 | M28: 75 | N28: N/A | O28: 2 | P28: 50-55 days | Q28: 2790 | R28: KF
A29: Incheon-Manzanillo(Normal Vessel) | C29: WOORY | D29: Saltillo | E29: INCHEON | F29: MANZANILLO | G29: CIF | H29: 70 | I29: 35 | J29: 145 | K29: 350 | L29: 150 | M29: 50 | N29: N/A | O29: 1 | P29: 25-30 days | Q29: 3400 | R29: KF
A30: SHA-Manzanillo(Normal Vessel) | C30: Jiangsu Chao Li | D30: Puebla | E30: SHA | F30: MANZANILLO | G30: FOB | H30: 70 | I30: 70 | J30: 145 | K30: 550 | L30: 15 | M30: 60 | N30: N/A | O30: 2 | P30: 18-23 days | Q30: 1748 | R30: Freetrans
A31: SHA-Manzanillo(Normal Vessel) | C31: Yangzhou RSL | D31: Puebla | E31: SHA | F31: MANZANILLO | G31: CIF | H31: 70 | I31: 70 | J31: 145 | K31: 550 | L31: 15 | M31: 60 | N31: N/A | O31: 1 | Q31: 1749 | R31: Freetrans
A32: SHA-Manzanillo(Normal Vessel) | C32: Zhejiang Yuansheng | D32: Puebla | E32: SHA | F32: MANZANILLO | G32: CIF | H32: 70 | I32: 70 | J32: 145 | K32: 550 | L32: 15 | M32: 60 | N32: N/A | O32: 0.5 | Q32: 1748 | R32: Freetrans
A33: SHA-Manzanillo(Normal Vessel) | C33: Shanghai Huafon Coil | D33: Puebla | E33: SHA | F33: MANZANILLO | G33: CIF | H33: 70 | I33: 70 | J33: 145 | K33: 250 | L33: 15 | M33: 60 | N33: N/A | O33: 2 | Q33: 1750 | R33: Freetrans
A34: SHA-Manzanillo(Normal Vessel) | C34: Dalian ABIC | D34: Puebla | E34: SHA | F34: MANZANILLO | G34: CIF | H34: 70 | I34: 70 | J34: 145 | K34: 200 | L34: 15 | M34: 50 | N34: N/A | O34: 2 | Q34: 1750 | R34: Freetrans
A35: SHA-Manzanillo(Normal Vessel) | C35: Chongqing Boling | D35: Puebla | E35: SHA | F35: MANZANILLO | G35: CIF | H35: 70 | I35: 70 | J35: 145 | K35: 1550 | L35: 15 | M35: 60 | N35: N/A | O35: 0.5 | Q35: 1750 | R35: Freetrans
A36: SHA-Manzanillo(Normal Vessel) | C36: AITD | D36: Saltillo | E36: SHA | F36: MANZANILLO | G36: CIF | H36: 70 | I36: 70 | J36: 145 | K36: 350 | L36: 15 | M36: 60 | N36: N/A | O36: 1 | Q36: 1750 | R36: Freetrans
A37: Tianjin-Manzanillo(Normal Vessel) | C37: AITD-Spring | D37: Saltillo | E37: Tianjin | F37: MANZANILLO | G37: CIF | H37: 70 | I37: 70 | J37: 145 | K37: 200 | L37: 15 | M37: 50 | N37: N/A | O37: 1 | Q37: 1750 | R37: Freetrans
A38: SHA-Manzanillo(Normal Vessel) | C38: Wuhu Bokang | D38: Saltillo | E38: SHA | F38: MANZANILLO | G38: FOB | H38: 70 | I38: 70 | J38: 145 | K38: 50 | L38: 15 | M38: 60 | N38: N/A | O38: 1 | Q38: 1750 | R38: Freetrans
A39: SHA-Manzanillo(Normal Vessel) | C39: Zhejiang Yida | D39: Puebla | E39: SHA | F39: MANZANILLO | G39: CIF | H39: 70 | I39: 70 | J39: 145 | K39: 550 | L39: 15 | M39: 60 | N39: N/A | O39: 1 | Q39: 1750 | R39: Freetrans
A40: SHA-Manzanillo(Normal Vessel) | C40: Nanjing PMC | D40: Saltillo | E40: SHA | F40: MANZANILLO | G40: CIF | H40: 70 | I40: 70 | J40: 145 | K40: 550 | L40: 15 | M40: 60 | N40: N/A | O40: 2 | Q40: 1750 | R40: Freetrans
A41: SHA-Manzanillo(Normal Vessel) | C41: Changsha Shenda | D41: Saltillo | E41: SHA | F41: MANZANILLO | G41: CIF | H41: 70 | I41: 70 | J41: 145 | K41: 1500 | L41: 15 | M41: 60 | N41: N/A | O41: 2 | Q41: 1750 | R41: Freetrans
A43: Laemchabang-Manzanillo(Express Vessel)
A44: Bangkok-Manzanillo(Express Vessel)
A45: Laemchabang-Manzanillo(Express Vessel)
A46: Incheon-Manzanillo(Express Vessel)
A47: SHA-Manzanillo(Express Vessel)
A48: SHA-Manzanillo(Express Vessel)
A49: SHA-Manzanillo(Express Vessel)
A50: SHA-Manzanillo(Express Vessel)
A51: SHA-Manzanillo(Express Vessel)
A52: SHA-Manzanillo(Express Vessel)
A53: SHA-Manzanillo(Express Vessel)
A54: Tianjin-Manzanillo(Express Vessel)
... A58: SHA-Manzanillo(Express Vessel)

Sheet _Backup_9月
H1: 发货人本地费用明细 | N1: 收货人本地费用 | O1: 海运费 | P1: 货代
B2: Consignor | C2: Consignee | D2: Port of Origin | E2: Port of Destination | F2: Incoterm | G2: Monthly HQ40 Demand | H2: Booking Fee 订舱费 | I2: Documentation Fee 文件费 | J2: THC - Terminal Handling Charge码头操作费 | K2: Loading Fee 提货费 | L2: Customs Declaration Fee 报关费 | M2: B/L Fee 提单正本，电放操作费 | N2: Destination local cost | O2: Sea Freight Cost | P2: Forwarder | Q2: Basic requirements | R2: Local Price Door to door
A3: AI-Turkey | B3: AINT- 666 Wenchang Road, Tongzhou District, Nantong City | C3: AIR INTERNATIONAL TERMAL SİSTEMLERİ A. Ş.ESENTEPE MAH. ALİ KAYA SK. POLAT PLAZA B BLOK NO: 1/1İÇ KAPI NO:69 ŞİŞLİ/İSTANBUL | D3: SHA | E3: Izmit | F3: DAP | G3: 22 | H3: 70 | I3: 70 | J3: 140 | K3: 400 | L3: 10 | M3: 70 | N3: 950 | O3: 2800 | P3: 合力通 | Q3: 1. Online tracking system 2. Only accept railway transportation from SAI to SHA port 3. Transit time should be between 8-10 weeks (any additional cost will be borne by the forwarder if vessel delayed more than 2 weeks)
B4: SAI-No. 3 Gaobao Lake East Road, Yubei District, Chongqing | C4: AIR INTERNATIONAL TERMAL SİSTEMLERİ A. Ş.ESENTEPE MAH. ALİ KAYA SK. POLAT PLAZA B BLOK NO: 1/1İÇ KAPI NO:69 ŞİŞLİ/İSTANBUL | D4: SHA | E4: Izmit | F4: EXW | G4: 4 | H4: 70 | I4: 70 | J4: 140 | K4: 200 | L4: 20 | M4: 50 | N4: 950 | O4: 4294 | P4: Freetrans
